Workbook
Name BoxPlot: "BoxPlot"
Name Bubble: "Bubble"
Name Candlestick: "Candlestick"
Name Chart: "Chart"
Name ChartImage: "ChartImage"
Name ColumnRange: "ColumnRange"
Name Dumbbell: "Dumbbell"
Name Heatmap: "Heatmap"
Name Histogram: "Histogram"
Name Map: "Map"
Name OHLC: "OHLC"
Name PieChart: "PieChart"
Name Scatter: "Scatter"
Name Series: "Series"
Name Stripe: "Stripe"
Name Table: "Table"
Name TM1REBUILDOPTION: 1
Name TreeMap: "TreeMap"
Name Type: #REF!
Name Type: #REF!
Name Waterfall: "Waterfall"

Sheet ss
D1: Full | E1: Recent | F1: Calibrated | J1: Full | K1: Recent | L1: Calibrated
B2: omegacv | D2: =AVERAGE('SA data'!B42:B137)/AVERAGE('SA data'!$A$42:$A$137) -> 0.53627456 | E2: =AVERAGE('SA data'!B78:B137)/AVERAGE('SA data'!$A$78:$A$137) -> 0.56480372 | F2: 0.6 | I2: z | J2: =D7*D51^((1-D56)/D56)*D54 -> 2.8991526 | K2: =E7*E51^((1-E56)/E56)*E54 -> 2.9408688 | L2: =F7*F51^((1-F56)/F56)*F54 -> 2.7870006 | O2: 2.38
B3: omegaiv | D3: =1-D2-D4-D13-D5+D6 -> 0.18913384 | E3: =1-E2-E4-E13-E5+E6 -> 0.19403025 | F3: =1-F2-F4-F13-F5+F6 -> 0.18 | I3: v | J3: =J2/D7 -> 1.7612183 | K3: =K2/E7 -> 1.8016794 | L3: =L2/F7 -> 1.6890913 | O3: =8*9-6 -> 66
B4: omegagv | D4: =AVERAGE('SA data'!C42:C137)/AVERAGE('SA data'!$A$42:$A$137) -> 0.12620883 | E4: =AVERAGE('SA data'!C78:C137)/AVERAGE('SA data'!$A$78:$A$137) -> 0.12970996 | F4: 0.13 | I4: c | J4: =D2*J3 -> 0.94449656 | K4: =E2*K3 -> 1.0175952 | L4: =F2*L3 -> 1.0134548 | O4: =O2/((O3)^(1/2)) -> 0.29295775 | R4: # omegacgv = 0.10; //fed gov consumption
B5: omegaxv | D5: =AVERAGE('SA data'!E42:E137)/AVERAGE('SA data'!$A$42:$A$137) -> 0.74877771 | E5: =AVERAGE('SA data'!E78:E137)/AVERAGE('SA data'!$A$78:$A$137) -> 0.70384792 | F5: 0.7 | I5: i | J5: =D3*J3 -> 0.33310598 | K5: =ss!E3*K3 -> 0.34958031 | L5: =F3*L3 -> 0.30403643 | R5: # omegatrv = 0.045; // government transfers
B6: omegamv | D6: =AVERAGE('SA data'!F42:F137)/AVERAGE('SA data'!$A$42:$A$137) -> 0.64610633 | E6: =AVERAGE('SA data'!F78:F137)/AVERAGE('SA data'!$A$78:$A$137) -> 0.63229309 | F6: 0.65 | I6: io | J6: =D13*J3 -> 0.080507722 | K6: =E13*K3 -> 0.071889256 | L6: =F13*L3 -> 0.067563651 | R6: # omegabv = 2.5; // government debt-to-GDP ratio
B7: omegazv | D7: =D2+D3+D13+D4+D5 -> 1.6461063 | E7: =E2+E3+E13+E4+E5 -> 1.6322931 | F7: =F2+F3+F13+F4+F5 -> 1.65 | I7: g | J7: =D4*J3 -> 0.2222813 | K7: =E4*K3 -> 0.23369576 | L7: =F4*L3 -> 0.21958187 | O7: =13333*5 -> 66665 | R7: # omegarev = omegacgv + omegaigv + omegatrv + (r - 1)*omegabv; // required steady-state revenue
B8: omegavz | D8: =1/D7 -> 0.60749417 | E8: =1/E7 -> 0.61263507 | F8: =1/F7 -> 0.60606061 | I8: x | J8: =D5*J3 -> 1.318761 | K8: =E5*K3 -> 1.2681083 | L8: =F5*L3 -> 1.1823639 | R8: # omegatxv = 0.75 * omegarev; // tax revenue
I9: m | J9: =D6*J3 -> 1.1379343 | K9: =E6*K3 -> 1.1391894 | L9: =F6*L3 -> 1.0979093 | R9: # omegatxh = (1/3) * omegatxv;
I10: k | J10: =D51*J3 -> 11.103533 | K10: =E51*K3 -> 11.652677 | L10: =F51*L3 -> 10.134548 | R10: # omegatxf = (2/3) * omegatxv;
I11: w | J11: =D55*J3 -> 1.1741455 | K11: =E55*K3 -> 1.2011196 | L11: =F55*L3 -> 1.1260609 | R11: # omegantxv = 0.25 * omegarev; // non-tax revenue
B12: omegacgv | D12: =AVERAGE('SA data'!I42:I137)/AVERAGE('SA data'!$A$42:$A$137) -> 0.11441127 | E12: =AVERAGE('SA data'!I78:I137)/AVERAGE('SA data'!$A$78:$A$137) -> 0.1116033 | F12: 0.1 | I12: rev | J12: =D26*J3 -> 0.38708261 | K12: =E26*K3 -> 0.3908848 | L12: =F26*L3 -> 0.34626371
B13: omegaigv | D13: =AVERAGE('SA data'!J42:J137)/AVERAGE('SA data'!$A$42:$A$137) -> 0.045711382 | E13: =AVERAGE('SA data'!J78:J137)/AVERAGE('SA data'!$A$78:$A$137) -> 0.039901248 | F13: 0.04 | I13: tx | J13: =D27*J3 -> 0.29031196 | K13: =E27*K3 -> 0.2931636 | L13: =F27*L3 -> 0.25969779
B14: omegatrv | D14: =AVERAGE('SA data'!K2:K137)/AVERAGE('SA data'!$A$2:$A$137) -> 0.037304253 | E14: =AVERAGE('SA data'!K78:K137)/AVERAGE('SA data'!$A$78:$A$137) -> 0.0439511 | F14: 0.045 | I14: txh | J14: =D29*J3 -> 0.096770652 | K14: =E29*K3 -> 0.097721201 | L14: =F29*L3 -> 0.086565928
B15: omegaintv | D15: =AVERAGE('SA data'!L2:L137)/AVERAGE('SA data'!$A$2:$A$137) -> 0.022354266 | E15: =AVERAGE('SA data'!L78:L137)/AVERAGE('SA data'!$A$78:$A$137) -> 0.021500157 | F15: 0.02 | I15: txf | J15: =D30*J3 -> 0.1935413 | K15: =E30*K3 -> 0.1954424 | L15: =F30*L3 -> 0.17313186
B16: omegabv | D16: =D15/(D49-1) -> 2.5483863 | E16: =E15/(E49-1) -> 2.4510179 | F16: =F15/(F49-1) -> 2.66 | G16: =F16/4 -> 0.665 | I16: ntx | J16: =D28*J3 -> 0.096770652 | K16: =E28*K3 -> 0.097721201 | L16: =F28*L3 -> 0.086565928 | Q16: =T16/$U$19 -> #DIV/0! | R16: omegacgv | T16: ='SA data'!I167 -> 0
B17: omegarevv | D17: =D18+D21 -> 0.18366004 | E17: =E18+E21 -> 0.17335321 | F17: =F12+F13+F14+F15 -> 0.205 | I17: tr | J17: =D14*J3 -> 0.065700932 | K17: =E14*K3 -> 0.079185791 | L17: =F14*L3 -> 0.076009108 | Q17: =T17/$U$19 -> #DIV/0! | R17: omegaigv | T17: ='SA data'!J167 -> 0
B18: omegatxv | D18: =D19+D20 -> 0.13565498 | E18: =E19+E20 -> 0.12685146 | F18: =0.75*F17 -> 0.15375 | I18: b | J18: =ss!D16*J3 -> 4.4882645 | K18: =ss!E16*K3 -> 4.4159485 | L18: =F16*L3 -> 4.4929828 | Q18: =T18/$U$19 -> #DIV/0! | R18: omegatrv | T18: ='SA data'!K167 -> 0
B19: omegatxhv | D19: =AVERAGE('SA data'!O2:O137)/AVERAGE('SA data'!$A$2:$A$137) -> 0.040917784 | E19: =AVERAGE('SA data'!O78:O137)/AVERAGE('SA data'!$A$78:$A$137) -> 0.041105824 | F19: =(1/3)*F18 -> 0.05125 | I19: cr | K19: =E32*K3 -> 8.0374015 | L19: =F32*L3 -> 7.5164562 | Q19: =T19/$U$19 -> #DIV/0! | R19: omegaintv | T19: ='SA data'!L167 -> 0 | U19: =T16+T17+T18+T19 -> 0 | W19: omegabv | X19: =T19/(F49-1) -> 0 | Y19: =X19/4 -> 0
B20: omegatxfv | D20: =AVERAGE('SA data'!P2:P137)/AVERAGE('SA data'!$A$2:$A$137) -> 0.094737194 | E20: =AVERAGE('SA data'!P78:P137)/AVERAGE('SA data'!$A$78:$A$137) -> 0.085745631 | F20: =(2/3)*F18 -> 0.1025 | I20: crh | K20: =ss!E33*K3 -> 1.445097 | L20: =F33*L3 -> 1.351273
B21: omegantxv | D21: =AVERAGE('SA data'!Q2:Q137)/AVERAGE('SA data'!$A$2:$A$137) -> 0.048005061 | E21: =AVERAGE('SA data'!Q78:Q137)/AVERAGE('SA data'!$A$78:$A$137) -> 0.046501756 | F21: =0.25*F17 -> 0.05125 | I21: crf | K21: =ss!E34*K3 -> 6.5923045 | L21: =F34*L3 -> 6.1651832 | Q21: =V21/$U$19 -> #DIV/0! | R21: omegarev | T21: =T22+T25 -> 0 | V21: =U19 -> 0
I22: lendg | K22: =ss!E35*K3 -> 1.0702495 | L22: =F35*L3 -> 1.0134548 | Q22: =V22/$U$19 -> #DIV/0! | R22: omegatxv | T22: =T23+T24 -> 0 | V22: =T22/T21*V21 -> #DIV/0!
I23: oa | K23: =ss!E36*K3 -> 4.4979798 | L23: =F36*L3 -> 4.2227282 | Q23: =V23/$U$19 -> #DIV/0! | R23: omegatxhv | T23: ='SA data'!O167 -> 0 | V23: =T23/T22*V22 -> #DIV/0!
I24: nw | K24: =ss!E37*K3 -> 1.4515888 | L24: =F37*L3 -> 1.351273 | Q24: =V24/$U$19 -> #DIV/0! | R24: omegatxfv | T24: ='SA data'!P167 -> 0 | V24: =T24/T22*V22 -> #DIV/0!
I25: loan | K25: =ss!E38*K3 -> 0.4972363 | L25: =F38*L3 -> 0.50672739 | Q25: =V25/$U$19 -> #DIV/0! | R25: omegantxv | T25: ='SA data'!Q167 -> 0 | U25: =T22+T25 -> 0 | V25: =T25/T21*V21 -> #DIV/0!
B26: omegarevv | D26: =ss!D12+D13+D14+D15 -> 0.21978117 | E26: =E12+E13+E14+E15 -> 0.21695581 | F26: =F12+F13+F14+F15 -> 0.205 | I26: depp | K26: =ss!E39*K3 -> 9.7400643 | L26: =F39*L3 -> 9.1210929 | U26: =U25-U19 -> 0
B27: omegatxv | D27: =0.75*D26 -> 0.16483588 | E27: =0.75*E26 -> 0.16271686 | F27: =0.75*F26 -> 0.15375 | I27: depg | K27: =E41*K3 -> 0 | L27: =F41*L3 -> 0
B28: omegantxv | D28: =0.25*D26 -> 0.054945292 | E28: =0.25*E26 -> 0.054238952 | F28: =0.25*F26 -> 0.05125 | I28: cash | K28: =E42*K3 -> 0 | L28: =F42*L3 -> 0
B29: omegatxhv | D29: =(1/3)*D27 -> 0.054945292 | E29: =(1/3)*E27 -> 0.054238952 | F29: =(1/3)*F27 -> 0.05125 | I29: ol | K29: =ss!E40*K3 -> 1.9167413 | L29: =F40*L3 -> 1.7735459
B30: omegatxfv | D30: =(2/3)*D27 -> 0.10989058 | E30: =(2/3)*E27 -> 0.1084779 | F30: =(2/3)*F27 -> 0.1025 | I30: ms | K30: =E44*K3 -> 1.8061949 | L30: =F44*L3 -> 1.6933246
Q31: cg | R31: =F12*L3 -> 0.16890913
B32: omegacrv | E32: =ss!E34+ss!E33 -> 4.4610609 | F32: =F34+F33 -> 4.45 | I32: wl/pc | J32: =(J11*D54)/(J4*D62) -> 1.2431443 | K32: =(K11*E54)/(K4*E62) -> 1.1803511 | L32: =(L11*F54)/(L4*F62) -> 1.1111111 | Q32: ig | R32: =F13*L3 -> 0.067563651
B33: omegacrhv | E33: =AVERAGE('SA data'!AJ78:AJ137)/AVERAGE('SA data'!A78:A137) -> 0.80208335 | F33: =MROUND(ss!E33,0.05) -> 0.8 | I33: tx/c | J33: =J13/J4 -> 0.30737217 | K33: =K13/K4 -> 0.28809452 | L33: =L13/L4 -> 0.25625 | Q33: tr | R33: =F14*L3 -> 0.076009108
B34: omegacrfv | E34: =AVERAGE('SA data'!AK78:AK137)/AVERAGE('SA data'!A78:A137) -> 3.6589776 | F34: =MROUND(ss!E34,0.05) -> 3.65 | I34: txh/c | J34: =J14/J4 -> 0.10245739 | K34: =K14/K4 -> 0.096031506 | L34: =L14/L4 -> 0.085416667 | Q34: txh | R34: =F19*L3 -> 0.086565928
B35: omegalendgv | E35: =AVERAGE('SA data'!AL78:AL137)/AVERAGE('SA data'!A78:A137) -> 0.59402881 | F35: =MROUND(ss!E35,0.05) -> 0.6 | I35: tr/c | J35: =J17/J4 -> 0.069561854 | K35: =K17/K4 -> 0.077816591 | L35: =L17/L4 -> 0.075 | Q35: txf | R35: =F20*L3 -> 0.17313186
B36: omegaoav | E36: =AVERAGE('SA data'!AM78:AM137)/AVERAGE('SA data'!A78:A137) -> 2.4965484 | F36: =MROUND(ss!E36,0.05) -> 2.5 | Q36: ntx | R36: =F21*L3 -> 0.086565928
B37: omeganwv | E37: =AVERAGE('SA data'!AN78:AN137)/AVERAGE('SA data'!$A78:$A137) -> 0.80568653 | F37: =MROUND(ss!E37,0.05) -> 0.8 | I37: v/nw | K37: =K3/K24 -> 1.2411775 | L37: =L3/L24 -> 1.25 | Q37: fp | R37: =R34+R35+R36 -> 0.34626371 | T37: =R31/R37 -> 0.48780488 | U37: =R32/R37 -> 0.19512195 | V37: =R33/R37 -> 0.2195122 | W37: =R34/R37 -> 0.25 | X37: =R35/R37 -> 0.5 | Y37: =R36/R37 -> 0.25
B38: omegaloanv | E38: =AVERAGE('SA data'!AO78:AO137)/AVERAGE('SA data'!$A78:$A137) -> 0.2759849 | F38: =MROUND(ss!E38,0.05) -> 0.3 | I38: w*l/nw | K38: =(K11*E54)/K24 -> 0.82745167 | L38: =(L11*F54)/L24 -> 0.83333333
B39: omegadeppv | E39: =AVERAGE('SA data'!AP78:AP137)/AVERAGE('SA data'!$A78:$A137) -> 5.406103 | F39: =MROUND(ss!E39,0.05) -> 5.4 | I39: rb*fd/nw | K39: =(E61*(K25+K26))/K24 -> 0.11475745 | L39: =(F61*(L25+L26))/L24 -> 0.10700893
B40: omegaolv | E40: =AVERAGE('SA data'!AQ78:AQ137)/AVERAGE('SA data'!$A78:$A137) -> 1.0638637 | F40: =MROUND(ss!E40,0.05) -> 1.05
I41: alphadep | K41: =K26/(K26+K25) -> 0.95142896 | L41: =L26/(L26+L25) -> 0.94736842
I42: alphadepp | K42: =K26/(K26+K27) -> 1 | L42: =L26/(L26+L27) -> 1
B44: rr | D44: =D49/D46 -> 1.0025063 | E44: =E49/E46 -> 1.0025063 | F44: =F49/F46 -> 1.0025063 | I44: alphacredh | K44: =K20/(K20+K21) -> 0.17979655 | L44: =L20/(L20+L21) -> 0.17977528
I45: alphacreditf | K45: =K21/(K20+K21) -> 0.82020345 | L45: =L21/(L20+L21) -> 0.82022472
B46: pistar | D46: =1+2.5/400 -> 1.00625 | E46: =1+2.5/400 -> 1.00625 | F46: =1+2/400 -> 1.005
B47: piz | D47: =D46 -> 1.00625 | E47: =E46 -> 1.00625 | F47: =F46 -> 1.005 | I47: philoanh | K47: =K20/(K25+K26) -> 0.14115997 | L47: =L20/(L25+L26) -> 0.14035088
B48: beta | D48: 0.9975 | E48: 0.9975 | F48: 0.9975 | I48: philoanf | K48: =(K21/(K25+K26)) -> 0.64394949 | L48: =(L21/(L25+L26)) -> 0.64035088
B49: r | D49: =D47/D48 -> 1.0087719 | E49: =E47/E48 -> 1.0087719 | F49: =F47/F48 -> 1.0075188
B50: deltak | D50: =12/400 -> 0.03 | E50: =12/400 -> 0.03 | F50: =12/400 -> 0.03 | I50: omegao | K50: 0.7 | L50: 0.7
B51: omegakv | D51: =D3/(1-(1-D50)) -> 6.3044613 | E51: =ss!E3/(1-(1-E50)) -> 6.4676751 | F51: =F3/(1-(1-F50)) -> 6 | I51: sh | K51: =K50*K4/K20 -> 0.49291959 | L51: =L50*L4/L20 -> 0.525
B52: rk | D52: =1/D48-(1-D50) -> 0.032506266 | E52: =1/E48-(1-E50) -> 0.032506266 | F52: =1/F48-(1-F50) -> 0.032506266 | I52: sf | K52: =K5/K21 -> 0.053028544 | L52: =L5/L21 -> 0.049315068
B53: omegalv | D53: =2/3 -> 0.66666667 | E53: =2/3 -> 0.66666667 | F53: =2/3 -> 0.66666667
B54: l | D54: 1 | E54: 1 | F54: 1
B55: omegawv | D55: =D53 -> 0.66666667 | E55: =E53 -> 0.66666667 | F55: =F53 -> 0.66666667
B56: alphal | D56: =1/(1+D52*D51/D55) -> 0.76487584 | E56: =1/(1+E52*E51/E55) -> 0.76024818 | F56: =1/(1+F52*F51/F55) -> 0.77366064
B57: muv | D57: =D56/D53 -> 1.1473138 | E57: =E56/E53 -> 1.1403723 | F57: =F56/F53 -> 1.160491
B58: mcv | D58: =1/D57 -> 0.87160116 | E58: =1/E57 -> 0.87690663 | F58: =1/F57 -> 0.86170426
B59: muz | D59: 1.005 | E59: 1.005 | F59: 1.005
B60: alphav | D60: =D8*D59 -> 0.61053164 | E60: =E8*E59 -> 0.61569825 | F60: =F8*F59 -> 0.60909091
B61: rb | D61: =D47/D48-1+3/400 -> 0.01627193 | E61: =E47/E48-1+3/400 -> 0.01627193 | F61: =F47/F48-1+3/400 -> 0.015018797
B62: pc | D62: 1 | E62: 1 | F62: 1

Sheet DATA
B1: Nominal | I1: Real | P1: Implicit deflator | W1: Nominal | Z1: 1 | AA1: 0.059 | AB1: 0.027 | AC1: 0.004 | AD1: =SUM(AA1:AC1) -> 0.09 | AG1: 0.767 | AH1: =Z1-AG1 -> 0.233 | AJ1: 0.8 | AK1: 0.1 | AL1: 0.1 | AU1: Nominal | BD1: Real | BM1: FISS & MSB (1.19, 1.19b, 1.19b) | BP1: Nominal | BZ1: Real Total asset/Liabilities | CK1: Real | CQ1: https://fred.stlouisfed.org/series/WTISPLC | CR1: Crude Oil Prices: Brent - Europe (DCOILBRENTEU) | FRED | St. Louis Fed
B2: Household consumption | C2: Gov consumption | D2: GFCF | E2: Change in Stock | F2: Exports of G&S | G2: Imports G&S | H2: GDP | I2: Household consumption | J2: Gov consumption | K2: GFCF | L2: Change in Stock | M2: Exports of G&S | N2: Imports G&S | O2: GDP | P2: Household consumption | Q2: Gov consumption | R2: GFCF | S2: Exports of G&S | T2: Imports G&S | U2: GDP | W2: Wage per worker | X2: Labour hour | Z2: Hradline CPI | AA2: Fuel price index | AB2: Electricity price index | AC2: Gas price index | AD2: Energy price index | AF2: DOSM Core CPI | AG2: Adjusted Core CPI | AH2: Non-coreCPI | AI2: Headline | AJ2: Core | AK2: Energy | AL2: Temporary | AN2: OPR | AO2: 3 mths deposit rate | AP2: Average lending rate (ALR) | AQ2: Spread (Risk premium) | AR2: MYRUSD | AS2: NEER, BIS | AU2: Household tax | AV2: Firm tax | AW2: Non-tax revenue | AX2: Transfer | AY2: Interest charges | AZ2: Fed gov consumption | BA2: Fed gov investment | BB2: Overall deficit | BC2: Deficit, % | BD2: Household tax | BE2: Firm tax | BF2: Non-tax revenue | BG2: Transfer | BH2: Interest charges | BI2: Fed gov consumption | BJ2: Fed gov investment | BK2: Overall deficit | BM2: Share of household consumption credit | BN2: Credit for consumption | BO2: Total credit | BP2: Total asset/Liabilities | BQ2: Lending to Government | BR2: Credit to Private sector | BS2: Credit to house-holds | BT2: Credit to firms | BU2: Other asset | BV2: Networth | BW2: External borrowings | BX2: Deposits | BY2: Other liabiities | BZ2: Total asset/Liabilities | CA2: Lending to Government | CB2: Credit to Private sector | CC2: Credit to house-holds | CD2: Credit to firms | CE2: Other asset | CF2: Networth | CG2: External borrowings | CH2: Deposits | CI2: Other liabiities | CK2: Global trade, sa | CL2: Global GDP, sa | CM2: US export G&S deflator, sa | CN2: FFR | CO2: US CPI | CP2: Global commodity price | CQ2: Crude oil WTI | CR2: Crude oil Brent
A3: 33298 | B3: 21813 | C3: 3672 | D3: 13437.633 | E3: =H3-B3-C3-D3-F3+G3 -> -2283.1171 | F3: 22804.771 | G3: 24503.287 | H3: 34941 | I3: 40020 | J3: 6650 | K3: 22298.503 | L3: =O3-I3-J3-K3-M3+N3 -> 1807.0153 | M3: 43385.472 | N3: 39647.99 | O3: 74513 | P3: =B3/I3*100 -> 54.505247 | Q3: =C3/J3*100 -> 55.218045 | R3: =D3/K3*100 -> 60.262492 | S3: =F3/M3*100 -> 52.563151 | T3: =G3/N3*100 -> 61.802093 | U3: =H3/O3*100 -> 46.892489 | W3: 1974.8527 | X3: 4844.7118 | Z3: 58.429371 | AA3: 59 | AB3: 93 | AC3: 67.666667 | AD3: =SUMPRODUCT($AA$1:$AC$1,AA3:AC3)/SUM($AA$1:$AC$1) -> 69.585185 | AF3: 67.076243 | AG3: 67.076243 | AH3: =(Z3-0.8*AG3)/0.2 -> 23.84188 | AN3: 6.5866667 | AO3: 6.49 | AP3: 9.1 | AQ3: =AP3-AN3 -> 2.5133333 | AR3: 2.7182 | AS3: 138.34506 | AU3: 1566.8777 | AV3: 4587.7392 | AW3: 1410.3143 | AX3: 681.75531 | AY3: 976.30021 | AZ3: 3807.6234 | BA3: 787.71857 | BB3: =AU3+AV3+AW3-AX3-AY3-AZ3-BA3 -> 1311.5337 | BC3: =BB3/H3*100 -> 3.7535665 | BD3: =AU3/$U3*100 -> 3341.4258 | BE3: =AV3/$U3*100 -> 9783.5269 | BF3: =AW3/$U3*100 -> 3007.5484 | BG3: =AX3/$U3*100 -> 1453.8689 | BH3: =AY3/$U3*100 -> 2081.997 | BI3: =AZ3/$U3*100 -> 8119.9006 | BJ3: =BA3/$U3*100 -> 1679.8396 | BK3: =BD3+BE3+BF3-BG3-BH3-BI3-BJ3 -> 2796.895 | CK3: 48.625969 | CL3: 68.775947 | CM3: 84.591 | CN3: 6.43 | CO3: 61.793 | CQ3: 21.781 | CR3: 20.82
A4: 33390 | B4: 18721 | C4: 3991 | D4: 13098.858 | E4: =H4-B4-C4-D4-F4+G4 -> 1771.0321 | F4: 22837.551 | G4: 25450.441 | H4: 34969 | I4: 33768 | J4: 7088 | K4: 21428.75 | L4: =O4-I4-J4-K4-M4+N4 -> 10203.238 | M4: 43069.236 | N4: 40861.223 | O4: 74696 | P4: =B4/I4*100 -> 55.440062 | Q4: =C4/J4*100 -> 56.306433 | R4: =D4/K4*100 -> 61.127496 | S4: =F4/M4*100 -> 53.025207 | T4: =G4/N4*100 -> 62.28507 | U4: =H4/O4*100 -> 46.815091 | W4: 1994.2184 | X4: 4744.3815 | Z4: 59.186543 | AA4: 59 | AB4: 93 | AC4: 68 | AD4: =SUMPRODUCT($AA$1:$AC$1,AA4:AC4)/SUM($AA$1:$AC$1) -> 69.6 | AF4: 67.734365 | AG4: 67.734365 | AH4: =(Z4-0.8*AG4)/0.2 -> 24.995253 | AN4: 6.8833333 | AO4: 6.7333333 | AP4: 9.3 | AQ4: =AP4-AN4 -> 2.4166667 | AR4: 2.7621 | AS4: 141.12479 | AU4: 1294.5311 | AV4: 5019.3896 | AW4: 1565.9482 | AX4: 464.8135 | AY4: 1868.2836 | AZ4: 3675.7309 | BA4: 1092.2764 | BB4: =AU4+AV4+AW4-AX4-AY4-AZ4-BA4 -> 778.76445 | BC4: =BB4/H4*100 -> 2.2270138 | BD4: =AU4/$U4*100 -> 2765.2005 | BE4: =AV4/$U4*100 -> 10721.734 | BF4: =AW4/$U4*100 -> 3344.9645 | BG4: =AX4/$U4*100 -> 992.87109 | BH4: =AY4/$U4*100 -> 3990.7721 | BI4: =AZ4/$U4*100 -> 7851.5941 | BJ4: =BA4/$U4*100 -> 2333.1717 | BK4: =BD4+BE4+BF4-BG4-BH4-BI4-BJ4 -> 1663.4902 | CK4: 50.008921 | CL4: 69.402571 | CM4: 84.115 | CN4: 5.86 | CO4: 62.27 | CQ4: 20.753 | CR4: 18.87
A5: 33482 | B5: 20857 | C5: 5052 | D5: 15269.136 | E5: =H5-B5-C5-D5-F5+G5 -> -722.07427 | F5: 27343.087 | G5: 27480.149 | H5: 40319 | I5: 38019 | J5: 9128 | K5: 25300.961 | L5: =O5-I5-J5-K5-M5+N5 -> 5074.1868 | M5: 50861.965 | N5: 43952.112 | O5: 84432 | P5: =B5/I5*100 -> 54.859412 | Q5: =C5/J5*100 -> 55.346188 | R5: =D5/K5*100 -> 60.350027 | S5: =F5/M5*100 -> 53.7594 | T5: =G5/N5*100 -> 62.522932 | U5: =H5/O5*100 -> 47.753222 | W5: 2069.3729 | X5: 4912.1779 | Z5: 59.47642 | AA5: 59 | AB5: 93 | AC5: 68 | AD5: =SUMPRODUCT($AA$1:$AC$1,AA5:AC5)/SUM($AA$1:$AC$1) -> 69.6 | AF5: 68.305718 | AG5: 68.305718 | AH5: =(Z5-0.8*AG5)/0.2 -> 24.159228 | AN5: 7.4066667 | AO5: 7.3266667 | AP5: 9.3 | AQ5: =AP5-AN5 -> 1.8933333 | AR5: 2.7756 | AS5: 140.05566 | AU5: 1532.4472 | AV5: 5056.6358 | AW5: 1270.9197 | AX5: 609.88596 | AY5: 1446.6994 | AZ5: 4381.2142 | BA5: 2699.7021 | BB5: =AU5+AV5+AW5-AX5-AY5-AZ5-BA5 -> -1277.4991 | BC5: =BB5/H5*100 -> -3.1684791 | BD5: =AU5/$U5*100 -> 3209.097 | BE5: =AV5/$U5*100 -> 10589.099 | BF5: =AW5/$U5*100 -> 2661.4323 | BG5: =AX5/$U5*100 -> 1277.1619 | BH5: =AY5/$U5*100 -> 3029.5326 | BI5: =AZ5/$U5*100 -> 9174.6988 | BJ5: =BA5/$U5*100 -> 5653.4451 | BK5: =BD5+BE5+BF5-BG5-BH5-BI5-BJ5 -> -2675.2103 | CK5: 51.228721 | CL5: 70.132529 | CM5: 83.542 | CN5: 5.65 | CO5: 62.83 | CQ5: 21.655 | CR5: 19.87
A6: 33573 | B6: 20709 | C6: 6837 | D6: 17261.737 | E6: =H6-B6-C6-D6-F6+G6 -> -1993.3961 | F6: 27957.658 | G6: 28081.999 | H6: 42690 | I6: 37877 | J6: 12378 | K6: 27787.64 | L6: =O6-I6-J6-K6-M6+N6 -> 289.93284 | M6: 51518.265 | N6: 44177.838 | O6: 85673 | P6: =B6/I6*100 -> 54.674341 | Q6: =C6/J6*100 -> 55.235095 | R6: =D6/K6*100 -> 62.120197 | S6: =F6/M6*100 -> 54.267468 | T6: =G6/N6*100 -> 63.565806 | U6: =H6/O6*100 -> 49.829001 | W6: 2226.5044 | X6: 4913.876 | Z6: 59.843581 | AA6: 59 | AB6: 93 | AC6: 68 | AD6: =SUMPRODUCT($AA$1:$AC$1,AA6:AC6)/SUM($AA$1:$AC$1) -> 69.6 | AF6: 68.669915 | AG6: 68.669915 | AH6: =(Z6-0.8*AG6)/0.2 -> 24.538245 | AN6: 7.71 | AO6: 7.8933333 | AP6: 9.69 | AQ6: =AP6-AN6 -> 1.98 | AR6: 2.7434 | AS6: 137.59667 | AU6: 1492.144 | AV6: 5280.2354 | AW6: 3975.8179 | AX6: 1023.5452 | AY6: 2756.7168 | AZ6: 6603.4314 | BA6: 3817.3029 | BB6: =AU6+AV6+AW6-AX6-AY6-AZ6-BA6 -> -3452.799 | BC6: =BB6/H6*100 -> -8.0880746 | BD6: =AU6/$U6*100 -> 2994.5292 | BE6: =AV6/$U6*100 -> 10596.711 | BF6: =AW6/$U6*100 -> 7978.9235 | BG6: =AX6/$U6*100 -> 2054.1155 | BH6: =AY6/$U6*100 -> 5532.3541 | BI6: =AZ6/$U6*100 -> 13252.185 | BJ6: =BA6/$U6*100 -> 7660.8055 | BK6: =BD6+BE6+BF6-BG6-BH6-BI6-BJ6 -> -6929.2961 | CK6: 52.115671 | CL6: 70.761915 | CM6: 83.691 | CN6: 4.82 | CO6: 63.325 | CQ6: 21.737 | CR6: 20.63
A7: 33664 | B7: 23814 | C7: 3698 | D7: 15708.593 | E7: =H7-B7-C7-D7-F7+G7 -> -2628.7459 | F7: 24195.856 | G7: 26006.703 | H7: 38781 | I7: 42183 | J7: 6597 | K7: 25643.278 | L7: =O7-I7-J7-K7-M7+N7 -> 3401.8332 | M7: 47408.986 | N7: 43408.098 | O7: 81826 | P7: =B7/I7*100 -> 56.454022 | Q7: =C7/J7*100 -> 56.055783 | R7: =D7/K7*100 -> 61.258133 | S7: =F7/M7*100 -> 51.036433 | T7: =G7/N7*100 -> 59.9121 | U7: =H7/O7*100 -> 47.394471 | W7: 2193.984 | X7: 4951.0638 | Z7: 60.951382 | AA7: 59 | AB7: 93 | AC7: 68 | AD7: =SUMPRODUCT($AA$1:$AC$1,AA7:AC7)/SUM($AA$1:$AC$1) -> 69.6 | AF7: 69.678963 | AG7: 69.678963 | AH7: =(Z7-0.8*AG7)/0.2 -> 26.041058 | AI7: =(Z7/Z3-1)*100 -> 4.3163419 | AJ7: =(AF7/AF3-1)*100*$AJ$1 -> 3.1041926 | AK7: =(AD7/AD3-1)*100*$AK$1 -> 0.0021290185 | AL7: =AI7-AJ7-AK7 -> 1.2100202 | AN7: 7.93 | AO7: 7.8866667 | AP7: 9.91 | AQ7: =AP7-AN7 -> 1.98 | AR7: 2.6227 | AS7: 143.47687 | AU7: 1822.2616 | AV7: 5106.571 | AW7: 1790.6209 | AX7: 771.91068 | AY7: 1011.7617 | AZ7: 4411.9613 | BA7: 789.68857 | BB7: =AU7+AV7+AW7-AX7-AY7-AZ7-BA7 -> 1734.1312 | BC7: =BB7/H7*100 -> 4.4715999 | BD7: =AU7/$U7*100 -> 3844.8822 | BE7: =AV7/$U7*100 -> 10774.613 | BF7: =AW7/$U7*100 -> 3778.1219 | BG7: =AX7/$U7*100 -> 1628.6935 | BH7: =AY7/$U7*100 -> 2134.7674 | BI7: =AZ7/$U7*100 -> 9309.0211 | BJ7: =BA7/$U7*100 -> 1666.204 | BK7: =BD7+BE7+BF7-BG7-BH7-BI7-BJ7 -> 3658.9314 | CK7: 52.952021 | CL7: 71.741311 | CM7: 83.551 | CN7: 4.02 | CO7: 63.809 | CP7: 45.563089 | CQ7: 18.91 | CR7: 17.95
A8: 33756 | B8: 20178 | C8: 4612 | D8: 14487.337 | E8: =H8-B8-C8-D8-F8+G8 -> 119.27277 | F8: 26452.19 | G8: 25939.799 | H8: 39909 | I8: 35487 | J8: 8257 | K8: 23871.627 | L8: =O8-I8-J8-K8-M8+N8 -> 6598.6375 | M8: 52164.087 | N8: 43615.352 | O8: 82763 | P8: =B8/I8*100 -> 56.860259 | Q8: =C8/J8*100 -> 55.855638 | R8: =D8/K8*100 -> 60.688519 | S8: =F8/M8*100 -> 50.70958 | T8: =G8/N8*100 -> 59.474012 | U8: =H8/O8*100 -> 48.220823 | W8: 2149.3003 | X8: 4921.7585 | Z8: 61.899059 | AA8: 59 | AB8: 93 | AC8: 68 | AD8: =SUMPRODUCT($AA$1:$AC$1,AA8:AC8)/SUM($AA$1:$AC$1) -> 69.6 | AF8: 70.352827 | AG8: 70.352827 | AH8: =(Z8-0.8*AG8)/0.2 -> 28.083987 | AI8: =(Z8/Z4-1)*100 -> 4.5829947 | AJ8: =(AF8/AF4-1)*100*$AJ$1 -> 3.0926242 | AK8: =(AD8/AD4-1)*100*$AK$1 -> 0 | AL8: =AI8-AJ8-AK8 -> 1.4903706 | AN8: 7.9566667 | AO8: 8.0166667 | AP8: 10.17 | AQ8: =AP8-AN8 -> 2.2133333 | AR8: 2.531 | AS8: 149.03633 | AU8: 1505.6862 | AV8: 5583.5346 | AW8: 1993.2345 | AX8: 482.45556 | AY8: 1936.1441 | AZ8: 4392.722 | BA8: 1095.0081 | BB8: =AU8+AV8+AW8-AX8-AY8-AZ8-BA8 -> 1176.1256 | BC8: =BB8/H8*100 -> 2.9470185 | BD8: =AU8/$U8*100 -> 3122.4814 | BE8: =AV8/$U8*100 -> 11579.094 | BF8: =AW8/$U8*100 -> 4133.5555 | BG8: =AX8/$U8*100 -> 1000.5129 | BH8: =AY8/$U8*100 -> 4015.1618 | BI8: =AZ8/$U8*100 -> 9109.5957 | BJ8: =BA8/$U8*100 -> 2270.82 | BK8: =BD8+BE8+BF8-BG8-BH8-BI8-BJ8 -> 2439.0409 | CK8: 53.652745 | CL8: 72.670182 | CM8: 83.628 | CN8: 3.77 | CO8: 64.26 | CP8: 47.754752 | CQ8: 21.186 | CR8: 20.01
A9: 33848 | B9: 22541 | C9: 4949 | D9: 17758.006 | E9: =H9-B9-C9-D9-F9+G9 -> -1078.5134 | F9: 28698.855 | G9: 28030.347 | H9: 44838 | I9: 39915 | J9: 8796 | K9: 28817.794 | L9: =O9-I9-J9-K9-M9+N9 -> 4734.4701 | M9: 55379.164 | N9: 46876.428 | O9: 90766 | P9: =B9/I9*100 -> 56.472504 | Q9: =C9/J9*100 -> 56.264211 | R9: =D9/K9*100 -> 61.621669 | S9: =F9/M9*100 -> 51.822479 | T9: =G9/N9*100 -> 59.796253 | U9: =H9/O9*100 -> 49.399555 | W9: 2227.1443 | X9: 4875.7835 | Z9: 62.499898 | AA9: 59 | AB9: 93 | AC9: 68 | AD9: =SUMPRODUCT($AA$1:$AC$1,AA9:AC9)/SUM($AA$1:$AC$1) -> 69.6 | AF9: 70.80095 | AG9: 70.80095 | AH9: =(Z9-0.8*AG9)/0.2 -> 29.295691 | AI9: =(Z9/Z5-1)*100 -> 5.0834913 | AJ9: =(AF9/AF5-1)*100*$AJ$1 -> 2.9224289 | AK9: =(AD9/AD5-1)*100*$AK$1 -> 0 | AL9: =AI9-AJ9-AK9 -> 2.1610624 | AN9: 7.8433333 | AO9: 7.97 | AP9: 10.3 | AQ9: =AP9-AN9 -> 2.4566667 | AR9: 2.5002 | AS9: 146.68425 | AU9: 1782.6988 | AV9: 5659.2796 | AW9: 1617.5789 | AX9: 603.58553 | AY9: 1499.2469 | AZ9: 5194.751 | BA9: 2706.4538 | BB9: =AU9+AV9+AW9-AX9-AY9-AZ9-BA9 -> -944.47999 | BC9: =BB9/H9*100 -> -2.1064276 | BD9: =AU9/$U9*100 -> 3608.7346 | BE9: =AV9/$U9*100 -> 11456.135 | BF9: =AW9/$U9*100 -> 3274.4807 | BG9: =AX9/$U9*100 -> 1221.8441 | BH9: =AY9/$U9*100 -> 3034.9402 | BI9: =AZ9/$U9*100 -> 10515.785 | BJ9: =BA9/$U9*100 -> 5478.7008 | BK9: =BD9+BE9+BF9-BG9-BH9-BI9-BJ9 -> -1911.9201 | CK9: 54.35499 | CL9: 73.535547 | CM9: 83.619 | CN9: 3.26 | CO9: 64.64 | CP9: 48.522837 | CQ9: 21.67 | CR9: 20.09
A10: 33939 | B10: 21690 | C10: 7455 | D10: 18331.964 | E10: =H10-B10-C10-D10-F10+G10 -> -3285.1689 | F10: 30549.236 | G10: 27777.031 | H10: 46964 | I10: 39059 | J10: 13309 | K10: 29010.296 | L10: =O10-I10-J10-K10-M10+N10 -> -1241.7934 | M10: 57665.595 | N10: 45486.098 | O10: 92316 | P10: =B10/I10*100 -> 55.531376 | Q10: =C10/J10*100 -> 56.014727 | R10: =D10/K10*100 -> 63.191235 | S10: =F10/M10*100 -> 52.976538 | T10: =G10/N10*100 -> 61.067079 | U10: =H10/O10*100 -> 50.873088 | W10: 2403.8501 | X10: 4997.5792 | Z10: 62.74584 | AA10: 59 | AB10: 93 | AC10: 68 | AD10: =SUMPRODUCT($AA$1:$AC$1,AA10:AC10)/SUM($AA$1:$AC$1) -> 69.6 | AF10: 71.024095 | AG10: 71.024095 | AH10: =(Z10-0.8*AG10)/0.2 -> 29.632818 | AI10: =(Z10/Z6-1)*100 -> 4.84974 | AJ10: =(AF10/AF6-1)*100*$AJ$1 -> 2.7426035 | AK10: =(AD10/AD6-1)*100*$AK$1 -> 0 | AL10: =AI10-AJ10-AK10 -> 2.1071366 | AN10: 7.9366667 | AO10: 7.8666667 | AP10: 10.27 | AQ10: =AP10-AN10 -> 2.3333333 | AR10: 2.5337 | AS10: 148.07411 | AU10: 1734.3533 | AV10: 5577.6148 | AW10: 5076.5657 | AX10: 885.04823 | AY10: 2856.8472 | AZ10: 8028.5656 | BA10: 3826.8495 | BB10: =AU10+AV10+AW10-AX10-AY10-AZ10-BA10 -> -3208.7768 | BC10: =BB10/H10*100 -> -6.832418 | BD10: =AU10/$U10*100 -> 3409.1765 | BE10: =AV10/$U10*100 -> 10963.783 | BF10: =AW10/$U10*100 -> 9978.8825 | BG10: =AX10/$U10*100 -> 1739.7179 | BH10: =AY10/$U10*100 -> 5615.6356 | BI10: =AZ10/$U10*100 -> 15781.557 | BJ10: =BA10/$U10*100 -> 7522.3456 | BK10: =BD10+BE10+BF10-BG10-BH10-BI10-BJ10 -> -6307.415 | CK10: 55.138063 | CL10: 74.585097 | CM10: 83.466 | CN10: 3.03 | CO10: 65.114 | CP10: 46.85093 | CQ10: 20.479 | CR10: 19.22
A11: 34029 | B11: 24281 | C11: 3758 | D11: 17310.87 | E11: =H11-B11-C11-D11-F11+G11 -> -2089.8982 | F11: 28881.058 | G11: 28037.03 | H11: 44104 | I11: 41328 | J11: 6453 | K11: 27566.524 | L11: =O11-I11-J11-K11-M11+N11 -> 5107.8074 | M11: 52922.058 | N11: 44971.389 | O11: 88406 | P11: =B11/I11*100 -> 58.751936 | Q11: =C11/J11*100 -> 58.236479 | R11: =D11/K11*100 -> 62.796709 | S11: =F11/M11*100 -> 54.572818 | T11: =G11/N11*100 -> 62.34415 | U11: =H11/O11*100 -> 49.888017 | W11: 2253.7762 | X11: 4946.9225 | Z11: 63.605043 | AA11: 59 | AB11: 93 | AC11: 68 | AD11: =SUMPRODUCT($AA$1:$AC$1,AA11:AC11)/SUM($AA$1:$AC$1) -> 69.6 | AF11: 71.836605 | AG11: 71.836605 | AH11: =(Z11-0.8*AG11)/0.2 -> 30.678796 | AI11: =(Z11/Z7-1)*100 -> 4.3537338 | AJ11: =(AF11/AF7-1)*100*$AJ$1 -> 2.4772375 | AK11: =(AD11/AD7-1)*100*$AK$1 -> 0 | AL11: =AI11-AJ11-AK11 -> 1.8764963 | AN11: 7.6466667 | AO11: 7.5566667 | AP11: 10.22 | AQ11: =AP11-AN11 -> 2.5733333 | AR11: 2.6106 | AS11: 145.4013 | AU11: 2220.7465 | AV11: 5386.6956 | AW11: 1654.2836 | AX11: 819.86224 | AY11: 992.64576 | AZ11: 4410.5546 | BA11: 855.54286 | BB11: =AU11+AV11+AW11-AX11-AY11-AZ11-BA11 -> 2183.1203 | BC11: =BB11/H11*100 -> 4.9499372 | BD11: =AU11/$U11*100 -> 4451.4629 | BE11: =AV11/$U11*100 -> 10797.574 | BF11: =AW11/$U11*100 -> 3315.994 | BG11: =AX11/$U11*100 -> 1643.4052 | BH11: =AY11/$U11*100 -> 1989.7479 | BI11: =AZ11/$U11*100 -> 8840.9099 | BJ11: =BA11/$U11*100 -> 1714.9266 | BK11: =BD11+BE11+BF11-BG11-BH11-BI11-BJ11 -> 4376.0415 | CK11: 56.014871 | CL11: 75.277223 | CM11: 83.568 | CN11: 3.04 | CO11: 65.563 | CP11: 46.327112 | CQ11: 19.825 | CR11: 18.24
A12: 34121 | B12: 22228 | C12: 5831 | D12: 19413.032 | E12: =H12-B12-C12-D12-F12+G12 -> -802.09939 | F12: 32417.921 | G12: 32011.853 | H12: 47076 | I12: 37957 | J12: 10148 | K12: 30316.966 | L12: =O12-I12-J12-K12-M12+N12 -> 7350.2101 | M12: 58415.867 | N12: 51003.044 | O12: 93185 | P12: =B12/I12*100 -> 58.561003 | Q12: =C12/J12*100 -> 57.459598 | R12: =D12/K12*100 -> 64.033556 | S12: =F12/M12*100 -> 55.495061 | T12: =G12/N12*100 -> 62.764594 | U12: =H12/O12*100 -> 50.51886 | W12: 2279.1197 | X12: 4986.6827 | Z12: 64.055098 | AA12: 59 | AB12: 93 | AC12: 68 | AD12: =SUMPRODUCT($AA$1:$AC$1,AA12:AC12)/SUM($AA$1:$AC$1) -> 69.6 | AF12: 72.172011 | AG12: 72.172011 | AH12: =(Z12-0.8*AG12)/0.2 -> 31.587448 | AI12: =(Z12/Z8-1)*100 -> 3.4831535 | AJ12: =(AF12/AF8-1)*100*$AJ$1 -> 2.0686406 | AK12: =(AD12/AD8-1)*100*$AK$1 -> 0 | AL12: =AI12-AJ12-AK12 -> 1.4145128 | AN12: 7.3066667 | AO12: 7.2466667 | AP12: 10.16 | AQ12: =AP12-AN12 -> 2.8533333 | AR12: 2.5713 | AS12: 143.26304 | AU12: 1835.7548 | AV12: 5955.3032 | AW12: 1856.2452 | AX12: 511.94978 | AY12: 1899.563 | AZ12: 4429.9634 | BA12: 1186.3238 | BB12: =AU12+AV12+AW12-AX12-AY12-AZ12-BA12 -> 1619.5031 | BC12: =BB12/H12*100 -> 3.4401884 | BD12: =AU12/$U12*100 -> 3633.8008 | BE12: =AV12/$U12*100 -> 11788.277 | BF12: =AW12/$U12*100 -> 3674.3608 | BG12: =AX12/$U12*100 -> 1013.3835 | BH12: =AY12/$U12*100 -> 3760.1067 | BI12: =AZ12/$U12*100 -> 8768.9299 | BJ12: =BA12/$U12*100 -> 2348.279 | BK12: =BD12+BE12+BF12-BG12-BH12-BI12-BJ12 -> 3205.7395 | CK12: 56.861776 | CL12: 76.119003 | CM12: 83.798 | CN12: 3 | CO12: 66.061 | CP12: 47.382121 | CQ12: 19.76 | CR12: 18.25
A13: 34213 | B13: 24278 | C13: 5894 | D13: 20261.885 | E13: =H13-B13-C13-D13-F13+G13 -> 350.67263 | F13: 34656.164 | G13: 33860.721 | H13: 51580 | I13: 42124 | J13: 10189 | K13: 32247.112 | L13: =O13-I13-J13-K13-M13+N13 -> 6722.454 | M13: 62890.863 | N13: 53404.428 | O13: 100769 | P13: =B13/I13*100 -> 57.634603 | Q13: =C13/J13*100 -> 57.846697 | R13: =D13/K13*100 -> 62.833176 | S13: =F13/M13*100 -> 55.105245 | T13: =G13/N13*100 -> 63.404332 | U13: =H13/O13*100 -> 51.186377 | W13: 2334.8817 | X13: 5037.5947 | Z13: 64.442401 | AA13: 59 | AB13: 93 | AC13: 68 | AD13: =SUMPRODUCT($AA$1:$AC$1,AA13:AC13)/SUM($AA$1:$AC$1) -> 69.6 | AF13: 72.514126 | AG13: 72.514126 | AH13: =(Z13-0.8*AG13)/0.2 -> 32.155503 | AI13: =(Z13/Z9-1)*100 -> 3.1080097 | AJ13: =(AF13/AF9-1)*100*$AJ$1 -> 1.9357659 | AK13: =(AD13/AD9-1)*100*$AK$1 -> 0 | AL13: =AI13-AJ13-AK13 -> 1.1722438 | AN13: 6.94 | AO13: 6.8566667 | AP13: 9.93 | AQ13: =AP13-AN13 -> 2.99 | AR13: 2.5553 | AS13: 144.01143 | AU13: 2162.0317 | AV13: 5954.9107 | AW13: 1506.0386 | AX13: 640.13578 | AY13: 1470.9205 | AZ13: 5218.8345 | BA13: 2932.1524 | BB13: =AU13+AV13+AW13-AX13-AY13-AZ13-BA13 -> -639.06219 | BC13: =BB13/H13*100 -> -1.2389728 | BD13: =AU13/$U13*100 -> 4223.842 | BE13: =AV13/$U13*100 -> 11633.78 | BF13: =AW13/$U13*100 -> 2942.2645 | BG13: =AX13/$U13*100 -> 1250.5979 | BH13: =AY13/$U13*100 -> 2873.6563 | BI13: =AZ13/$U13*100 -> 10195.749 | BJ13: =BA13/$U13*100 -> 5728.3843 | BK13: =BD13+BE13+BF13-BG13-BH13-BI13-BJ13 -> -1248.5005 | CK13: 57.458111 | CL13: 77.104476 | CM13: 83.741 | CN13: 3.06 | CO13: 66.43 | CP13: 46.698385 | CQ13: 17.796 | CR13: 16.49
A14: 34304 | B14: 26001 | C14: 7380 | D14: 23428.25 | E14: =H14-B14-C14-D14-F14+G14 -> -2783.4593 | F14: 34475.111 | G14: 36498.902 | H14: 52002 | I14: 45056 | J14: 13078 | K14: 36378.911 | L14: =O14-I14-J14-K14-M14+N14 -> -781.69003 | M14: 62935.038 | N14: 56975.259 | O14: 99691 | P14: =B14/I14*100 -> 57.708185 | Q14: =C14/J14*100 -> 56.430647 | R14: =D14/K14*100 -> 64.400636 | S14: =F14/M14*100 -> 54.778883 | T14: =G14/N14*100 -> 64.060967 | U14: =H14/O14*100 -> 52.163184 | W14: 2476.6207 | X14: 4973.5275 | Z14: 64.83051 | AA14: 59 | AB14: 91.666667 | AC14: 68 | AD14: =SUMPRODUCT($AA$1:$AC$1,AA14:AC14)/SUM($AA$1:$AC$1) -> 69.2 | AF14: 72.725912 | AG14: 72.725912 | AH14: =(Z14-0.8*AG14)/0.2 -> 33.248901 | AI14: =(Z14/Z10-1)*100 -> 3.3224044 | AJ14: =(AF14/AF10-1)*100*$AJ$1 -> 1.9168904 | AK14: =(AD14/AD10-1)*100*$AK$1 -> -0.057471264 | AL14: =AI14-AJ14-AK14 -> 1.4629853 | AN14: 6.5233333 | AO14: 6.4433333 | AP14: 9.82 | AQ14: =AP14-AN14 -> 3.2966667 | AR14: 2.5595 | AS14: 144.75982 | AU14: 2110.467 | AV14: 6274.0905 | AW14: 4774.4326 | AX14: 937.0522 | AY14: 2802.8707 | AZ14: 8082.6475 | BA14: 4145.981 | BB14: =AU14+AV14+AW14-AX14-AY14-AZ14-BA14 -> -2809.5612 | BC14: =BB14/H14*100 -> -5.4027945 | BD14: =AU14/$U14*100 -> 4045.8938 | BE14: =AV14/$U14*100 -> 12027.814 | BF14: =AW14/$U14*100 -> 9152.8779 | BG14: =AX14/$U14*100 -> 1796.3861 | BH14: =AY14/$U14*100 -> 5373.2737 | BI14: =AZ14/$U14*100 -> 15494.927 | BJ14: =BA14/$U14*100 -> 7948.0979 | BK14: =BD14+BE14+BF14-BG14-BH14-BI14-BJ14 -> -5386.0998 | CK14: 59.35085 | CL14: 78.078835 | CM14: 83.707 | CN14: 2.99 | CO14: 66.772 | CP14: 45.472073 | CQ14: 16.451 | CR14: 15.18
A15: 34394 | B15: 28387 | C15: 4453 | D15: 20911.531 | E15: =H15-B15-C15-D15-F15+G15 -> -4427.6264 | F15: 36539.212 | G15: 37654.117 | H15: 48209 | I15: 46771 | J15: 7392 | K15: 32418.232 | L15: =O15-I15-J15-K15-M15+N15 -> 1456.0638 | M15: 63907.536 | N15: 56399.832 | O15: 95545 | P15: =B15/I15*100 -> 60.693592 | Q15: =C15/J15*100 -> 60.240801 | R15: =D15/K15*100 -> 64.505463 | S15: =F15/M15*100 -> 57.175123 | T15: =G15/N15*100 -> 66.762817 | U15: =H15/O15*100 -> 50.456853 | W15: 2397.6399 | X15: 4832.536 | Z15: 66.206978 | AA15: 59 | AB15: 89 | AC15: 67 | AD15: =SUMPRODUCT($AA$1:$AC$1,AA15:AC15)/SUM($AA$1:$AC$1) -> 68.355556 | AF15: 73.300146 | AG15: 73.300146 | AH15: =(Z15-0.8*AG15)/0.2 -> 37.834309 | AI15: =(Z15/Z11-1)*100 -> 4.0907691 | AJ15: =(AF15/AF11-1)*100*$AJ$1 -> 1.6298554 | AK15: =(AD15/AD11-1)*100*$AK$1 -> -0.17879949 | AL15: =AI15-AJ15-AK15 -> 2.6397132 | AN15: 4.0466667 | AO15: 6.0133333 | AP15: 9.35 | AQ15: =AP15-AN15 -> 5.3033333 | AR15: 2.7306 | AS15: 137.59667 | AU15: 2531.0962 | AV15: 6433.4877 | AW15: 2019.9282 | AX15: 958.67224 | AY15: 944.02468 | AZ15: 4870.2946 | BA15: 935.65619 | BB15: =AU15+AV15+AW15-AX15-AY15-AZ15-BA15 -> 3275.8644 | BC15: =BB15/H15*100 -> 6.7951303 | BD15: =AU15/$U15*100 -> 5016.3577 | BE15: =AV15/$U15*100 -> 12750.474 | BF15: =AW15/$U15*100 -> 4003.2782 | BG15: =AX15/$U15*100 -> 1899.9842 | BH15: =AY15/$U15*100 -> 1870.9543 | BI15: =AZ15/$U15*100 -> 9652.3947 | BJ15: =BA15/$U15*100 -> 1854.3689 | BK15: =BD15+BE15+BF15-BG15-BH15-BI15-BJ15 -> 6492.4072 | CK15: 60.603953 | CL15: 79.203567 | CM15: 84.082 | CN15: 3.21 | CO15: 67.075 | CP15: 45.829922 | CQ15: 14.813 | CR15: 13.96
A16: 34486 | B16: 25074 | C16: 5253 | D16: 20558.4 | E16: =H16-B16-C16-D16-F16+G16 -> 996.15616 | F16: 40255.536 | G16: 40414.093 | H16: 51723 | I16: 41547 | J16: 8931 | K16: 31772.181 | L16: =O16-I16-J16-K16-M16+N16 -> 9516.2462 | M16: 70747.184 | N16: 62206.611 | O16: 100307 | P16: =B16/I16*100 -> 60.350928 | Q16: =C16/J16*100 -> 58.817602 | R16: =D16/K16*100 -> 64.705664 | S16: =F16/M16*100 -> 56.900549 | T16: =G16/N16*100 -> 64.96752 | U16: =H16/O16*100 -> 51.564696 | W16: 2443.2014 | X16: 5162.4223 | Z16: 66.209658 | AA16: 59 | AB16: 90 | AC16: 68 | AD16: =SUMPRODUCT($AA$1:$AC$1,AA16:AC16)/SUM($AA$1:$AC$1) -> 68.7 | AF16: 73.578579 | AG16: 73.578579 | AH16: =(Z16-0.8*AG16)/0.2 -> 36.733974 | AI16: =(Z16/Z12-1)*100 -> 3.363604 | AJ16: =(AF16/AF12-1)*100*$AJ$1 -> 1.5591289 | AK16: =(AD16/AD12-1)*100*$AK$1 -> -0.12931034 | AL16: =AI16-AJ16-AK16 -> 1.9337855 | AN16: 4.0666667 | AO16: 4.48 | AP16: 8.95 | AQ16: =AP16-AN16 -> 4.8833333 | AR16: 2.6326 | AS16: 141.09 | AU16: 2090.9604 | AV16: 7083.8008 | AW16: 2267.0499 | AX16: 590.33966 | AY16: 1806.52 | AZ16: 5049.1944 | BA16: 1297.4116 | BB16: =AU16+AV16+AW16-AX16-AY16-AZ16-BA16 -> 2698.3456 | BC16: =BB16/H16*100 -> 5.2169162 | BD16: =AU16/$U16*100 -> 4055.0232 | BE16: =AV16/$U16*100 -> 13737.695 | BF16: =AW16/$U16*100 -> 4396.5156 | BG16: =AX16/$U16*100 -> 1144.8524 | BH16: =AY16/$U16*100 -> 3503.4046 | BI16: =AZ16/$U16*100 -> 9791.9599 | BJ16: =BA16/$U16*100 -> 2516.085 | BK16: =BD16+BE16+BF16-BG16-BH16-BI16-BJ16 -> 5232.9321 | CK16: 62.407797 | CL16: 80.292642 | CM16: 84.411 | CN16: 3.94 | CO16: 67.526 | CP16: 48.167029 | CQ16: 17.777 | CR16: 16.1
A17: 34578 | B17: 27745 | C17: 5997 | D17: 25590.76 | E17: =H17-B17-C17-D17-F17+G17 -> 388.42583 | F17: 44100.42 | G17: 44673.606 | H17: 59148 | I17: 45802 | J17: 10271 | K17: 40083.16 | L17: =O17-I17-J17-K17-M17+N17 -> 7087.6281 | M17: 75751.095 | N17: 68651.883 | O17: 110343 | P17: =B17/I17*100 -> 60.575957 | Q17: =C17/J17*100 -> 58.387694 | R17: =D17/K17*100 -> 63.844169 | S17: =F17/M17*100 -> 58.217535 | T17: =G17/N17*100 -> 65.07266 | U17: =H17/O17*100 -> 53.603763 | W17: 2519.5274 | X17: 5350.4723 | Z17: 66.752108 | AA17: 59 | AB17: 89 | AC17: 68 | AD17: =SUMPRODUCT($AA$1:$AC$1,AA17:AC17)/SUM($AA$1:$AC$1) -> 68.4 | AF17: 74.124367 | AG17: 74.124367 | AH17: =(Z17-0.8*AG17)/0.2 -> 37.263072 | AI17: =(Z17/Z13-1)*100 -> 3.5841411 | AJ17: =(AF17/AF13-1)*100*$AJ$1 -> 1.7764714 | AK17: =(AD17/AD13-1)*100*$AK$1 -> -0.17241379 | AL17: =AI17-AJ17-AK17 -> 1.9800835 | AN17: 4.0533333 | AO17: 4.26 | AP17: 8.54 | AQ17: =AP17-AN17 -> 4.4866667 | AR17: 2.5712 | AS17: 141.26 | AU17: 2491.8157 | AV17: 7081.8228 | AW17: 1839.3264 | AX17: 732.0729 | AY17: 1398.8729 | AZ17: 5846.6837 | BA17: 3206.7202 | BB17: =AU17+AV17+AW17-AX17-AY17-AZ17-BA17 -> 228.61516 | BC17: =BB17/H17*100 -> 0.38651375 | BD17: =AU17/$U17*100 -> 4648.5835 | BE17: =AV17/$U17*100 -> 13211.429 | BF17: =AW17/$U17*100 -> 3431.3382 | BG17: =AX17/$U17*100 -> 1365.7118 | BH17: =AY17/$U17*100 -> 2609.6544 | BI17: =AZ17/$U17*100 -> 10907.226 | BJ17: =BA17/$U17*100 -> 5982.2669 | BK17: =BD17+BE17+BF17-BG17-BH17-BI17-BJ17 -> 426.49087 | CK17: 64.205576 | CL17: 81.108168 | CM17: 84.806 | CN17: 4.49 | CO17: 67.903 | CP17: 50.360795 | CQ17: 18.497 | CR17: 16.78
A18: 34669 | B18: 28348 | C18: 9678 | D18: 27481.338 | E18: =H18-B18-C18-D18-F18+G18 -> -2430.823 | F18: 46362.483 | G18: 47267.997 | H18: 62171 | I18: 47958 | J18: 16728 | K18: 42781.599 | L18: =O18-I18-J18-K18-M18+N18 -> -3115.3605 | M18: 78701.057 | N18: 71995.296 | O18: 111058 | P18: =B18/I18*100 -> 59.110055 | Q18: =C18/J18*100 -> 57.855093 | R18: =D18/K18*100 -> 64.236349 | S18: =F18/M18*100 -> 58.909606 | T18: =G18/N18*100 -> 65.654286 | U18: =H18/O18*100 -> 55.980659 | W18: 2684.4919 | X18: 5410.5365 | Z18: 67.290089 | AA18: 59 | AB18: 93 | AC18: 68 | AD18: =SUMPRODUCT($AA$1:$AC$1,AA18:AC18)/SUM($AA$1:$AC$1) -> 69.6 | AF18: 74.48447 | AG18: 74.48447 | AH18: =(Z18-0.8*AG18)/0.2 -> 38.512562 | AI18: =(Z18/Z14-1)*100 -> 3.7938599 | AJ18: =(AF18/AF14-1)*100*$AJ$1 -> 1.93445 | AK18: =(AD18/AD14-1)*100*$AK$1 -> 0.057803468 | AL18: =AI18-AJ18-AK18 -> 1.8016064 | AN18: 4.6333333 | AO18: 4.8166667 | AP18: 8.21 | AQ18: =AP18-AN18 -> 3.5766667 | AR18: 2.5607 | AS18: 140.96333 | AU18: 2409.1277 | AV18: 7364.8887 | AW18: 5832.6955 | AX18: 1043.9152 | AY18: 2665.5824 | AZ18: 9157.8273 | BA18: 4534.2121 | BB18: =AU18+AV18+AW18-AX18-AY18-AZ18-BA18 -> -1794.8251 | BC18: =BB18/H18*100 -> -2.8869169 | BD18: =AU18/$U18*100 -> 4303.5001 | BE18: =AV18/$U18*100 -> 13156.131 | BF18: =AW18/$U18*100 -> 10419.126 | BG18: =AX18/$U18*100 -> 1864.7784 | BH18: =AY18/$U18*100 -> 4761.6132 | BI18: =AZ18/$U18*100 -> 16358.913 | BJ18: =BA18/$U18*100 -> 8099.6047 | BK18: =BD18+BE18+BF18-BG18-BH18-BI18-BJ18 -> -3206.1521 | CK18: 65.831577 | CL18: 81.942238 | CM18: 85.341 | CN18: 5.17 | CO18: 68.248 | CP18: 51.088318 | CQ18: 17.657 | CR18: 16.56
... A25: 35309 | B25: 33994 | C25: 8152 | D25: 31805.016 | E25: =H25-B25-C25-D25-F25+G25 -> -1049.9796 | F25: 56802.94 | G25: 55136.976 | H25: 74567 | I25: 54119 | J25: 12614 | K25: 48429.756 | L25: =O25-I25-J25-K25-M25+N25 -> 4945.0807 | M25: 95620.408 | N25: 84944.245 | O25: 130784 | P25: =B25/I25*100 -> 62.81343 | Q25: =C25/J25*100 -> 64.626605 | R25: =D25/K25*100 -> 65.672467 | S25: =F25/M25*100 -> 59.40462 | T25: =G25/N25*100 -> 64.909607 | U25: =H25/O25*100 -> 57.015384 | W25: 3006.2437 | X25: 5604.3436 | Z25: 71.570776 | AA25: 59 | AB25: 88 | AC25: 68 | AD25: =SUMPRODUCT($AA$1:$AC$1,AA25:AC25)/SUM($AA$1:$AC$1) -> 68.1 | AF25: 78.514076 | AG25: 78.514076 | AH25: =(Z25-0.8*AG25)/0.2 -> 43.797578 | AI25: =(Z25/Z21-1)*100 -> 3.600103 | AJ25: =(AF25/AF21-1)*100*$AJ$1 -> 2.6083309 | AK25: =(AD25/AD21-1)*100*$AK$1 -> -0.21551724 | AL25: =AI25-AJ25-AK25 -> 1.2072894 | AN25: 6.9066667 | AO25: 7.22 | AP25: 10.14 | AQ25: =AP25-AN25 -> 3.2333333 | AR25: 2.4951 | AS25: 148.16 | AU25: 3368 | AV25: 8389 | AW25: 1695 | AX25: 959.3644 | AY25: 1394.7677 | AZ25: 7625.8679 | BA25: 4051 | BB25: =AU25+AV25+AW25-AX25-AY25-AZ25-BA25 -> -579 | BC25: =BB25/H25*100 -> -0.77648289 | BD25: =AU25/$U25*100 -> 5907.1776 | BE25: =AV25/$U25*100 -> 14713.573 | BF25: =AW25/$U25*100 -> 2972.8818 | BG25: =AX25/$U25*100 -> 1682.6413 | BH25: =AY25/$U25*100 -> 2446.3006 | BI25: =AZ25/$U25*100 -> 13375.106 | BJ25: =BA25/$U25*100 -> 7105.0999 | BK25: =BD25+BE25+BF25-BG25-BH25-BI25-BJ25 -> -1015.5154 | CK25: 74.947163 | CL25: 86.893889 | CM25: 85.274 | CN25: 5.31 | CO25: 70.617 | CP25: 56.909897 | CQ25: 22.423 | CR25: 20.86
A26: 35400 | B26: 36304 | C26: 10082 | D26: 37298.661 | E26: =H26-B26-C26-D26-F26+G26 -> -5975.9492 | F26: 58073.681 | G26: 57066.392 | H26: 78716 | I26: 58047 | J26: 15550 | K26: 54735.591 | L26: =O26-I26-J26-K26-M26+N26 -> -3173.3916 | M26: 95573.426 | N26: 88077.625 | O26: 132655 | P26: =B26/I26*100 -> 62.542423 | Q26: =C26/J26*100 -> 64.836013 | R26: =D26/K26*100 -> 68.143341 | S26: =F26/M26*100 -> 60.763419 | T26: =G26/N26*100 -> 64.79102 | U26: =H26/O26*100 -> 59.338887 | W26: 3236.7036 | X26: 5685.2538 | Z26: 71.854434 | AA26: 59 | AB26: 88 | AC26: 68 | AD26: =SUMPRODUCT($AA$1:$AC$1,AA26:AC26)/SUM($AA$1:$AC$1) -> 68.1 | AF26: 78.907436 | AG26: 78.907436 | AH26: =(Z26-0.8*AG26)/0.2 -> 43.642427 | AI26: =(Z26/Z22-1)*100 -> 3.3460856 | AJ26: =(AF26/AF22-1)*100*$AJ$1 -> 2.6142394 | AK26: =(AD26/AD22-1)*100*$AK$1 -> -0.21551724 | AL26: =AI26-AJ26-AK26 -> 0.94736342 | AN26: 7.0666667 | AO26: 7.21 | AP26: 10.21 | AQ26: =AP26-AN26 -> 3.1433333 | AR26: 2.5183 | AS26: 147.98 | AU26: 3257 | AV26: 9780 | AW26: 5358 | AX26: 1393.7515 | AY26: 2657.7597 | AZ26: 12045.489 | BA26: 5728 | BB26: =AU26+AV26+AW26-AX26-AY26-AZ26-BA26 -> -3430 | BC26: =BB26/H26*100 -> -4.3574369 | BD26: =AU26/$U26*100 -> 5488.8121 | BE26: =AV26/$U26*100 -> 16481.603 | BF26: =AW26/$U26*100 -> 9029.492 | BG26: =AX26/$U26*100 -> 2348.7995 | BH26: =AY26/$U26*100 -> 4478.9511 | BI26: =AZ26/$U26*100 -> 20299.486 | BJ26: =BA26/$U26*100 -> 9653.0291 | BK26: =BD26+BE26+BF26-BG26-BH26-BI26-BJ26 -> -5780.3579 | BM26: 0.12970698 | BN26: =BM26*BO26 -> 43227.508 | BO26: 333270.49 | BP26: 513968.42 | BQ26: 13850.228 | BR26: 319305.1 | BS26: =BM26*BR26 -> 41416.1 | BT26: =BR26-BS26 -> 277889 | BU26: 180813.09 | BV26: 40868.974 | BW26: 21226.688 | BX26: 358769.48 | BY26: 93103.276 | BZ26: =BP26/$U26*100 -> 866157.84 | CA26: =BQ26/$U26*100 -> 23340.897 | CB26: =BR26/$U26*100 -> 538104.3 | CC26: =BS26/$U26*100 -> 69795.884 | CD26: =BT26/$U26*100 -> 468308.41 | CE26: =BU26/$U26*100 -> 304712.64 | CF26: =BV26/$U26*100 -> 68873.847 | CG26: =BW26/$U26*100 -> 35771.97 | ... CI26: =BY26/$U26*100 -> 156900.95 | CK26: 76.798273 | CL26: 87.854615 | CM26: 84.399 | CN26: 5.28 | CO26: 71.019 | CP26: 58.251899 | CQ26: 24.667 | CR26: 23.58
A27: 35490 | B27: 37781 | C27: 5668 | D27: 31163.84 | E27: =H27-B27-C27-D27-F27+G27 -> -5018.1431 | F27: 55900.307 | G27: 53639.004 | H27: 71856 | I27: 57893 | J27: 8808 | K27: 46088.032 | L27: =O27-I27-J27-K27-M27+N27 -> 1178.9567 | M27: 97495.322 | N27: 84164.311 | O27: 127299 | P27: =B27/I27*100 -> 65.260049 | Q27: =C27/J27*100 -> 64.35059 | R27: =D27/K27*100 -> 67.618075 | S27: =F27/M27*100 -> 57.336399 | T27: =G27/N27*100 -> 63.731293 | U27: =H27/O27*100 -> 56.446634 | W27: 3161.2539 | X27: 5903.1293 | Z27: 72.878912 | AA27: 59 | AB27: 88 | AC27: 68 | AD27: =SUMPRODUCT($AA$1:$AC$1,AA27:AC27)/SUM($AA$1:$AC$1) -> 68.1 | AF27: 79.727141 | AG27: 79.727141 | AH27: =(Z27-0.8*AG27)/0.2 -> 45.485992 | AI27: =(Z27/Z23-1)*100 -> 3.1801178 | AJ27: =(AF27/AF23-1)*100*$AJ$1 -> 2.5389678 | AK27: =(AD27/AD23-1)*100*$AK$1 -> -0.1447178 | AL27: =AI27-AJ27-AK27 -> 0.78586778 | AN27: 7.0586667 | AO27: 7.2266667 | AP27: 10.15 | AQ27: =AP27-AN27 -> 3.0913333 | AR27: 2.4845 | AS27: 154.76333 | AU27: 3723 | AV27: 8534 | AW27: 2034 | AX27: 1288.381 | AY27: 890.13978 | AZ27: 6759.4792 | BA27: 1544 | BB27: =AU27+AV27+AW27-AX27-AY27-AZ27-BA27 -> 3809 | BC27: =BB27/H27*100 -> 5.3008795 | BD27: =AU27/$U27*100 -> 6595.6103 | BE27: =AV27/$U27*100 -> 15118.705 | BF27: =AW27/$U27*100 -> 3603.4036 | BG27: =AX27/$U27*100 -> 2282.4762 | BH27: =AY27/$U27*100 -> 1576.9581 | BI27: =AZ27/$U27*100 -> 11974.991 | BJ27: =BA27/$U27*100 -> 2735.327 | BK27: =BD27+BE27+BF27-BG27-BH27-BI27-BJ27 -> 6747.9666 | BM27: 0.12174573 | BN27: =BM27*BO27 -> 43794.584 | BO27: 359721.73 | BP27: 553444.67 | BQ27: 13749.253 | BR27: 344769.7 | BS27: =BM27*BR27 -> 41974.239 | BT27: =BR27-BS27 -> 302795.46 | BU27: 194925.72 | BV27: 46971.782 | BW27: 29059.668 | BX27: 378104.49 | BY27: 99308.728 | BZ27: =BP27/$U27*100 -> 980474.19 | CA27: =BQ27/$U27*100 -> 24357.968 | CB27: =BR27/$U27*100 -> 610788.78 | CC27: =BS27/$U27*100 -> 74360.925 | CD27: =BT27/$U27*100 -> 536427.85 | CE27: =BU27/$U27*100 -> 345327.44 | CF27: =BV27/$U27*100 -> 83214.497 | CG27: =BW27/$U27*100 -> 51481.668 | ... CI27: =BY27/$U27*100 -> 175933.84 | CK27: 78.793163 | CL27: 88.73199 | CM27: 84.16 | CN27: 5.28 | CO27: 71.298 | CP27: 56.059259 | CQ27: 22.79 | CR27: 21.22
A28: 35582 | B28: 35154 | C28: 7136 | D28: 36922.519 | E28: =H28-B28-C28-D28-F28+G28 -> -636.79911 | F28: 56697.884 | G28: 60135.604 | H28: 75138 | I28: 53465 | J28: 10860 | K28: 52749.99 | L28: =O28-I28-J28-K28-M28+N28 -> 13941.358 | M28: 96139.193 | N28: 94527.541 | O28: 132628 | P28: =B28/I28*100 -> 65.751426 | Q28: =C28/J28*100 -> 65.709024 | R28: =D28/K28*100 -> 69.99531 | S28: =F28/M28*100 -> 58.974787 | T28: =G28/N28*100 -> 63.61702 | U28: =H28/O28*100 -> 56.653195 | W28: 3206.1361 | X28: 6055.7736 | Z28: 72.894962 | AA28: 59 | AB28: 92 | AC28: 68 | AD28: =SUMPRODUCT($AA$1:$AC$1,AA28:AC28)/SUM($AA$1:$AC$1) -> 69.3 | AF28: 80.117734 | AG28: 80.117734 | AH28: =(Z28-0.8*AG28)/0.2 -> 44.003872 | AI28: =(Z28/Z24-1)*100 -> 2.4665771 | AJ28: =(AF28/AF24-1)*100*$AJ$1 -> 2.421912 | AK28: =(AD28/AD24-1)*100*$AK$1 -> 0.17621145 | AL28: =AI28-AJ28-AK28 -> -0.13154637 | AN28: 8.1946667 | AO28: 7.3266667 | AP28: 10.523333 | AQ28: =AP28-AN28 -> 2.3286667 | AR28: 2.5087 | AS28: 154.11667 | AU28: 2945 | AV28: 10483 | AW28: 2595 | AX28: 807.17555 | AY28: 1703.4039 | AZ28: 6508.4206 | BA28: 3255 | BB28: =AU28+AV28+AW28-AX28-AY28-AZ28-BA28 -> 3749 | BC28: =BB28/H28*100 -> 4.989486 | BD28: =AU28/$U28*100 -> 5198.2946 | BE28: =AV28/$U28*100 -> 18503.811 | BF28: =AW28/$U28*100 -> 4580.5007 | BG28: =AX28/$U28*100 -> 1424.7661 | BH28: =AY28/$U28*100 -> 3006.7216 | BI28: =AZ28/$U28*100 -> 11488.179 | BJ28: =BA28/$U28*100 -> 5745.4835 | BK28: =BD28+BE28+BF28-BG28-BH28-BI28-BJ28 -> 6617.4555 | BM28: 0.12940018 | BN28: =BM28*BO28 -> 49377.053 | BO28: 381584.12 | BP28: 607217.69 | BQ28: 14003.799 | BR28: 365589.49 | BS28: =BM28*BR28 -> 47307.344 | BT28: =BR28-BS28 -> 318282.14 | BU28: 227624.41 | BV28: 57737.627 | BW28: 32789.617 | BX28: 398334.52 | BY28: 118355.92 | BZ28: =BP28/$U28*100 -> 1071815.4 | CA28: =BQ28/$U28*100 -> 24718.462 | CB28: =BR28/$U28*100 -> 645311.33 | CC28: =BS28/$U28*100 -> 83503.4 | CD28: =BT28/$U28*100 -> 561807.93 | CE28: =BU28/$U28*100 -> 401785.64 | CF28: =BV28/$U28*100 -> 101914.16 | CG28: =BW28/$U28*100 -> 57877.789 | ... CI28: =BY28/$U28*100 -> 208913.06 | CK28: 81.267947 | CL28: 89.714659 | CM28: 84.104 | CN28: 5.52 | CO28: 71.67 | CP28: 53.892031 | CQ28: 19.907 | CR28: 18.05
A29: 35674 | B29: 37893 | C29: 7458 | D29: 38677.45 | E29: =H29-B29-C29-D29-F29+G29 -> -4125.9027 | F29: 65111.464 | G29: 62930.012 | H29: 82084 | I29: 57368 | J29: 11349 | K29: 57906.99 | L29: =O29-I29-J29-K29-M29+N29 -> 2464.4033 | M29: 102188.37 | N29: 91015.767 | O29: 140261 | P29: =B29/I29*100 -> 66.052503 | Q29: =C29/J29*100 -> 65.715041 | R29: =D29/K29*100 -> 66.792368 | S29: =F29/M29*100 -> 63.717096 | T29: =G29/N29*100 -> 69.141879 | U29: =H29/O29*100 -> 58.522326 | W29: 3268.7635 | X29: 5954.5442 | Z29: 73.214046 | AA29: 59 | AB29: 94 | AC29: 68 | AD29: =SUMPRODUCT($AA$1:$AC$1,AA29:AC29)/SUM($AA$1:$AC$1) -> 69.9 | AF29: 80.367979 | AG29: 80.367979 | AH29: =(Z29-0.8*AG29)/0.2 -> 44.598315 | AI29: =(Z29/Z25-1)*100 -> 2.2960075 | AJ29: =(AF29/AF25-1)*100*$AJ$1 -> 1.8889898 | AK29: =(AD29/AD25-1)*100*$AK$1 -> 0.26431718 | AL29: =AI29-AJ29-AK29 -> 0.1427005 | AN29: 7.5613333 | AO29: 7.6533333 | AP29: 10.74 | AQ29: =AP29-AN29 -> 3.1786667 | AR29: 2.7854 | AS29: 142.38333 | AU29: 3966 | AV29: 9631 | AW29: 2922 | AX29: 1011.2391 | AY29: 1319.0253 | AZ29: 8343.7356 | BA29: 3066 | BB29: =AU29+AV29+AW29-AX29-AY29-AZ29-BA29 -> 2779 | BC29: =BB29/H29*100 -> 3.3855563 | BD29: =AU29/$U29*100 -> 6776.9008 | BE29: =AV29/$U29*100 -> 16456.967 | BF29: =AW29/$U29*100 -> 4992.9663 | BG29: =AX29/$U29*100 -> 1727.9543 | BH29: =AY29/$U29*100 -> 2253.8839 | BI29: =AZ29/$U29*100 -> 14257.355 | BJ29: =BA29/$U29*100 -> 5239.0262 | BK29: =BD29+BE29+BF29-BG29-BH29-BI29-BJ29 -> 4748.6151 | BM29: 0.13642773 | BN29: =BM29*BO29 -> 54820.825 | BO29: 401830.53 | BP29: 639531.26 | BQ29: 15006.982 | BR29: 384748.84 | BS29: =BM29*BR29 -> 52490.409 | BT29: =BR29-BS29 -> 332258.43 | BU29: 239775.44 | BV29: 52021.1 | BW29: 36343.38 | BX29: 408796.89 | BY29: 142369.89 | BZ29: =BP29/$U29*100 -> 1092798.8 | CA29: =BQ29/$U29*100 -> 25643.174 | CB29: =BR29/$U29*100 -> 657439.41 | CC29: =BS29/$U29*100 -> 89692.963 | CD29: =BT29/$U29*100 -> 567746.45 | CE29: =BU29/$U29*100 -> 409716.18 | CF29: =BV29/$U29*100 -> 88891.032 | CG29: =BW29/$U29*100 -> 62101.735 | ... CI29: =BY29/$U29*100 -> 243274.49 | CK29: 83.227116 | CL29: 90.553315 | CM29: 83.891 | CN29: 5.53 | CO29: 71.837 | CP29: 52.462664 | CQ29: 19.783 | CR29: 18.51
A30: 35765 | B30: 37945 | C30: 11815 | D30: 38904.938 | E30: =H30-B30-C30-D30-F30+G30 -> -713.42923 | F30: 74644.569 | G30: 72788.078 | H30: 89808 | I30: 57852 | J30: 17819 | K30: 56021.225 | L30: =O30-I30-J30-K30-M30+N30 -> -5222.5519 | M30: 100582.68 | N30: 86245.349 | O30: 140807 | P30: =B30/I30*100 -> 65.589781 | Q30: =C30/J30*100 -> 66.305629 | R30: =D30/K30*100 -> 69.446782 | S30: =F30/M30*100 -> 74.212154 | T30: =G30/N30*100 -> 84.396527 | U30: =H30/O30*100 -> 63.78092 | W30: 3494.9271 | X30: 6320.6805 | Z30: 73.804113 | AA30: 59 | AB30: 94 | AC30: 68 | AD30: =SUMPRODUCT($AA$1:$AC$1,AA30:AC30)/SUM($AA$1:$AC$1) -> 69.9 | AF30: 80.827224 | AG30: 80.827224 | AH30: =(Z30-0.8*AG30)/0.2 -> 45.711668 | AI30: =(Z30/Z26-1)*100 -> 2.7133734 | AJ30: =(AF30/AF26-1)*100*$AJ$1 -> 1.9463702 | AK30: =(AD30/AD26-1)*100*$AK$1 -> 0.26431718 | AL30: =AI30-AJ30-AK30 -> 0.50268598 | AN30: 7.4626667 | AO30: 8.9 | AP30: 11.096667 | AQ30: =AP30-AN30 -> 3.634 | AR30: 3.4961 | AS30: 119.17 | AU30: 3437 | AV30: 10908 | AW30: 4558 | AX30: 1489.2044 | AY30: 2513.4311 | AZ30: 12031.365 | BA30: 6580 | BB30: =AU30+AV30+AW30-AX30-AY30-AZ30-BA30 -> -3711 | BC30: =BB30/H30*100 -> -4.1321486 | BD30: =AU30/$U30*100 -> 5388.7589 | BE30: =AV30/$U30*100 -> 17102.293 | BF30: =AW30/$U30*100 -> 7146.3378 | BG30: =AX30/$U30*100 -> 2334.8744 | BH30: =AY30/$U30*100 -> 3940.7256 | BI30: =AZ30/$U30*100 -> 18863.579 | BJ30: =BA30/$U30*100 -> 10316.565 | BK30: =BD30+BE30+BF30-BG30-BH30-BI30-BJ30 -> -5818.3545 | BM30: 0.13666521 | BN30: =BM30*BO30 -> 57607.164 | BO30: 421520.31 | BP30: 676934.97 | BQ30: 18019.65 | BR30: 401865.43 | BS30: =BM30*BR30 -> 54921.026 | BT30: =BR30-BS30 -> 346944.41 | BU30: 257049.89 | BV30: 52054.528 | BW30: 40318.264 | BX30: 435046.67 | BY30: 149515.51 | BZ30: =BP30/$U30*100 -> 1061344 | CA30: =BQ30/$U30*100 -> 28252.414 | CB30: =BR30/$U30*100 -> 630071.55 | CC30: =BS30/$U30*100 -> 86108.864 | CD30: =BT30/$U30*100 -> 543962.69 | CE30: =BU30/$U30*100 -> 403020.04 | CF30: =BV30/$U30*100 -> 81614.577 | CG30: =BW30/$U30*100 -> 63213.675 | ... CI30: =BY30/$U30*100 -> 234420.44 | CK30: 84.205155 | CL30: 91.37373 | CM30: 83.518 | CN30: 5.51 | CO30: 72.065 | CP30: 51.565524 | CQ30: 19.917 | CR30: 18.76
A31: 35855 | B31: 36231 | C31: 5440 | D31: 26509.833 | E31: =H31-B31-C31-D31-F31+G31 -> -80.0726 | F31: 77384.938 | G31: 67233.699 | H31: 78252 | I31: 52628 | J31: 8423 | K31: 35140.48 | L31: =O31-I31-J31-K31-M31+N31 -> 8698.2943 | M31: 96637.115 | N31: 76181.89 | O31: 125345 | P31: =B31/I31*100 -> 68.843581 | Q31: =C31/J31*100 -> 64.585065 | R31: =D31/K31*100 -> 75.439587 | S31: =F31/M31*100 -> 80.077865 | T31: =G31/N31*100 -> 88.254176 | U31: =H31/O31*100 -> 62.429295 | W31: 3348.2355 | X31: 6283.5318 | Z31: 76.014331 | AA31: 59 | AB31: 94 | AC31: 68 | AD31: =SUMPRODUCT($AA$1:$AC$1,AA31:AC31)/SUM($AA$1:$AC$1) -> 69.9 | AF31: 82.664781 | AG31: 82.664781 | AH31: =(Z31-0.8*AG31)/0.2 -> 49.41253 | AI31: =(Z31/Z27-1)*100 -> 4.3022307 | AJ31: =(AF31/AF27-1)*100*$AJ$1 -> 2.9476929 | AK31: =(AD31/AD27-1)*100*$AK$1 -> 0.26431718 | AL31: =AI31-AJ31-AK31 -> 1.0902206 | AN31: 9.9893333 | AO31: 9.4466667 | AP31: 12.543333 | AQ31: =AP31-AN31 -> 2.554 | AR31: 3.9848 | AS31: 110.46 | AU31: 3621 | AV31: 8108 | AW31: 2083 | AX31: 1310.4892 | AY31: 959.67762 | AZ31: 6164.8332 | BA31: 1174 | BB31: =AU31+AV31+AW31-AX31-AY31-AZ31-BA31 -> 4203 | BC31: =BB31/H31*100 -> 5.3711087 | BD31: =AU31/$U31*100 -> 5800.1616 | BE31: =AV31/$U31*100 -> 12987.492 | BF31: =AW31/$U31*100 -> 3336.5746 | BG31: =AX31/$U31*100 -> 2099.1574 | BH31: =AY31/$U31*100 -> 1537.2232 | BI31: =AZ31/$U31*100 -> 9874.9044 | BJ31: =BA31/$U31*100 -> 1880.5274 | BK31: =BD31+BE31+BF31-BG31-BH31-BI31-BJ31 -> 6732.4162 | BM31: 0.13108477 | BN31: =BM31*BO31 -> 55111.672 | BO31: 420427.74 | BP31: 642532.04 | BQ31: 17099.349 | BR31: 399558.72 | BS31: =BM31*BR31 -> 52376.062 | BT31: =BR31-BS31 -> 347182.66 | BU31: 225873.96 | BV31: 53144.713 | BW31: 31127.233 | BX31: 430778 | BY31: 127482.09 | BZ31: =BP31/$U31*100 -> 1029215.6 | CA31: =BQ31/$U31*100 -> 27389.944 | CB31: =BR31/$U31*100 -> 640018 | CC31: =BS31/$U31*100 -> 83896.609 | CD31: =BT31/$U31*100 -> 556121.39 | CE31: =BU31/$U31*100 -> 361807.65 | CF31: =BV31/$U31*100 -> 85127.844 | CG31: =BW31/$U31*100 -> 49859.978 | ... CI31: =BY31/$U31*100 -> 204202.36 | CK31: 86.125276 | CL31: 92.046631 | CM31: 82.678 | CN31: 5.52 | CO31: 72.277 | CP31: 49.142449 | CQ31: 15.93 | CR31: 14.1
A32: 35947 | B32: 32926 | C32: 6950 | D32: 22753.74 | E32: =H32-B32-C32-D32-F32+G32 -> 1764.7158 | F32: 75464.544 | G32: 62028.999 | H32: 77830 | I32: 48667 | J32: 10526 | K32: 30141.04 | L32: =O32-I32-J32-K32-M32+N32 -> 8891.4523 | M32: 97553.286 | N32: 71008.778 | O32: 124770 | P32: =B32/I32*100 -> 67.655701 | Q32: =C32/J32*100 -> 66.026981 | R32: =D32/K32*100 -> 75.490892 | S32: =F32/M32*100 -> 77.357254 | T32: =G32/N32*100 -> 87.353988 | U32: =H32/O32*100 -> 62.378777 | W32: 3326.0414 | X32: 5517.0761 | Z32: 77.070328 | AA32: 59 | AB32: 94 | AC32: 68 | AD32: =SUMPRODUCT($AA$1:$AC$1,AA32:AC32)/SUM($AA$1:$AC$1) -> 69.9 | AF32: 83.874289 | AG32: 83.874289 | AH32: =(Z32-0.8*AG32)/0.2 -> 49.854484 | AI32: =(Z32/Z28-1)*100 -> 5.7279222 | AJ32: =(AF32/AF28-1)*100*$AJ$1 -> 3.7510349 | AK32: =(AD32/AD28-1)*100*$AK$1 -> 0.086580087 | AL32: =AI32-AJ32-AK32 -> 1.8903072 | AN32: 10.065667 | AO32: 10.026667 | AP32: 13.513333 | AQ32: =AP32-AN32 -> 3.4476667 | AR32: 3.8539 | AS32: 114.02667 | AU32: 2585 | AV32: 8811 | AW32: 2654 | AX32: 835.55439 | AY32: 1836.474 | AZ32: 9355.9716 | BA32: 2405 | BB32: =AU32+AV32+AW32-AX32-AY32-AZ32-BA32 -> -383 | BC32: =BB32/H32*100 -> -0.49209816 | BD32: =AU32/$U32*100 -> 4144.0376 | BE32: =AV32/$U32*100 -> 14124.996 | BF32: =AW32/$U32*100 -> 4254.6522 | BG32: =AX32/$U32*100 -> 1339.485 | BH32: =AY32/$U32*100 -> 2944.0686 | BI32: =AZ32/$U32*100 -> 14998.645 | BJ32: =BA32/$U32*100 -> 3855.478 | BK32: =BD32+BE32+BF32-BG32-BH32-BI32-BJ32 -> -613.99088 | BM32: 0.12532295 | BN32: =BM32*BO32 -> 52702.113 | BO32: 420530.42 | BP32: 623665.25 | BQ32: 18149.365 | BR32: 400007.16 | BS32: =BM32*BR32 -> 50130.077 | BT32: =BR32-BS32 -> 349877.08 | BU32: 205508.73 | BV32: 49244.661 | BW32: 29758.358 | BX32: 422342.26 | BY32: 122319.97 | BZ32: =BP32/$U32*100 -> 999803.58 | CA32: =BQ32/$U32*100 -> 29095.416 | CB32: =BR32/$U32*100 -> 641255.21 | CC32: =BS32/$U32*100 -> 80363.995 | CD32: =BT32/$U32*100 -> 560891.21 | CE32: =BU32/$U32*100 -> 329452.96 | CF32: =BV32/$U32*100 -> 78944.575 | CG32: =BW32/$U32*100 -> 47705.902 | ... CI32: =BY32/$U32*100 -> 196092.29 | CK32: 86.478154 | CL32: 92.730958 | CM32: 82.234 | CN32: 5.5 | CO32: 72.498 | CP32: 48.160079 | CQ32: 14.653 | CR32: 13.31
A33: 36039 | B33: 33683 | C33: 7612 | D33: 19404.037 | E33: =H33-B33-C33-D33-F33+G33 -> 4357.7668 | F33: 80377.549 | G33: 63211.353 | H33: 82223 | I33: 50309 | J33: 11547 | K33: 25222.515 | L33: =O33-I33-J33-K33-M33+N33 -> 9567.6723 | M33: 99868.272 | N33: 70513.46 | O33: 126001 | P33: =B33/I33*100 -> 66.952235 | Q33: =C33/J33*100 -> 65.921884 | R33: =D33/K33*100 -> 76.931411 | S33: =F33/M33*100 -> 80.483568 | T33: =G33/N33*100 -> 89.644378 | U33: =H33/O33*100 -> 65.255831 | W33: 3325.7469 | X33: 5032.894 | Z33: 77.366528 | AA33: 59 | AB33: 94 | AC33: 68 | AD33: =SUMPRODUCT($AA$1:$AC$1,AA33:AC33)/SUM($AA$1:$AC$1) -> 69.9 | AF33: 84.468656 | AG33: 84.468656 | AH33: =(Z33-0.8*AG33)/0.2 -> 48.958016 | AI33: =(Z33/Z29-1)*100 -> 5.6717012 | AJ33: =(AF33/AF29-1)*100*$AJ$1 -> 4.0819014 | AK33: =(AD33/AD29-1)*100*$AK$1 -> 0 | AL33: =AI33-AJ33-AK33 -> 1.5897998 | AN33: 8.461 | AO33: 8.6466667 | AP33: 12.556667 | AQ33: =AP33-AN33 -> 4.0956667 | AR33: 4.0591 | AS33: 110.56667 | AU33: 3052 | AV33: 8004 | AW33: 3378 | AX33: 1057.4162 | AY33: 1422.0677 | AZ33: 6871.5161 | BA33: 3585 | BB33: =AU33+AV33+AW33-AX33-AY33-AZ33-BA33 -> 1498 | BC33: =BB33/H33*100 -> 1.8218747 | BD33: =AU33/$U33*100 -> 4676.9767 | BE33: =AV33/$U33*100 -> 12265.571 | BF33: =AW33/$U33*100 -> 5176.5489 | BG33: =AX33/$U33*100 -> 1620.4163 | BH33: =AY33/$U33*100 -> 2179.2194 | BI33: =AZ33/$U33*100 -> 10530.118 | BJ33: =BA33/$U33*100 -> 5493.7619 | BK33: =BD33+BE33+BF33-BG33-BH33-BI33-BJ33 -> 2295.5803 | BM33: 0.12150674 | BN33: =BM33*BO33 -> 51017.668 | BO33: 419875.2 | BP33: 610015.4 | BQ33: 18783.588 | BR33: 400185.34 | BS33: =BM33*BR33 -> 48625.217 | BT33: =BR33-BS33 -> 351560.12 | BU33: 191046.47 | BV33: 48426.414 | BW33: 23841.177 | BX33: 423051.24 | BY33: 114696.57 | BZ33: =BP33/$U33*100 -> 934805.96 | CA33: =BQ33/$U33*100 -> 28784.535 | CB33: =BR33/$U33*100 -> 613256.06 | CC33: =BS33/$U33*100 -> 74514.747 | CD33: =BT33/$U33*100 -> 538741.31 | CE33: =BU33/$U33*100 -> 292765.36 | CF33: =BV33/$U33*100 -> 74210.095 | CG33: =BW33/$U33*100 -> 36534.937 | ... CI33: =BY33/$U33*100 -> 175764.48 | CK33: 87.155225 | CL33: 93.465965 | CM33: 81.561 | CN33: 5.53 | CO33: 72.756 | CP33: 45.148292 | CQ33: 14.13 | CR33: 12.46
A34: 36130 | B34: 34224 | C34: 9111 | D34: 22388.847 | E34: =H34-B34-C34-D34-F34+G34 -> -3418.4686 | F34: 81415.211 | G34: 61927.589 | H34: 81793 | I34: 51757 | J34: 13798 | K34: 30832.059 | L34: =O34-I34-J34-K34-M34+N34 -> -4095.0652 | M34: 104276.15 | N34: 71505.144 | O34: 125063 | P34: =B34/I34*100 -> 66.124389 | Q34: =C34/J34*100 -> 66.031309 | R34: =D34/K34*100 -> 72.615477 | S34: =F34/M34*100 -> 78.076541 | T34: =G34/N34*100 -> 86.605783 | U34: =H34/O34*100 -> 65.401438 | W34: 3487.56 | X34: 4955.7102 | Z34: 77.770288 | AA34: 59 | AB34: 94 | AC34: 68 | AD34: =SUMPRODUCT($AA$1:$AC$1,AA34:AC34)/SUM($AA$1:$AC$1) -> 69.9 | AF34: 84.664628 | AG34: 84.664628 | AH34: =(Z34-0.8*AG34)/0.2 -> 50.192927 | AI34: =(Z34/Z30-1)*100 -> 5.3739208 | AJ34: =(AF34/AF30-1)*100*$AJ$1 -> 3.7981297 | AK34: =(AD34/AD30-1)*100*$AK$1 -> 0 | AL34: =AI34-AJ34-AK34 -> 1.575791 | AN34: 5.9446667 | AO34: 5.9333333 | AP34: 10.013333 | AQ34: =AP34-AN34 -> 4.0686667 | AR34: 3.8005 | AS34: 111.03 | AU34: 2934 | AV34: 8221 | AW34: 3259 | AX34: 1605.5403 | AY34: 2709.7806 | AZ34: 10454.679 | BA34: 9964 | BB34: =AU34+AV34+AW34-AX34-AY34-AZ34-BA34 -> -10320 | BC34: =BB34/H34*100 -> -12.617217 | BD34: =AU34/$U34*100 -> 4486.1399 | BE34: =AV34/$U34*100 -> 12570.06 | BF34: =AW34/$U34*100 -> 4983.0709 | BG34: =AX34/$U34*100 -> 2454.9006 | BH34: =AY34/$U34*100 -> 4143.3044 | BI34: =AZ34/$U34*100 -> 15985.396 | BJ34: =BA34/$U34*100 -> 15235.139 | BK34: =BD34+BE34+BF34-BG34-BH34-BI34-BJ34 -> -15779.47 | BM34: 0.12326917 | BN34: =BM34*BO34 -> 51014.259 | BO34: 413844.41 | BP34: 616319.13 | BQ34: 19160.615 | BR34: 394421.65 | BS34: =BM34*BR34 -> 48620.03 | BT34: =BR34-BS34 -> 345801.61 | BU34: 202736.86 | BV34: 48945.985 | BW34: 27461.932 | BX34: 433388.53 | BY34: 106522.68 | BZ34: =BP34/$U34*100 -> 942363.27 | CA34: =BQ34/$U34*100 -> 29296.933 | CB34: =BR34/$U34*100 -> 603077.94 | CC34: =BS34/$U34*100 -> 74340.92 | CD34: =BT34/$U34*100 -> 528737.02 | CE34: =BU34/$U34*100 -> 309988.39 | CF34: =BV34/$U34*100 -> 74839.311 | CG34: =BW34/$U34*100 -> 41989.799 | ... CI34: =BY34/$U34*100 -> 162875.14 | CK34: 87.976281 | CL34: 94.291183 | CM34: 81.249 | CN34: 4.86 | CO34: 72.988 | CP34: 43.818511 | CQ34: 12.84 | CR34: 11.21
A35: 36220 | B35: 35694 | C35: 6364 | D35: 18111.634 | E35: =H35-B35-C35-D35-F35+G35 -> -796.19209 | F35: 75461.771 | G35: 60124.214 | H35: 74711 | I35: 51225 | J35: 9629 | K35: 26335.079 | L35: =O35-I35-J35-K35-M35+N35 -> 8041.3134 | M35: 98670.274 | N35: 69796.666 | O35: 124104 | P35: =B35/I35*100 -> 69.68082 | Q35: =C35/J35*100 -> 66.092014 | R35: =D35/K35*100 -> 68.7738 | S35: =F35/M35*100 -> 76.478729 | T35: =G35/N35*100 -> 86.141956 | U35: =H35/O35*100 -> 60.200316 | W35: 3472.8805 | X35: 5219.7224 | Z35: 79.061583 | AA35: 59 | AB35: 94 | AC35: 68 | AD35: =SUMPRODUCT($AA$1:$AC$1,AA35:AC35)/SUM($AA$1:$AC$1) -> 69.9 | AF35: 85.167747 | AG35: 85.167747 | AH35: =(Z35-0.8*AG35)/0.2 -> 54.636929 | AI35: =(Z35/Z31-1)*100 -> 4.0087871 | AJ35: =(AF35/AF31-1)*100*$AJ$1 -> 2.4222805 | AK35: =(AD35/AD31-1)*100*$AK$1 -> 0 | AL35: =AI35-AJ35-AK35 -> 1.5865065 | AN35: 5.2136667 | AO35: 5.5833333 | AP35: 9.58 | AQ35: =AP35-AN35 -> 4.3663333 | AR35: 3.8 | AS35: 111.91667 | AU35: 2964 | AV35: 6044 | AW35: 2310 | AX35: 1354 | AY35: 1100 | AZ35: 6744 | BA35: 873 | BB35: =AU35+AV35+AW35-AX35-AY35-AZ35-BA35 -> 1247 | BC35: =BB35/H35*100 -> 1.6690983 | BD35: =AU35/$U35*100 -> 4923.5622 | BE35: =AV35/$U35*100 -> 10039.814 | BF35: =AW35/$U35*100 -> 3837.1892 | BG35: =AX35/$U35*100 -> 2249.1576 | BH35: =AY35/$U35*100 -> 1827.2329 | BI35: =AZ35/$U35*100 -> 11202.599 | BJ35: =BA35/$U35*100 -> 1450.1585 | BK35: =BD35+BE35+BF35-BG35-BH35-BI35-BJ35 -> 2071.4177 | BM35: 0.12439319 | BN35: =BM35*BO35 -> 50077.3 | BO35: 402572.69 | BP35: 617111.18 | BQ35: 18580.662 | BR35: 385190.16 | BS35: =BM35*BR35 -> 47915.032 | BT35: =BR35-BS35 -> 337275.13 | BU35: 213340.35 | BV35: 48398.884 | BW35: 26496.921 | BX35: 438435.22 | BY35: 103780.15 | BZ35: =BP35/$U35*100 -> 1025096.2 | CA35: =BQ35/$U35*100 -> 30864.724 | CB35: =BR35/$U35*100 -> 639847.41 | CC35: =BS35/$U35*100 -> 79592.658 | CD35: =BT35/$U35*100 -> 560254.75 | CE35: =BU35/$U35*100 -> 354384.11 | CF35: =BV35/$U35*100 -> 80396.395 | CG35: =BW35/$U35*100 -> 44014.588 | ... CI35: =BY35/$U35*100 -> 172391.37 | CK35: 88.936011 | CL35: 95.215539 | CM35: 81.052 | CN35: 4.73 | CO35: 73.171 | CP35: 42.049951 | CQ35: 13.047 | CR35: 11.37
A36: 36312 | B36: 34310 | C36: 7430 | D36: 18599.203 | E36: =H36-B36-C36-D36-F36+G36 -> 3832.2801 | F36: 83911.453 | G36: 66352.937 | H36: 81730 | I36: 49434 | J36: 11027 | K36: 26791.331 | L36: =O36-I36-J36-K36-M36+N36 -> 10852.767 | M36: 109959.03 | N36: 77315.127 | O36: 130749 | P36: =B36/I36*100 -> 69.405672 | Q36: =C36/J36*100 -> 67.380067 | R36: =D36/K36*100 -> 69.422468 | S36: =F36/M36*100 -> 76.311563 | T36: =G36/N36*100 -> 85.821415 | U36: =H36/O36*100 -> 62.509082 | W36: 3425.2936 | X36: 5325.3495 | Z36: 79.113928 | AA36: 58.666667 | AB36: 94 | AC36: 68 | AD36: =SUMPRODUCT($AA$1:$AC$1,AA36:AC36)/SUM($AA$1:$AC$1) -> 69.681481 | AF36: 85.46324 | AG36: 85.46324 | AH36: =(Z36-0.8*AG36)/0.2 -> 53.716681 | AI36: =(Z36/Z32-1)*100 -> 2.6516041 | AJ36: =(AF36/AF32-1)*100*$AJ$1 -> 1.5155545 | AK36: =(AD36/AD32-1)*100*$AK$1 -> -0.031261591 | AL36: =AI36-AJ36-AK36 -> 1.1673112 | AN36: 3.0656667 | AO36: 3.8333333 | AP36: 8.7366667 | AQ36: =AP36-AN36 -> 5.671 | AR36: 3.8 | AS36: 113.43667 | AU36: 3288 | AV36: 9050 | AW36: 3160 | AX36: 859 | AY36: 2105 | AZ36: 7094 | BA36: 5317 | BB36: =AU36+AV36+AW36-AX36-AY36-AZ36-BA36 -> 123 | BC36: =BB36/H36*100 -> 0.15049553 | BD36: =AU36/$U36*100 -> 5260.0356 | BE36: =AV36/$U36*100 -> 14477.896 | BF36: =AW36/$U36*100 -> 5055.2654 | BG36: =AX36/$U36*100 -> 1374.2003 | BH36: =AY36/$U36*100 -> 3367.5106 | BI36: =AZ36/$U36*100 -> 11348.751 | BJ36: =BA36/$U36*100 -> 8505.9639 | BK36: =BD36+BE36+BF36-BG36-BH36-BI36-BJ36 -> 196.77141 | BM36: 0.12807426 | BN36: =BM36*BO36 -> 51588.025 | BO36: 402797.77 | BP36: 629758.62 | BQ36: 19600.767 | BR36: 386152.23 | BS36: =BM36*BR36 -> 49456.16 | BT36: =BR36-BS36 -> 336696.07 | BU36: 224005.63 | BV36: 47261.851 | BW36: 26526.015 | BX36: 448642.93 | BY36: 107327.83 | BZ36: =BP36/$U36*100 -> 1007467.4 | CA36: =BQ36/$U36*100 -> 31356.671 | CB36: =BR36/$U36*100 -> 617753.8 | CC36: =BS36/$U36*100 -> 79118.358 | CD36: =BT36/$U36*100 -> 538635.44 | CE36: =BU36/$U36*100 -> 358356.92 | CF36: =BV36/$U36*100 -> 75607.975 | CG36: =BW36/$U36*100 -> 42435.457 | ... CI36: =BY36/$U36*100 -> 171699.57 | CK36: 90.99663 | CL36: 96.184584 | CM36: 81.21 | CN36: 4.75 | CO36: 73.425 | CP36: 45.626233 | CQ36: 17.66 | CR36: 15.48
A37: 36404 | B37: 36444 | C37: 9726 | D37: 19265.176 | E37: =H37-B37-C37-D37-F37+G37 -> 3166.889 | F37: 92862.915 | G37: 72268.98 | H37: 89196 | I37: 52370 | J37: 14478 | K37: 27961.109 | L37: =O37-I37-J37-K37-M37+N37 -> 7266.3588 | M37: 118325.17 | N37: 82959.633 | O37: 137441 | P37: =B37/I37*100 -> 69.58946 | Q37: =C37/J37*100 -> 67.177787 | R37: =D37/K37*100 -> 68.899899 | S37: =F37/M37*100 -> 78.48112 | T37: =G37/N37*100 -> 87.113428 | U37: =H37/O37*100 -> 64.897665 | W37: 3521.4835 | X37: 5612.0393 | Z37: 79.16511 | AA37: 59 | AB37: 94 | AC37: 68 | AD37: =SUMPRODUCT($AA$1:$AC$1,AA37:AC37)/SUM($AA$1:$AC$1) -> 69.9 | AF37: 85.617366 | AG37: 85.617366 | AH37: =(Z37-0.8*AG37)/0.2 -> 53.356083 | AI37: =(Z37/Z33-1)*100 -> 2.3247537 | AJ37: =(AF37/AF33-1)*100*$AJ$1 -> 1.0879396 | AK37: =(AD37/AD33-1)*100*$AK$1 -> 0 | AL37: =AI37-AJ37-AK37 -> 1.2368141 | AN37: 2.549 | AO37: 3.75 | AP37: 8.1066667 | AQ37: =AP37-AN37 -> 5.5576667 | AR37: 3.8 | AS37: 112.01667 | AU37: 2671 | AV37: 8235 | AW37: 3091 | AX37: 1084 | AY37: 1630 | AZ37: 9444 | BA37: 7487 | BB37: =AU37+AV37+AW37-AX37-AY37-AZ37-BA37 -> -5648 | BC37: =BB37/H37*100 -> -6.3321225 | BD37: =AU37/$U37*100 -> 4115.7105 | BE37: =AV37/$U37*100 -> 12689.208 | BF37: =AW37/$U37*100 -> 4762.8832 | BG37: =AX37/$U37*100 -> 1670.322 | BH37: =AY37/$U37*100 -> 2511.6466 | BI37: =AZ37/$U37*100 -> 14552.141 | BJ37: =BA37/$U37*100 -> 11536.625 | BK37: =BD37+BE37+BF37-BG37-BH37-BI37-BJ37 -> -8702.9325 | BM37: 0.1306426 | BN37: =BM37*BO37 -> 52305.798 | BO37: 400373.23 | BP37: 632813.18 | BQ37: 17114.298 | BR37: 382642.88 | BS37: =BM37*BR37 -> 49989.459 | BT37: =BR37-BS37 -> 332653.42 | BU37: 233056 | BV37: 49472.412 | BW37: 24913.406 | BX37: 445695.38 | BY37: 112731.98 | BZ37: =BP37/$U37*100 -> 975093.91 | CA37: =BQ37/$U37*100 -> 26371.208 | CB37: =BR37/$U37*100 -> 589609.62 | CC37: =BS37/$U37*100 -> 77028.132 | CD37: =BT37/$U37*100 -> 512581.49 | CE37: =BU37/$U37*100 -> 359113.08 | CF37: =BV37/$U37*100 -> 76231.42 | CG37: =BW37/$U37*100 -> 38388.755 | ... CI37: =BY37/$U37*100 -> 173707.29 | CK37: 93.487758 | CL37: 97.438874 | CM37: 81.316 | CN37: 5.1 | CO37: 73.695 | CP37: 49.6544 | CQ37: 21.737 | CR37: 20.64
... A62: 38687 | B62: 68604 | C62: 23261 | D62: 31967.974 | E62: =H62-B62-C62-D62-F62+G62 -> -3121.7792 | F62: 156192.63 | G62: 126271.83 | H62: 150632 | I62: 87147 | J62: 29477 | K62: 39874.543 | L62: =O62-I62-J62-K62-M62+N62 -> -5066.1905 | M62: 177064.55 | N62: 139313.9 | O62: 189183 | P62: =B62/I62*100 -> 78.722159 | Q62: =C62/J62*100 -> 78.912372 | R62: =D62/K62*100 -> 80.171386 | S62: =F62/M62*100 -> 88.212256 | T62: =G62/N62*100 -> 90.638355 | U62: =H62/O62*100 -> 79.622376 | W62: 5133.8117 | X62: 6504.7113 | Z62: 88.78749 | AA62: 87 | AB62: 94 | AC62: 81 | AD62: =SUMPRODUCT($AA$1:$AC$1,AA62:AC62)/SUM($AA$1:$AC$1) -> 88.833333 | AF62: 90.157004 | AG62: 90.157004 | AH62: =(Z62-0.8*AG62)/0.2 -> 83.309431 | AI62: =(Z62/Z58-1)*100 -> 3.4267226 | AJ62: =(AF62/AF58-1)*100*$AJ$1 -> 1.4068231 | AK62: =(AD62/AD58-1)*100*$AK$1 -> 0.9012817 | AL62: =AI62-AJ62-AK62 -> 1.1186178 | AN62: 2.9 | AO62: 3.0066667 | AP62: 6.0166667 | AQ62: =AP62-AN62 -> 3.1166667 | AR62: 3.7766 | AS62: 111.88 | AU62: -2258 | AV62: 22431 | AW62: 12010 | AX62: 8092 | AY62: 3067 | AZ62: 24292 | BA62: 14583 | BB62: =AU62+AV62+AW62-AX62-AY62-AZ62-BA62 -> -17851 | BC62: =BB62/H62*100 -> -11.850736 | BD62: =AU62/$U62*100 -> -2835.8862 | BE62: =AV62/$U62*100 -> 28171.729 | BF62: =AW62/$U62*100 -> 15083.7 | BG62: =AX62/$U62*100 -> 10162.972 | BH62: =AY62/$U62*100 -> 3851.9323 | BI62: =AZ62/$U62*100 -> 30509.012 | BJ62: =BA62/$U62*100 -> 18315.203 | BK62: =BD62+BE62+BF62-BG62-BH62-BI62-BJ62 -> -22419.577 | BM62: 0.23090077 | BN62: =BM62*BO62 -> 128857.94 | BO62: 558066.3 | BP62: 958545.73 | BQ62: 19549.525 | BR62: 555494.78 | BS62: =BM62*BR62 -> 128264.17 | BT62: =BR62-BS62 -> 427230.6 | BU62: 383501.43 | BV62: 75203.439 | BW62: 43439.37 | BX62: 694597.94 | BY62: 145304.98 | BZ62: =BP62/$U62*100 -> 1203864.8 | CA62: =BQ62/$U62*100 -> 24552.803 | CB62: =BR62/$U62*100 -> 697661.64 | CC62: =BS62/$U62*100 -> 161090.61 | CD62: =BT62/$U62*100 -> 536571.03 | CE62: =BU62/$U62*100 -> 481650.32 | CF62: =BV62/$U62*100 -> 94450.131 | CG62: =BW62/$U62*100 -> 54556.737 | ... CI62: =BY62/$U62*100 -> 182492.65 | CK62: 135.65165 | CL62: 121.75223 | CM62: 89.582 | CN62: 3.98 | CO62: 82.831 | CP62: 107.38803 | CQ62: 60.033 | CR62: 56.85
A63: 38777 | B63: 69073 | C63: 13621 | D63: 32291.42 | E63: =H63-B63-C63-D63-F63+G63 -> 3669.9346 | F63: 148992.71 | G63: 119605.06 | H63: 148043 | I63: 86274 | J63: 17339 | K63: 39971.121 | L63: =O63-I63-J63-K63-M63+N63 -> 4145.9664 | M63: 172073.14 | N63: 134540.22 | O63: 185263 | P63: =B63/I63*100 -> 80.062359 | Q63: =C63/J63*100 -> 78.55701 | R63: =D63/K63*100 -> 80.786876 | S63: =F63/M63*100 -> 86.586849 | T63: =G63/N63*100 -> 88.89911 | U63: =H63/O63*100 -> 79.909642 | W63: 5044.4103 | X63: 6578.6119 | Z63: 89.898962 | AA63: 92.666667 | AB63: 94 | AC63: 86 | AD63: =SUMPRODUCT($AA$1:$AC$1,AA63:AC63)/SUM($AA$1:$AC$1) -> 92.77037 | AF63: 90.814884 | AG63: 90.814884 | AH63: =(Z63-0.8*AG63)/0.2 -> 86.235271 | AI63: =(Z63/Z59-1)*100 -> 3.7499817 | AJ63: =(AF63/AF59-1)*100*$AJ$1 -> 1.4260841 | AK63: =(AD63/AD59-1)*100*$AK$1 -> 1.3782139 | AL63: =AI63-AJ63-AK63 -> 0.94568374 | AN63: 3.1666667 | AO63: 3.0433333 | AP63: 6.2433333 | AQ63: =AP63-AN63 -> 3.0766667 | AR63: 3.727 | AS63: 111.46333 | AU63: 9527 | AV63: 7799 | AW63: 6888 | AX63: 3039.0489 | AY63: 3227.9253 | AZ63: 11061.026 | BA63: 2017 | BB63: =AU63+AV63+AW63-AX63-AY63-AZ63-BA63 -> 4869 | BC63: =BB63/H63*100 -> 3.2889093 | BD63: =AU63/$U63*100 -> 11922.216 | BE63: =AV63/$U63*100 -> 9759.7734 | BF63: =AW63/$U63*100 -> 8619.7358 | BG63: =AX63/$U63*100 -> 3803.1067 | BH63: =AY63/$U63*100 -> 4039.469 | BI63: =AZ63/$U63*100 -> 13841.916 | BJ63: =BA63/$U63*100 -> 2524.1009 | BK63: =BD63+BE63+BF63-BG63-BH63-BI63-BJ63 -> 6093.132 | BM63: 0.23484099 | BN63: 132991.87 | BO63: 566306.05 | BP63: 984647.3 | BQ63: 18917.776 | BR63: 560324.69 | BS63: =BM63*BR63 -> 131587.2 | BT63: =BR63-BS63 -> 428737.49 | BU63: 405404.84 | BV63: 73858.784 | BW63: 40618.445 | BX63: 713129.51 | BY63: 157040.56 | BZ63: =BP63/$U63*100 -> 1232200.9 | CA63: =BQ63/$U63*100 -> 23673.959 | CB63: =BR63/$U63*100 -> 701197.84 | CC63: =BS63/$U63*100 -> 164669.99 | CD63: =BT63/$U63*100 -> 536527.85 | CE63: =BU63/$U63*100 -> 507329.06 | CF63: =BV63/$U63*100 -> 92427.875 | CG63: =BW63/$U63*100 -> 50830.468 | ... CI63: =BY63/$U63*100 -> 196522.67 | CK63: 139.63972 | CL63: 123.48145 | CM63: 90.12 | CN63: 4.45 | CO63: 83.311 | CP63: 109.45024 | CQ63: 63.347 | CR63: 61.79
A64: 38869 | B64: 66992 | C64: 15231 | D64: 34583.86 | E64: =H64-B64-C64-D64-F64+G64 -> 10323.284 | F64: 154394.51 | G64: 128128.65 | H64: 153396 | I64: 83575 | J64: 19071 | K64: 42808.378 | L64: =O64-I64-J64-K64-M64+N64 -> 8068.9039 | M64: 176954.37 | N64: 141791.66 | O64: 188686 | P64: =B64/I64*100 -> 80.157942 | Q64: =C64/J64*100 -> 79.864716 | R64: =D64/K64*100 -> 80.787599 | S64: =F64/M64*100 -> 87.251028 | T64: =G64/N64*100 -> 90.36403 | U64: =H64/O64*100 -> 81.29697 | W64: 4982.4129 | X64: 6577.4662 | Z64: 90.939853 | AA64: 103 | AB64: 94.666667 | AC64: 97 | AD64: =SUMPRODUCT($AA$1:$AC$1,AA64:AC64)/SUM($AA$1:$AC$1) -> 100.23333 | AF64: 91.140027 | AG64: 91.140027 | AH64: =(Z64-0.8*AG64)/0.2 -> 90.139157 | AI64: =(Z64/Z60-1)*100 -> 4.1208511 | AJ64: =(AF64/AF60-1)*100*$AJ$1 -> 1.4943179 | AK64: =(AD64/AD60-1)*100*$AK$1 -> 1.9104832 | AL64: =AI64-AJ64-AK64 -> 0.71604994 | AN64: 3.5 | AO64: 3.1566667 | AP64: 6.5066667 | AQ64: =AP64-AN64 -> 3.0066667 | AR64: 3.6446 | AS64: 112.15667 | AU64: 3081 | AV64: 21611 | AW64: 8351 | AX64: 3054.7233 | AY64: 2740.3978 | AZ64: 15807.879 | BA64: 5025 | BB64: =AU64+AV64+AW64-AX64-AY64-AZ64-BA64 -> 6415 | BC64: =BB64/H64*100 -> 4.1819865 | BD64: =AU64/$U64*100 -> 3789.8092 | BE64: =AV64/$U64*100 -> 26582.787 | BF64: =AW64/$U64*100 -> 10272.216 | BG64: =AX64/$U64*100 -> 3757.4873 | BH64: =AY64/$U64*100 -> 3370.8486 | BI64: =AZ64/$U64*100 -> 19444.61 | BJ64: =BA64/$U64*100 -> 6181.0422 | BK64: =BD64+BE64+BF64-BG64-BH64-BI64-BJ64 -> 7890.823 | BM64: 0.23346338 | BN64: 135254.81 | BO64: 579340.58 | BP64: 1006329.1 | BQ64: 18249.694 | BR64: 574612.45 | BS64: =BM64*BR64 -> 134150.96 | BT64: =BR64-BS64 -> 440461.49 | BU64: 413466.99 | BV64: 76622.319 | BW64: 43387.77 | BX64: 722984.44 | BY64: 163334.61 | BZ64: =BP64/$U64*100 -> 1237843.4 | CA64: =BQ64/$U64*100 -> 22448.185 | CB64: =BR64/$U64*100 -> 706806.72 | CC64: =BS64/$U64*100 -> 165013.48 | CD64: =BT64/$U64*100 -> 541793.24 | CE64: =BU64/$U64*100 -> 508588.45 | CF64: =BV64/$U64*100 -> 94249.908 | CG64: =BW64/$U64*100 -> 53369.48 | ... CI64: =BY64/$U64*100 -> 200911.07 | CK64: 141.82235 | CL64: 124.75039 | CM64: 91.344 | CN64: 4.91 | CO64: 83.975 | CP64: 120.02926 | CQ64: 70.53 | CR64: 69.49
A65: 38961 | B65: 69766 | C65: 17949 | D65: 33647.573 | E65: =H65-B65-C65-D65-F65+G65 -> 5057.977 | F65: 171888.54 | G65: 136210.09 | H65: 162099 | I65: 87037 | J65: 22375 | K65: 41527.269 | L65: =O65-I65-J65-K65-M65+N65 -> 4128.0712 | M65: 191032.25 | N65: 148670.59 | O65: 197429 | P65: =B65/I65*100 -> 80.156715 | Q65: =C65/J65*100 -> 80.218994 | R65: =D65/K65*100 -> 81.02525 | S65: =F65/M65*100 -> 89.978806 | T65: =G65/N65*100 -> 91.618718 | U65: =H65/O65*100 -> 82.104959 | W65: 5126.3748 | X65: 6583.1234 | Z65: 91.174504 | AA65: 103 | AB65: 96 | AC65: 97 | AD65: =SUMPRODUCT($AA$1:$AC$1,AA65:AC65)/SUM($AA$1:$AC$1) -> 100.63333 | AF65: 91.301853 | AG65: 91.301853 | AH65: =(Z65-0.8*AG65)/0.2 -> 90.66511 | AI65: =(Z65/Z61-1)*100 -> 3.5512582 | AJ65: =(AF65/AF61-1)*100*$AJ$1 -> 1.3073829 | AK65: =(AD65/AD61-1)*100*$AK$1 -> 1.4732708 | AL65: =AI65-AJ65-AK65 -> 0.77060439 | AN65: 3.5 | AO65: 3.1966667 | AP65: 6.65 | AQ65: =AP65-AN65 -> 3.15 | AR65: 3.6704 | AS65: 111.18 | AU65: 11584 | AV65: 11772 | AW65: 8516 | AX65: 4515.18 | AY65: 3243.5562 | AZ65: 21015.264 | BA65: 8886 | BB65: =AU65+AV65+AW65-AX65-AY65-AZ65-BA65 -> -5788 | BC65: =BB65/H65*100 -> -3.5706574 | BD65: =AU65/$U65*100 -> 14108.77 | BE65: =AV65/$U65*100 -> 14337.745 | BF65: =AW65/$U65*100 -> 10372.09 | BG65: =AX65/$U65*100 -> 5499.278 | BH65: =AY65/$U65*100 -> 3950.4998 | BI65: =AZ65/$U65*100 -> 25595.608 | BJ65: =BA65/$U65*100 -> 10822.732 | BK65: =BD65+BE65+BF65-BG65-BH65-BI65-BJ65 -> -7049.5133 | BM65: 0.23586736 | BN65: 138915.61 | BO65: 588956.49 | BP65: 1029621.9 | BQ65: 19667.595 | BR65: 583548.58 | BS65: =BM65*BR65 -> 137640.06 | BT65: =BR65-BS65 -> 445908.52 | BU65: 426405.75 | BV65: 80405.868 | BW65: 41560.344 | BX65: 744596.9 | BY65: 163058.81 | BZ65: =BP65/$U65*100 -> 1254031.3 | CA65: =BQ65/$U65*100 -> 23954.211 | CB65: =BR65/$U65*100 -> 710734.87 | CC65: =BS65/$U65*100 -> 167639.16 | CD65: =BT65/$U65*100 -> 543095.72 | CE65: =BU65/$U65*100 -> 519342.26 | CF65: =BV65/$U65*100 -> 97930.586 | CG65: =BW65/$U65*100 -> 50618.555 | ... CI65: =BY65/$U65*100 -> 198598.01 | CK65: 144.29957 | CL65: 126.4073 | CM65: 92.443 | CN65: 5.25 | CO65: 84.427 | CP65: 121.56252 | CQ65: 70.443 | CR65: 69.73
A66: 39052 | B66: 74139 | C66: 24730 | D66: 34572.288 | E66: =H66-B66-C66-D66-F66+G66 -> -6719.3294 | F66: 167306 | G66: 132984.95 | H66: 161043 | I66: 92688 | J66: 30967 | K66: 42445.732 | L66: =O66-I66-J66-K66-M66+N66 -> -5261.9554 | M66: 184415.69 | N66: 145930.47 | O66: 199324 | P66: =B66/I66*100 -> 79.987701 | Q66: =C66/J66*100 -> 79.859205 | R66: =D66/K66*100 -> 81.450563 | S66: =F66/M66*100 -> 90.722214 | T66: =G66/N66*100 -> 91.128987 | U66: =H66/O66*100 -> 80.794586 | W66: 5323.5827 | X66: 6584.7834 | Z66: 91.475335 | AA66: 103 | AB66: 96 | AC66: 97 | AD66: =SUMPRODUCT($AA$1:$AC$1,AA66:AC66)/SUM($AA$1:$AC$1) -> 100.63333 | AF66: 91.337875 | AG66: 91.337875 | AH66: =(Z66-0.8*AG66)/0.2 -> 92.025178 | AI66: =(Z66/Z62-1)*100 -> 3.0272799 | AJ66: =(AF66/AF62-1)*100*$AJ$1 -> 1.0478347 | AK66: =(AD66/AD62-1)*100*$AK$1 -> 1.3283302 | AL66: =AI66-AJ66-AK66 -> 0.651115 | AN66: 3.5 | AO66: 3.2 | AP66: 6.5833333 | AQ66: =AP66-AN66 -> 3.0833333 | AR66: 3.623 | AS66: 111.79667 | AU66: -4778 | AV66: 26034 | AW66: 13161 | AX66: 6511.2215 | AY66: 3283.5355 | AZ66: 30194.243 | BA66: 19032 | BB66: =AU66+AV66+AW66-AX66-AY66-AZ66-BA66 -> -24604 | BC66: =BB66/H66*100 -> -15.277907 | BD66: =AU66/$U66*100 -> -5913.7626 | BE66: =AV66/$U66*100 -> 32222.456 | BF66: =AW66/$U66*100 -> 16289.458 | BG66: =AX66/$U66*100 -> 8058.9824 | BH66: =AY66/$U66*100 -> 4064.0539 | BI66: =AZ66/$U66*100 -> 37371.617 | BJ66: =BA66/$U66*100 -> 23556.034 | BK66: =BD66+BE66+BF66-BG66-BH66-BI66-BJ66 -> -30452.536 | BM66: 0.2391444 | BN66: 141815.97 | BO66: 593013.96 | BP66: 1092914.4 | BQ66: 19018.941 | BR66: 587863.72 | BS66: =BM66*BR66 -> 140584.32 | BT66: =BR66-BS66 -> 447279.4 | BU66: 486031.76 | BV66: 84952.057 | BW66: 32876.349 | BX66: 812328.28 | BY66: 162757.74 | BZ66: =BP66/$U66*100 -> 1352707.5 | CA66: =BQ66/$U66*100 -> 23539.871 | CB66: =BR66/$U66*100 -> 727602.86 | CC66: =BS66/$U66*100 -> 174002.15 | CD66: =BT66/$U66*100 -> 553600.71 | CE66: =BU66/$U66*100 -> 601564.77 | CF66: =BV66/$U66*100 -> 105145.73 | CG66: =BW66/$U66*100 -> 40691.277 | ... CI66: =BY66/$U66*100 -> 201446.34 | CK66: 147.48625 | CL66: 128.00194 | CM66: 92.452 | CN66: 5.24 | CO66: 84.791 | CP66: 116.09609 | CQ66: 60.093 | CR66: 59.55
A67: 39142 | B67: 75256 | C67: 14912 | D67: 35815.574 | E67: =H67-B67-C67-D67-F67+G67 -> 5549.6022 | F67: 154739.2 | G67: 128944.37 | H67: 157328 | I67: 92795 | J67: 18611 | K67: 42926.397 | L67: =O67-I67-J67-K67-M67+N67 -> 6713.6936 | M67: 175611.5 | N67: 141833.59 | O67: 194824 | P67: =B67/I67*100 -> 81.099197 | Q67: =C67/J67*100 -> 80.124657 | R67: =D67/K67*100 -> 83.434847 | S67: =F67/M67*100 -> 88.114501 | T67: =G67/N67*100 -> 90.912436 | U67: =H67/O67*100 -> 80.753911 | W67: 5130.1218 | X67: 6740.1722 | Z67: 92.270157 | AA67: 103 | AB67: 96 | AC67: 97 | AD67: =SUMPRODUCT($AA$1:$AC$1,AA67:AC67)/SUM($AA$1:$AC$1) -> 100.63333 | AF67: 91.986674 | AG67: 91.986674 | AH67: =(Z67-0.8*AG67)/0.2 -> 93.404088 | AI67: =(Z67/Z63-1)*100 -> 2.6376227 | AJ67: =(AF67/AF63-1)*100*$AJ$1 -> 1.0322449 | AK67: =(AD67/AD63-1)*100*$AK$1 -> 0.84757266 | AL67: =AI67-AJ67-AK67 -> 0.75780518 | AN67: 3.5 | AO67: 3.1866667 | AP67: 6.55 | AQ67: =AP67-AN67 -> 3.05 | AR67: 3.4969 | AS67: 114.85667 | AU67: 11219.344 | AV67: 7940.4627 | AW67: 5067.3933 | AX67: 3851.4058 | AY67: 3067.3135 | AZ67: 14773.481 | BA67: 5168.933 | BB67: =AU67+AV67+AW67-AX67-AY67-AZ67-BA67 -> -2633.933 | BC67: =BB67/H67*100 -> -1.6741667 | BD67: =AU67/$U67*100 -> 13893.252 | BE67: =AV67/$U67*100 -> 9832.9141 | BF67: =AW67/$U67*100 -> 6275.1057 | BG67: =AX67/$U67*100 -> 4769.3118 | BH67: =AY67/$U67*100 -> 3798.3466 | BI67: =AZ67/$U67*100 -> 18294.446 | BJ67: =BA67/$U67*100 -> 6400.8454 | BK67: =BD67+BE67+BF67-BG67-BH67-BI67-BJ67 -> -3261.6785 | BM67: 0.2376317 | BN67: 142946.49 | BO67: 601546.39 | BP67: 1125880.2 | BQ67: 27254.888 | BR67: 568759.44 | BS67: =BM67*BR67 -> 135155.27 | BT67: =BR67-BS67 -> 433604.17 | BU67: 529865.87 | BV67: 90844.229 | BW67: 33615.138 | BX67: 841825.05 | BY67: 159595.78 | BZ67: =BP67/$U67*100 -> 1394211.4 | CA67: =BQ67/$U67*100 -> 33750.549 | CB67: =BR67/$U67*100 -> 704311.95 | CC67: =BS67/$U67*100 -> 167366.84 | CD67: =BT67/$U67*100 -> 536945.1 | CE67: =BU67/$U67*100 -> 656148.86 | CF67: =BV67/$U67*100 -> 112495.14 | CG67: =BW67/$U67*100 -> 41626.638 | ... CI67: =BY67/$U67*100 -> 197632.26 | CK67: 150.31534 | CL67: 129.70327 | CM67: 93.406 | CN67: 5.25 | CO67: 85.375 | CP67: 118.76915 | CQ67: 58.13 | CR67: 57.84
A68: 39234 | B68: 75992 | C68: 17102 | D68: 38437.971 | E68: =H68-B68-C68-D68-F68+G68 -> 5353.6796 | F68: 163161.85 | G68: 133016.5 | H68: 167031 | I68: 92100 | J68: 21065 | K68: 46147.413 | L68: =O68-I68-J68-K68-M68+N68 -> 5499.042 | M68: 182080.89 | N68: 147002.34 | O68: 199890 | P68: =B68/I68*100 -> 82.510315 | Q68: =C68/J68*100 -> 81.186803 | R68: =D68/K68*100 -> 83.293881 | S68: =F68/M68*100 -> 89.609543 | T68: =G68/N68*100 -> 90.485974 | U68: =H68/O68*100 -> 83.561459 | W68: 5193.6198 | X68: 6808.3581 | Z68: 92.285846 | AA68: 103 | AB68: 96 | AC68: 97 | AD68: =SUMPRODUCT($AA$1:$AC$1,AA68:AC68)/SUM($AA$1:$AC$1) -> 100.63333 | AF68: 92.311908 | AG68: 92.311908 | AH68: =(Z68-0.8*AG68)/0.2 -> 92.181596 | AI68: =(Z68/Z64-1)*100 -> 1.480091 | AJ68: =(AF68/AF64-1)*100*$AJ$1 -> 1.0286423 | AK68: =(AD68/AD64-1)*100*$AK$1 -> 0.039906884 | AL68: =AI68-AJ68-AK68 -> 0.41154187 | AN68: 3.5 | AO68: 3.1766667 | AP68: 6.4566667 | AQ68: =AP68-AN68 -> 2.9566667 | AR68: 3.4266 | AS68: 115.83667 | AU68: -6107.2568 | AV68: 31974.889 | AW68: 8329.6679 | AX68: 2101.3318 | AY68: 3035.5655 | AZ68: 19647.303 | BA68: 5804.867 | BB68: =AU68+AV68+AW68-AX68-AY68-AZ68-BA68 -> 3608.233 | BC68: =BB68/H68*100 -> 2.1602176 | BD68: =AU68/$U68*100 -> -7308.7005 | BE68: =AV68/$U68*100 -> 38265.116 | BF68: =AW68/$U68*100 -> 9968.3132 | BG68: =AX68/$U68*100 -> 2514.7141 | BH68: =AY68/$U68*100 -> 3632.734 | BI68: =AZ68/$U68*100 -> 23512.398 | BJ68: =BA68/$U68*100 -> 6946.8234 | BK68: =BD68+BE68+BF68-BG68-BH68-BI68-BJ68 -> 4318.0589 | BM68: 0.23653954 | BN68: 145236.26 | BO68: 614004.15 | BP68: 1156834.4 | BQ68: 29612.402 | BR68: 582176.02 | BS68: =BM68*BR68 -> 137707.65 | BT68: =BR68-BS68 -> 444468.37 | BU68: 545046.01 | BV68: 91412.217 | BW68: 39814.93 | BX68: 839774.93 | BY68: 185832.36 | BZ68: =BP68/$U68*100 -> 1384411.5 | CA68: =BQ68/$U68*100 -> 35437.871 | CB68: =BR68/$U68*100 -> 696704 | CC68: =BS68/$U68*100 -> 164798.04 | CD68: =BT68/$U68*100 -> 531905.95 | CE68: =BU68/$U68*100 -> 652269.62 | CF68: =BV68/$U68*100 -> 109395.19 | CG68: =BW68/$U68*100 -> 47647.481 | ... CI68: =BY68/$U68*100 -> 222390.04 | CK68: 152.9176 | CL68: 131.3597 | CM68: 94.623 | CN68: 5.25 | CO68: 85.731 | CP68: 130.44387 | CQ68: 64.97 | CR68: 68.59
A69: 39326 | B69: 82242 | C69: 21434 | D69: 39494.156 | E69: =H69-B69-C69-D69-F69+G69 -> 423.20763 | F69: 177450.94 | G69: 141465.3 | H69: 179579 | I69: 99402 | J69: 23755 | K69: 47335.578 | L69: =O69-I69-J69-K69-M69+N69 -> -2190.9978 | M69: 196121.66 | N69: 154283.24 | O69: 210140 | P69: =B69/I69*100 -> 82.736766 | Q69: =C69/J69*100 -> 90.229425 | R69: =D69/K69*100 -> 83.4344 | S69: =F69/M69*100 -> 90.480031 | T69: =G69/N69*100 -> 91.691944 | U69: =H69/O69*100 -> 85.456838 | W69: 5464.4523 | X69: 7079.3502 | Z69: 92.810944 | AA69: 103 | AB69: 96 | AC69: 97 | AD69: =SUMPRODUCT($AA$1:$AC$1,AA69:AC69)/SUM($AA$1:$AC$1) -> 100.63333 | AF69: 92.774467 | AG69: 92.774467 | AH69: =(Z69-0.8*AG69)/0.2 -> 92.956855 | AI69: =(Z69/Z65-1)*100 -> 1.7948441 | AJ69: =(AF69/AF65-1)*100*$AJ$1 -> 1.2903257 | AK69: =(AD69/AD65-1)*100*$AK$1 -> 0 | AL69: =AI69-AJ69-AK69 -> 0.50451847 | AN69: 3.5 | AO69: 3.15 | AP69: 6.33 | AQ69: =AP69-AN69 -> 2.83 | AR69: 3.4643 | AS69: 113.18667 | AU69: 13506.937 | AV69: 9519.1161 | AW69: 10237.326 | AX69: 5118.6658 | AY69: 3040.0033 | AZ69: 25534.199 | BA69: 10706.981 | BB69: =AU69+AV69+AW69-AX69-AY69-AZ69-BA69 -> -11136.47 | BC69: =BB69/H69*100 -> -6.2014322 | BD69: =AU69/$U69*100 -> 15805.565 | BE69: =AV69/$U69*100 -> 11139.092 | BF69: =AW69/$U69*100 -> 11979.529 | BG69: =AX69/$U69*100 -> 5989.7673 | BH69: =AY69/$U69*100 -> 3557.3552 | BI69: =AZ69/$U69*100 -> 29879.644 | BJ69: =BA69/$U69*100 -> 12529.11 | BK69: =BD69+BE69+BF69-BG69-BH69-BI69-BJ69 -> -13031.69 | BM69: 0.23089227 | BN69: 148779.71 | BO69: 644368.51 | BP69: 1156586.8 | BQ69: 40360.587 | BR69: 612766.68 | BS69: =BM69*BR69 -> 141483.09 | BT69: =BR69-BS69 -> 471283.59 | BU69: 503459.48 | BV69: 92648.72 | BW69: 54026.667 | BX69: 834009.34 | BY69: 175902.03 | BZ69: =BP69/$U69*100 -> 1353416.3 | CA69: =BQ69/$U69*100 -> 47229.207 | CB69: =BR69/$U69*100 -> 717048.15 | CC69: =BS69/$U69*100 -> 165560.88 | CD69: =BT69/$U69*100 -> 551487.28 | CE69: =BU69/$U69*100 -> 589138.91 | CF69: =BV69/$U69*100 -> 108415.81 | CG69: =BW69/$U69*100 -> 63220.999 | ... CI69: =BY69/$U69*100 -> 205837.27 | CK69: 155.10158 | CL69: 132.84454 | CM69: 95.314 | CN69: 5.07 | CO69: 86.152 | CP69: 132.7477 | CQ69: 75.5 | CR69: 74.75
A70: 39417 | B70: 84398 | C70: 29146 | D70: 39940.3 | E70: =H70-B70-C70-D70-F70+G70 -> 3107.8678 | F70: 182639.82 | G70: 146796.99 | H70: 192435 | I70: 101780 | J70: 32264 | K70: 47603.468 | L70: =O70-I70-J70-K70-M70+N70 -> -3608.7293 | M70: 197945.97 | N70: 161579.71 | O70: 214405 | P70: =B70/I70*100 -> 82.921989 | Q70: =C70/J70*100 -> 90.335978 | R70: =D70/K70*100 -> 83.902081 | S70: =F70/M70*100 -> 92.267512 | T70: =G70/N70*100 -> 90.851129 | U70: =H70/O70*100 -> 89.753037 | W70: 5665.6925 | X70: 7256.21 | Z70: 93.49123 | AA70: 103 | AB70: 96 | AC70: 97 | AD70: =SUMPRODUCT($AA$1:$AC$1,AA70:AC70)/SUM($AA$1:$AC$1) -> 100.63333 | AF70: 93.277699 | AG70: 93.277699 | AH70: =(Z70-0.8*AG70)/0.2 -> 94.345356 | AI70: =(Z70/Z66-1)*100 -> 2.2037579 | AJ70: =(AF70/AF66-1)*100*$AJ$1 -> 1.6990316 | AK70: =(AD70/AD66-1)*100*$AK$1 -> 0 | AL70: =AI70-AJ70-AK70 -> 0.50472626 | AN70: 3.5 | AO70: 3.15 | AP70: 6.2866667 | AQ70: =AP70-AN70 -> 2.7866667 | AR70: 3.3558 | AS70: 113.85 | AU70: 2697.3282 | AV70: 24417.57 | AW70: 21082.558 | AX70: 7661.2584 | AY70: 3767.9467 | AZ70: 31485.755 | BA70: 15778.936 | BB70: =AU70+AV70+AW70-AX70-AY70-AZ70-BA70 -> -10496.439 | BC70: =BB70/H70*100 -> -5.4545373 | BD70: =AU70/$U70*100 -> 3005.2779 | BE70: =AV70/$U70*100 -> 27205.286 | BF70: =AW70/$U70*100 -> 23489.521 | BG70: =AX70/$U70*100 -> 8535.9322 | BH70: =AY70/$U70*100 -> 4198.1273 | BI70: =AZ70/$U70*100 -> 35080.434 | BJ70: =BA70/$U70*100 -> 17580.392 | BK70: =BD70+BE70+BF70-BG70-BH70-BI70-BJ70 -> -11694.801 | BM70: 0.23621126 | BN70: 152176.07 | BO70: 644237.17 | BP70: 1186708.8 | BQ70: 32654.869 | BR70: 613112.95 | BS70: =BM70*BR70 -> 144824.18 | BT70: =BR70-BS70 -> 468288.77 | BU70: 540940.99 | BV70: 94383.19 | BW70: 50183.606 | BX70: 868822.51 | BY70: 173319.5 | BZ70: =BP70/$U70*100 -> 1322193.5 | CA70: =BQ70/$U70*100 -> 36383.024 | CB70: =BR70/$U70*100 -> 683111.08 | CC70: =BS70/$U70*100 -> 161358.53 | CD70: =BT70/$U70*100 -> 521752.56 | CE70: =BU70/$U70*100 -> 602699.37 | CF70: =BV70/$U70*100 -> 105158.77 | CG70: =BW70/$U70*100 -> 55912.989 | ... CI70: =BY70/$U70*100 -> 193107.12 | CK70: 158.31281 | CL70: 134.37274 | CM70: 96.768 | CN70: 4.5 | CO70: 86.747 | CP70: 149.79285 | CQ70: 90.85 | CR70: 88.29
A71: 39508 | B71: 86671 | C71: 18968 | D71: 39663.597 | E71: =H71-B71-C71-D71-F71+G71 -> 11956.47 | F71: 169084.34 | G71: 135496.4 | H71: 190847 | I71: 103443 | J71: 20470 | K71: 46148.678 | L71: =O71-I71-J71-K71-M71+N71 -> 526.62895 | M71: 185118.08 | N71: 146067.38 | O71: 209639 | P71: =B71/I71*100 -> 83.78624 | Q71: =C71/J71*100 -> 92.662433 | R71: =D71/K71*100 -> 85.947418 | S71: =F71/M71*100 -> 91.338641 | T71: =G71/N71*100 -> 92.762942 | U71: =H71/O71*100 -> 91.036019 | W71: 5241.3958 | X71: 7542.9886 | Z71: 94.641224 | AA71: 103.33333 | AB71: 96 | AC71: 97 | AD71: =SUMPRODUCT($AA$1:$AC$1,AA71:AC71)/SUM($AA$1:$AC$1) -> 100.85185 | AF71: 94.527038 | AG71: 94.527038 | AH71: =(Z71-0.8*AG71)/0.2 -> 95.097965 | AI71: =(Z71/Z67-1)*100 -> 2.5697002 | AJ71: =(AF71/AF67-1)*100*$AJ$1 -> 2.2093319 | AK71: =(AD71/AD67-1)*100*$AK$1 -> 0.021714328 | AL71: =AI71-AJ71-AK71 -> 0.33865395 | AN71: 3.5 | AO71: 3.1433333 | AP71: 6.25 | AQ71: =AP71-AN71 -> 2.75 | AR71: 3.2237 | AS71: 115.62333 | AU71: 15705.012 | AV71: 6207.0425 | AW71: 6043.0455 | AX71: 10097.624 | AY71: 3364.7215 | AZ71: 16962.354 | BA71: 5193.972 | BB71: =AU71+AV71+AW71-AX71-AY71-AZ71-BA71 -> -7663.572 | BC71: =BB71/H71*100 -> -4.015558 | BD71: =AU71/$U71*100 -> 17251.427 | BE71: =AV71/$U71*100 -> 6818.2271 | BF71: =AW71/$U71*100 -> 6638.0819 | BG71: =AX71/$U71*100 -> 11091.9 | BH71: =AY71/$U71*100 -> 3696.0333 | BI71: =AZ71/$U71*100 -> 18632.575 | BJ71: =BA71/$U71*100 -> 5705.4033 | BK71: =BD71+BE71+BF71-BG71-BH71-BI71-BJ71 -> -8418.1757 | BM71: 0.23243039 | BN71: 153773.8 | BO71: 661590.76 | BP71: 1229912.1 | BQ71: 29735.024 | BR71: 630672.98 | BS71: =BM71*BR71 -> 146587.57 | BT71: =BR71-BS71 -> 484085.41 | BU71: 569504.11 | BV71: 98895.985 | BW71: 53986.518 | BX71: 912889.18 | BY71: 164140.43 | BZ71: =BP71/$U71*100 -> 1351017 | CA71: =BQ71/$U71*100 -> 32662.922 | CB71: =BR71/$U71*100 -> 692773.03 | CC71: =BS71/$U71*100 -> 161021.51 | CD71: =BT71/$U71*100 -> 531751.52 | CE71: =BU71/$U71*100 -> 625581.08 | CF71: =BV71/$U71*100 -> 108633.91 | CG71: =BW71/$U71*100 -> 59302.371 | ... CI71: =BY71/$U71*100 -> 180302.74 | CK71: 156.96566 | CL71: 135.41829 | CM71: 98.656 | CN71: 3.18 | CO71: 87.207 | CP71: 167.76011 | CQ71: 97.953 | CR71: 96.86
A72: 39600 | B72: 87271 | C72: 20952 | D72: 42591.169 | E72: =H72-B72-C72-D72-F72+G72 -> 4721.4726 | F72: 193161.72 | G72: 144971.36 | H72: 203726 | I72: 100768 | J72: 22187 | K72: 49780.802 | L72: =O72-I72-J72-K72-M72+N72 -> 281.82509 | M72: 198444.07 | N72: 158332.7 | O72: 213129 | P72: =B72/I72*100 -> 86.605867 | Q72: =C72/J72*100 -> 94.433677 | R72: =D72/K72*100 -> 85.557419 | S72: =F72/M72*100 -> 97.338116 | T72: =G72/N72*100 -> 91.561228 | U72: =H72/O72*100 -> 95.588118 | W72: 5293.1558 | X72: 7599.4821 | Z72: 96.760484 | AA72: 116 | AB72: 96 | AC72: 97 | AD72: =SUMPRODUCT($AA$1:$AC$1,AA72:AC72)/SUM($AA$1:$AC$1) -> 109.15556 | AF72: 95.683775 | AG72: 95.683775 | AH72: =(Z72-0.8*AG72)/0.2 -> 101.06732 | AI72: =(Z72/Z68-1)*100 -> 4.8486719 | AJ72: =(AF72/AF68-1)*100*$AJ$1 -> 2.9221512 | AK72: =(AD72/AD68-1)*100*$AK$1 -> 0.84685878 | AL72: =AI72-AJ72-AK72 -> 1.0796619 | AN72: 3.5 | AO72: 3.14 | AP72: 6.1333333 | AQ72: =AP72-AN72 -> 2.6333333 | AR72: 3.2092 | AS72: 114.73 | AU72: 6419.8479 | AV72: 25063.976 | AW72: 8380.076 | AX72: 8821.0706 | AY72: 2615.4498 | AZ72: 21426.88 | BA72: 8930.518 | BB72: =AU72+AV72+AW72-AX72-AY72-AZ72-BA72 -> -1930.018 | BC72: =BB72/H72*100 -> -0.94735969 | BD72: =AU72/$U72*100 -> 6716.1568 | BE72: =AV72/$U72*100 -> 26220.807 | BF72: =AW72/$U72*100 -> 8766.8595 | BG72: =AX72/$U72*100 -> 9228.2082 | BH72: =AY72/$U72*100 -> 2736.1662 | BI72: =AZ72/$U72*100 -> 22415.84 | BJ72: =BA72/$U72*100 -> 9342.7072 | BK72: =BD72+BE72+BF72-BG72-BH72-BI72-BJ72 -> -2019.0982 | BM72: 0.2320597 | BN72: 159166.49 | BO72: 685885.97 | BP72: 1259834 | BQ72: 29527.788 | BR72: 655823.74 | BS72: =BM72*BR72 -> 152190.26 | BT72: =BR72-BS72 -> 503633.48 | BU72: 574482.49 | BV72: 102212.26 | BW72: 60767.514 | BX72: 930294.95 | BY72: 166559.29 | BZ72: =BP72/$U72*100 -> 1317981.8 | CA72: =BQ72/$U72*100 -> 30890.647 | CB72: =BR72/$U72*100 -> 686093.37 | CC72: =BS72/$U72*100 -> 159214.62 | CD72: =BT72/$U72*100 -> 526878.74 | CE72: =BU72/$U72*100 -> 600997.8 | CF72: =BV72/$U72*100 -> 106929.88 | CG72: =BW72/$U72*100 -> 63572.247 | ... CI72: =BY72/$U72*100 -> 174246.85 | CK72: 158.74766 | CL72: 136.54324 | CM72: 100.702 | CN72: 2.08 | CO72: 87.573 | CP72: 195.38186 | CQ72: 123.963 | CR72: 121.2
A73: 39692 | B73: 96531 | C73: 22513 | D73: 42212.222 | E73: =H73-B73-C73-D73-F73+G73 -> 5194.5083 | F73: 203819.72 | G73: 155722.45 | H73: 214548 | I73: 108068 | J73: 24575 | K73: 48408.641 | L73: =O73-I73-J73-K73-M73+N73 -> 1583.5152 | M73: 205628.81 | N73: 167334.96 | O73: 220929 | P73: =B73/I73*100 -> 89.324314 | Q73: =C73/J73*100 -> 91.609359 | R73: =D73/K73*100 -> 87.199767 | S73: =F73/M73*100 -> 99.120215 | T73: =G73/N73*100 -> 93.060317 | U73: =H73/O73*100 -> 97.111742 | W73: 5515.9283 | X73: 7307.3371 | Z73: 100.61328 | AA73: 141.33333 | AB73: 101 | AC73: 97 | AD73: =SUMPRODUCT($AA$1:$AC$1,AA73:AC73)/SUM($AA$1:$AC$1) -> 127.26296 | AF73: 97.014999 | AG73: 97.014999 | AH73: =(Z73-0.8*AG73)/0.2 -> 115.00642 | AI73: =(Z73/Z69-1)*100 -> 8.4067019 | AJ73: =(AF73/AF69-1)*100*$AJ$1 -> 3.6566372 | AK73: =(AD73/AD69-1)*100*$AK$1 -> 2.6462037 | AL73: =AI73-AJ73-AK73 -> 2.103861 | AN73: 3.5 | AO73: 3.14 | AP73: 5.9866667 | AQ73: =AP73-AN73 -> 2.4866667 | AR73: 3.3379 | AS73: 112.44 | AU73: 1055.3883 | AV73: 28547.749 | AW73: 16070.963 | AX73: 12074.325 | AY73: 3646.4295 | AZ73: 25635.346 | BA73: 12106.21 | BB73: =AU73+AV73+AW73-AX73-AY73-AZ73-BA73 -> -7788.21 | BC73: =BB73/H73*100 -> -3.6300548 | BD73: =AU73/$U73*100 -> 1086.7773 | BE73: =AV73/$U73*100 -> 29396.805 | BF73: =AW73/$U73*100 -> 16548.939 | BG73: =AX73/$U73*100 -> 12433.434 | BH73: =AY73/$U73*100 -> 3754.8801 | BI73: =AZ73/$U73*100 -> 26397.782 | BJ73: =BA73/$U73*100 -> 12466.268 | BK73: =BD73+BE73+BF73-BG73-BH73-BI73-BJ73 -> -8019.8438 | BM73: 0.22901075 | BN73: 163221.68 | BO73: 712724.95 | BP73: 1275440.2 | BQ73: 41445.506 | BR73: 682451.38 | BS73: =BM73*BR73 -> 156288.71 | BT73: =BR73-BS73 -> 526162.67 | BU73: 551543.27 | BV73: 107193.74 | BW73: 66206.945 | BX73: 942169.45 | BY73: 159870.02 | BZ73: =BP73/$U73*100 -> 1313373.8 | CA73: =BQ73/$U73*100 -> 42678.162 | CB73: =BR73/$U73*100 -> 702748.57 | CC73: =BS73/$U73*100 -> 160936.98 | CD73: =BT73/$U73*100 -> 541811.59 | CE73: =BU73/$U73*100 -> 567947.05 | CF73: =BV73/$U73*100 -> 110381.85 | CG73: =BW73/$U73*100 -> 68176.045 | ... CI73: =BY73/$U73*100 -> 164624.81 | CK73: 159.45195 | CL73: 137.05838 | CM73: 102.052 | CN73: 1.94 | CO73: 88.02 | CP73: 187.93064 | CQ73: 117.983 | CR73: 114.69
A74: 39783 | B74: 93759 | C74: 32642 | D74: 38871.602 | E74: =H74-B74-C74-D74-F74+G74 -> -4641.518 | F74: 169109.13 | G74: 133105.21 | H74: 196635 | I74: 107478 | J74: 35040 | K74: 44077.522 | L74: =O74-I74-J74-K74-M74+N74 -> 1026.3266 | M74: 174589.59 | N74: 147105.44 | O74: 215106 | P74: =B74/I74*100 -> 87.235527 | Q74: =C74/J74*100 -> 93.156393 | R74: =D74/K74*100 -> 88.189172 | S74: =F74/M74*100 -> 96.860944 | T74: =G74/N74*100 -> 90.482861 | U74: =H74/O74*100 -> 91.413071 | W74: 5494.5366 | X74: 6445.8471 | Z74: 99.013338 | AA74: 113.33333 | AB74: 101 | AC74: 97 | AD74: =SUMPRODUCT($AA$1:$AC$1,AA74:AC74)/SUM($AA$1:$AC$1) -> 108.90741 | AF74: 97.409946 | AG74: 97.409946 | AH74: =(Z74-0.8*AG74)/0.2 -> 105.4269 | AI74: =(Z74/Z70-1)*100 -> 5.9065511 | AJ74: =(AF74/AF70-1)*100*$AJ$1 -> 3.5440391 | AK74: =(AD74/AD70-1)*100*$AK$1 -> 0.82220014 | AL74: =AI74-AJ74-AK74 -> 1.5403118 | AN74: 3.3333333 | AO74: 3.08 | AP74: 5.95 | AQ74: =AP74-AN74 -> 2.6166667 | AR74: 3.5495 | AS74: 111.58667 | AU74: 3504.6984 | AV74: 26393.589 | AW74: 16401.998 | AX74: 14194.039 | AY74: 3170.217 | AZ74: 31490.429 | BA74: 15657.955 | BB74: =AU74+AV74+AW74-AX74-AY74-AZ74-BA74 -> -18212.354 | BC74: =BB74/H74*100 -> -9.2620103 | BD74: =AU74/$U74*100 -> 3833.9139 | BE74: =AV74/$U74*100 -> 28872.883 | BF74: =AW74/$U74*100 -> 17942.728 | BG74: =AX74/$U74*100 -> 15527.363 | BH74: =AY74/$U74*100 -> 3468.0128 | BI74: =AZ74/$U74*100 -> 34448.497 | BJ74: =BA74/$U74*100 -> 17128.792 | BK74: =BD74+BE74+BF74-BG74-BH74-BI74-BJ74 -> -19923.14 | BM74: 0.22818294 | BN74: 165785.34 | BO74: 726545.73 | BP74: 1302113.2 | BQ74: 61888.823 | BR74: 696367.84 | BS74: =BM74*BR74 -> 158899.26 | BT74: =BR74-BS74 -> 537468.58 | BU74: 543856.56 | BV74: 111603.51 | BW74: 51489.231 | BX74: 972251.15 | BY74: 166769.34 | BZ74: =BP74/$U74*100 -> 1424427.8 | CA74: =BQ74/$U74*100 -> 67702.378 | CB74: =BR74/$U74*100 -> 761781.48 | CC74: =BS74/$U74*100 -> 173825.54 | CD74: =BT74/$U74*100 -> 587955.94 | CE74: =BU74/$U74*100 -> 594943.98 | CF74: =BV74/$U74*100 -> 122087.04 | CG74: =BW74/$U74*100 -> 56325.896 | ... CI74: =BY74/$U74*100 -> 182434.89 | CK74: 158.3393 | CL74: 135.11217 | CM74: 95.911 | CN74: 0.51 | CO74: 87.951 | CP74: 119.74457 | CQ74: 58.37 | CR74: 55.03
... A137: 45536 | B137: 307203.08 | C137: 56240.312 | D137: 100551.85 | E137: =H137-B137-C137-D137-F137+G137 -> 4673.76 | F137: 353211.96 | G137: 331634.66 | H137: 490246.31 | I137: 258514.18 | J137: 53013.09 | K137: 89306.13 | L137: =O137-I137-J137-K137-M137+N137 -> 1960.24 | M137: 291804.86 | N137: 274244.6 | O137: 420353.91 | P137: =B137/I137*100 -> 118.83413 | Q137: =C137/J137*100 -> 106.08759 | R137: =D137/K137*100 -> 112.59233 | S137: =F137/M137*100 -> 121.04389 | T137: =G137/N137*100 -> 120.9266 | U137: =H137/O137*100 -> 116.62704 | W137: 10235.572 | X137: 9672 | Z137: 133.16667 | AA137: 116.66667 | AB137: 98.3 | AC137: 107.3 | AD137: =SUMPRODUCT($AA$1:$AC$1,AA137:AC137)/SUM($AA$1:$AC$1) -> 110.74037 | AF137: 131.7 | AG137: 131.7 | AH137: =(Z137-0.8*AG137)/0.2 -> 139.03333 | AI137: =(Z137/Z133-1)*100 -> 1.8872737 | AJ137: =(AF137/AF133-1)*100*$AJ$1 -> 1.5479876 | AK137: =(AD137/AD133-1)*100*$AK$1 -> 0.095792168 | AL137: =AI137-AJ137-AK137 -> 0.24349387 | AN137: 3 | AO137: 2.6307246 | AP137: 5.26528 | AQ137: =AP137-AN137 -> 2.26528 | AR137: 4.4538 | AS137: 101.57667 | AU137: 22970.392 | AV137: 41928.841 | AW137: 22230.867 | AX137: 23374.939 | AY137: 11996.916 | AZ137: 40976.633 | BA137: 17397.757 | BB137: =AU137+AV137+AW137-AX137-AY137-AZ137-BA137 -> -6616.1447 | BC137: =BB137/H137*100 -> -1.3495552 | BD137: =AU137/$U137*100 -> 19695.597 | BE137: =AV137/$U137*100 -> 35951.219 | BF137: =AW137/$U137*100 -> 19061.504 | BG137: =AX137/$U137*100 -> 20042.47 | BH137: =AY137/$U137*100 -> 10286.565 | BI137: =AZ137/$U137*100 -> 35134.763 | BJ137: =BA137/$U137*100 -> 14917.43 | BK137: =BD137+BE137+BF137-BG137-BH137-BI137-BJ137 -> -5672.9081 | BM137: 0.17180401 | BN137: 378590.69 | BO137: 2203619.7 | BP137: 3625388 | BQ137: 384550.59 | BR137: 2113115.4 | BS137: =BM137*BR137 -> 363041.7 | BT137: =BR137-BS137 -> 1750073.7 | BU137: 1127721.9 | BV137: 400192.58 | BW137: 125932.53 | BX137: 2512137.7 | BY137: 587125.18 | BZ137: =BP137/$U137*100 -> 3108531.3 | CA137: =BQ137/$U137*100 -> 329726.79 | CB137: =BR137/$U137*100 -> 1811857.3 | CC137: =BS137/$U137*100 -> 311284.34 | CD137: =BT137/$U137*100 -> 1500572.9 | CE137: =BU137/$U137*100 -> 966947.26 | CF137: =BV137/$U137*100 -> 343138.77 | CG137: =BW137/$U137*100 -> 107978.85 | ... CI137: =BY137/$U137*100 -> 503421.16 | CK137: 249.98453 | CL137: 224.90425 | CM137: 122.225 | CN137: 5.26 | CO137: 123.168 | CP137: 163.85906 | CQ137: 76.24 | CR137: 80.01
A138: 45627 | B138: 301023.7 | C138: 72431.929 | D138: 99873.317 | E138: =H138-B138-C138-D138-F138+G138 -> -7778.414 | F138: 360099.91 | G138: 324178.46 | H138: 501471.98 | I138: 253019.38 | J138: 67505.818 | K138: 89038.862 | L138: =O138-I138-J138-K138-M138+N138 -> -481.257 | M138: 290282.36 | N138: 268888.35 | O138: 430476.82 | P138: =B138/I138*100 -> 118.97258 | Q138: =C138/J138*100 -> 107.29731 | R138: =D138/K138*100 -> 112.16823 | S138: =F138/M138*100 -> 124.0516 | T138: =G138/N138*100 -> 120.56248 | U138: =H138/O138*100 -> 116.49222 | W138: 10617.573 | X138: 9747 | Z138: 133.36667 | AA138: 116.2 | AB138: 98.3 | AC138: 107.3 | AD138: =SUMPRODUCT($AA$1:$AC$1,AA138:AC138)/SUM($AA$1:$AC$1) -> 110.43444 | AF138: 131.8 | AG138: 131.8 | AH138: =(Z138-0.8*AG138)/0.2 -> 139.63333 | AI138: =(Z138/Z134-1)*100 -> 1.8066158 | AJ138: =(AF138/AF134-1)*100*$AJ$1 -> 1.3580247 | AK138: =(AD138/AD134-1)*100*$AK$1 -> 0.045887787 | AL138: =AI138-AJ138-AK138 -> 0.4027033 | AN138: 3 | AO138: 2.5918435 | AP138: 5.1499293 | AQ138: =AP138-AN138 -> 2.1499293 | AR138: 4.3939 | AS138: 103.91333 | AU138: 22789.43 | AV138: 46577.714 | AW138: 29039.156 | AX138: 29026.133 | AY138: 14051.262 | AZ138: 44978.867 | BA138: 31335.087 | BB138: =AU138+AV138+AW138-AX138-AY138-AZ138-BA138 -> -20985.05 | BC138: =BB138/H138*100 -> -4.1846904 | BD138: =AU138/$U138*100 -> 19563.049 | BE138: =AV138/$U138*100 -> 39983.542 | BF138: =AW138/$U138*100 -> 24927.98 | BG138: =AX138/$U138*100 -> 24916.801 | BH138: =AY138/$U138*100 -> 12061.975 | BI138: =AZ138/$U138*100 -> 38611.049 | BJ138: =BA138/$U138*100 -> 26898.868 | BK138: =BD138+BE138+BF138-BG138-BH138-BI138-BJ138 -> -18014.122 | BM138: 0.17136383 | BN138: 385412.15 | BO138: 2249086.9 | BP138: 3666466.4 | BQ138: 382351.24 | BR138: 2156949.9 | BS138: =BM138*BR138 -> 369623.2 | BT138: =BR138-BS138 -> 1787326.7 | BU138: 1127165.3 | BV138: 407137.31 | BW138: 142999.29 | BX138: 2561195.8 | BY138: =BP138-BV138-BW138-BX138 -> 555133.97 | BZ138: =BP138/$U138*100 -> 3147391.7 | CA138: =BQ138/$U138*100 -> 328220.42 | CB138: =BR138/$U138*100 -> 1851582.9 | CC138: =BS138/$U138*100 -> 317294.34 | CD138: =BT138/$U138*100 -> 1534288.5 | CE138: =BU138/$U138*100 -> 967588.48 | CF138: =BV138/$U138*100 -> 349497.44 | CG138: =BW138/$U138*100 -> 122754.38 | ... CI138: =BY138/$U138*100 -> 476541.69 | CK138: 252.30002 | CL138: 227.02351 | CM138: 122.186 | CN138: 4.65 | CO138: 123.997 | CP138: 166.47995 | CQ138: 70.687 | CR138: 74.66
A139: 45717 | B139: 301923.85 | C139: 54840.163 | D139: 104768.01 | E139: =H139-B139-C139-D139-F139+G139 -> -11778.164 | F139: 346276.01 | G139: 311217.65 | H139: 484812.22 | I139: 258562.9 | J139: 51200.647 | K139: 93243.344 | L139: =O139-I139-J139-K139-M139+N139 -> -7795.713 | M139: 278486.04 | N139: 258359.62 | O139: 415337.61 | P139: =B139/I139*100 -> 116.76998 | Q139: =C139/J139*100 -> 107.10834 | R139: =D139/K139*100 -> 112.35978 | S139: =F139/M139*100 -> 124.34232 | T139: =G139/N139*100 -> 120.45909 | U139: =H139/O139*100 -> 116.72726 | W139: 10579.011 | X139: 9653 | Z139: 133.9 | AA139: 116.83333 | AB139: 98.3 | AC139: 107.3 | AD139: =SUMPRODUCT($AA$1:$AC$1,AA139:AC139)/SUM($AA$1:$AC$1) -> 110.84963 | AF139: 132.7 | AG139: 132.7 | AH139: =(Z139-0.8*AG139)/0.2 -> 138.7 | AI139: =(Z139/Z135-1)*100 -> 1.5163002 | AJ139: =(AF139/AF135-1)*100*$AJ$1 -> 1.4735226 | AK139: =(AD139/AD135-1)*100*$AK$1 -> 0.066257685 | AL139: =AI139-AJ139-AK139 -> -0.023480098 | AN139: 3 | AO139: 2.5730303 | AP139: 5.0135958 | AQ139: =AP139-AN139 -> 2.0135958 | AR139: 4.4453 | AS139: 103.89 | AU139: 22743.266 | AV139: 34034.746 | AW139: 15348.988 | AX139: 23024 | AY139: 8545 | AZ139: 44889 | BA139: 17577 | BB139: =AU139+AV139+AW139-AX139-AY139-AZ139-BA139 -> -21908 | BC139: =BB139/H139*100 -> -4.518863 | BD139: =AU139/$U139*100 -> 19484.108 | BE139: =AV139/$U139*100 -> 29157.495 | BF139: =AW139/$U139*100 -> 13149.446 | BG139: =AX139/$U139*100 -> 19724.612 | BH139: =AY139/$U139*100 -> 7320.4835 | BI139: =AZ139/$U139*100 -> 38456.312 | BJ139: =BA139/$U139*100 -> 15058.179 | BK139: =BD139+BE139+BF139-BG139-BH139-BI139-BJ139 -> -18768.537 | BM139: 0.1712989 | BN139: 389434.23 | BO139: 2273419.3 | BP139: 3713867.7 | BQ139: 378708.15 | BR139: 2180462 | BS139: =BM139*BR139 -> 373510.75 | BT139: =BR139-BS139 -> 1806951.3 | BU139: 1154697.5 | BV139: 411277 | BW139: 147424 | BX139: 2593814.7 | BY139: =BP139-BV139-BW139-BX139 -> 561352 | BZ139: =BP139/$U139*100 -> 3181662.6 | CA139: =BQ139/$U139*100 -> 324438.47 | CB139: =BR139/$U139*100 -> 1867997.2 | CC139: =BS139/$U139*100 -> 319985.87 | CD139: =BT139/$U139*100 -> 1548011.3 | CE139: =BU139/$U139*100 -> 989226.94 | CF139: =BV139/$U139*100 -> 352340.14 | CG139: =BW139/$U139*100 -> 126297.83 | ... CI139: =BY139/$U139*100 -> 480909.07 | CK139: 256.99448 | CL139: 229.03415 | CM139: 123.844 | CN139: 4.33 | CO139: 125 | CP139: 170.9364 | CQ139: 71.837 | CR139: 75.87
A140: 45809 | B140: 299239.92 | C140: 54687.204 | D140: 111513.09 | E140: =H140-B140-C140-D140-F140+G140 -> 9121.836 | F140: 345342.7 | G140: 331611.15 | H140: 488293.6 | I140: 256125.05 | J140: 51007.323 | K140: 99725.656 | L140: =O140-I140-J140-K140-M140+N140 -> 8683.75 | M140: 281729.7 | N140: 277851.24 | O140: 419420.24 | P140: =B140/I140*100 -> 116.83353 | Q140: =C140/J140*100 -> 107.21442 | R140: =D140/K140*100 -> 111.81986 | S140: =F140/M140*100 -> 122.57944 | T140: =G140/N140*100 -> 119.34845 | U140: =H140/O140*100 -> 116.42109 | W140: 10430.403 | X140: 9703 | Z140: 134.4 | AA140: 115.96667 | AB140: 98.3 | AC140: 107.3 | AD140: =SUMPRODUCT($AA$1:$AC$1,AA140:AC140)/SUM($AA$1:$AC$1) -> 110.28148 | AF140: 133.5 | AG140: 133.5 | AH140: =(Z140-0.8*AG140)/0.2 -> 138 | AI140: =(Z140/Z136-1)*100 -> 1.2556504 | AJ140: =(AF140/AF136-1)*100*$AJ$1 -> 1.4645309 | AK140: =(AD140/AD136-1)*100*$AK$1 -> -0.033571761 | AL140: =AI140-AJ140-AK140 -> -0.1753087 | AN140: 3 | AO140: 2.5757971 | AP140: 4.9160708 | AQ140: =AP140-AN140 -> 1.9160708 | AR140: 4.3075 | AS140: 104.17667 | AU140: 26343.665 | AV140: 35983.572 | AW140: 13169.763 | AX140: 20026 | AY140: 17812 | AZ140: 41040 | BA140: 15171 | BB140: =AU140+AV140+AW140-AX140-AY140-AZ140-BA140 -> -18552 | BC140: =BB140/H140*100 -> -3.7993535 | BD140: =AU140/$U140*100 -> 22627.915 | BE140: =AV140/$U140*100 -> 30908.123 | BF140: =AW140/$U140*100 -> 11312.18 | BG140: =AX140/$U140*100 -> 17201.351 | BH140: =AY140/$U140*100 -> 15299.634 | BI140: =AZ140/$U140*100 -> 35251.346 | BJ140: =BA140/$U140*100 -> 13031.144 | BK140: =BD140+BE140+BF140-BG140-BH140-BI140-BJ140 -> -15935.258 | BM140: 0.1718126 | BN140: 394669.22 | BO140: 2297091.2 | BP140: 3761706.1 | BQ140: 397836.41 | BR140: 2204214.2 | BS140: =BM140*BR140 -> 378711.79 | BT140: =BR140-BS140 -> 1825502.4 | BU140: 1159655.5 | BV140: 420540.8 | BW140: 130168.3 | BX140: 2588668.2 | BY140: =BP140-BV140-BW140-BX140 -> 622328.81 | BZ140: =BP140/$U140*100 -> 3231120.9 | CA140: =BQ140/$U140*100 -> 341721.95 | CB140: =BR140/$U140*100 -> 1893311.8 | CC140: =BS140/$U140*100 -> 325294.84 | CD140: =BT140/$U140*100 -> 1568017 | CE140: =BU140/$U140*100 -> 996087.15 | CF140: =BV140/$U140*100 -> 361223.91 | CG140: =BW140/$U140*100 -> 111808.18 | ... CI140: =BY140/$U140*100 -> 534549.91 | CK140: 259.23284 | CL140: 231.02747 | CM140: 123.429 | CN140: 4.33 | CO140: 125.804 | CP140: 163.3783 | CQ140: 64.627 | CR140: 68.07
A141: 45901 | B141: 325765.71 | C141: 61160.485 | D141: 106959.52 | E141: =H141-B141-C141-D141-F141+G141 -> -11365.178 | F141: 363751.9 | G141: 329172.44 | H141: 517100 | I141: 271562.38 | J141: 56763.071 | K141: 95881.078 | L141: =O141-I141-J141-K141-M141+N141 -> -1834.135 | M141: 296897.35 | N141: 276061.35 | O141: 443208.4 | P141: =B141/I141*100 -> 119.95981 | Q141: =C141/J141*100 -> 107.74696 | R141: =D141/K141*100 -> 111.55436 | S141: =F141/M141*100 -> 122.51773 | T141: =G141/N141*100 -> 119.23887 | U141: =H141/O141*100 -> 116.67198 | W141: 10344.033 | X141: 9795 | Z141: 134.9 | AA141: 116.1 | AB141: 93.8 | AC141: 107.3 | AD141: =SUMPRODUCT($AA$1:$AC$1,AA141:AC141)/SUM($AA$1:$AC$1) -> 109.01889 | AF141: 134.3 | AG141: 134.3 | AH141: =(Z141-0.8*AG141)/0.2 -> 137.3 | AI141: =(Z141/Z137-1)*100 -> 1.301627 | AJ141: =(AF141/AF137-1)*100*$AJ$1 -> 1.579347 | AK141: =(AD141/AD137-1)*100*$AK$1 -> -0.15545202 | AL141: =AI141-AJ141-AK141 -> -0.12226794 | AN141: 2.75 | AO141: 2.2995916 | AP141: 4.7515542 | AQ141: =AP141-AN141 -> 2.0015542 | AR141: 4.2232 | AS141: 105.14 | AU141: 27287.184 | AV141: 48811.07 | AW141: 17717.745 | AX141: 24527 | AY141: 12105 | AZ141: 46394.477 | BA141: 20171 | BB141: =AU141+AV141+AW141-AX141-AY141-AZ141-BA141 -> -9381.4773 | BC141: =BB141/H141*100 -> -1.8142482 | BD141: =AU141/$U141*100 -> 23387.95 | BE141: =AV141/$U141*100 -> 41836.156 | BF141: =AW141/$U141*100 -> 15185.948 | BG141: =AX141/$U141*100 -> 21022.186 | BH141: =AY141/$U141*100 -> 10375.242 | BI141: =AZ141/$U141*100 -> 39764.885 | BJ141: =BA141/$U141*100 -> 17288.642 | BK141: =BD141+BE141+BF141-BG141-BH141-BI141-BJ141 -> -8040.9002 | BM141: 0.17144843 | BN141: 398550.03 | BO141: 2324605.9 | BP141: 3801520.2 | BQ141: 408796.33 | BR141: 2232016 | BS141: =BM141*BR141 -> 382675.64 | BT141: =BR141-BS141 -> 1849340.3 | BU141: 1160707.9 | BV141: 418345.7 | BW141: 143401.5 | BX141: 2613129.2 | BY141: =BP141-BV141-BW141-BX141 -> 626643.77 | BZ141: =BP141/$U141*100 -> 3258297.6 | CA141: =BQ141/$U141*100 -> 350380.9 | CB141: =BR141/$U141*100 -> 1913069.5 | CC141: =BS141/$U141*100 -> 327992.76 | CD141: =BT141/$U141*100 -> 1585076.7 | CE141: =BU141/$U141*100 -> 994847.18 | CF141: =BV141/$U141*100 -> 358565.71 | CG141: =BW141/$U141*100 -> 122909.98 | ... CI141: =BY141/$U141*100 -> 537098.78 | CK141: 260.6366 | CL141: 232.57194 | CM141: 124.295 | CN141: 4.29 | CO141: 126.699 | CP141: 165.50667 | CQ141: 65.737 | CR141: 69.03
A142: 45992 | B142: 319887.26 | C142: 79569.232 | D142: 108355.47 | E142: =H142-B142-C142-D142-F142+G142 -> -3633.972 | F142: 380361.52 | G142: 351669.76 | H142: 532869.76 | I142: 266319.87 | J142: 72895.887 | K142: 97329.094 | L142: =O142-I142-J142-K142-M142+N142 -> 9534.905 | M142: 301695.52 | N142: 290094.35 | O142: 457680.93 | P142: =B142/I142*100 -> 120.11393 | Q142: =C142/J142*100 -> 109.15462 | R142: =D142/K142*100 -> 111.32896 | S142: =F142/M142*100 -> 126.07463 | T142: =G142/N142*100 -> 121.226 | U142: =H142/O142*100 -> 116.42822 | W142: 10740.001 | X142: 9880 | Z142: 135.2 | AA142: 114 | AB142: 88.2 | AC142: 107.3 | AD142: =SUMPRODUCT($AA$1:$AC$1,AA142:AC142)/SUM($AA$1:$AC$1) -> 105.96222 | AF142: 134.8 | AG142: 134.8 | AH142: =(Z142-0.8*AG142)/0.2 -> 136.8 | AI142: =(Z142/Z138-1)*100 -> 1.3746563 | AJ142: =(AF142/AF138-1)*100*$AJ$1 -> 1.8209408 | AK142: =(AD142/AD138-1)*100*$AK$1 -> -0.40496624 | AL142: =AI142-AJ142-AK142 -> -0.041318239 | AN142: 2.75 | AO142: 2.24 | AP142: 4.6621306 | AQ142: =AP142-AN142 -> 1.9121306 | AR142: 4.1519 | AS142: 107.81 | AU142: 25070 | AV142: 39553 | AW142: 30006 | AX142: 27380 | AY142: 15249 | AZ142: 49784.633 | BA142: 27663.044 | BB142: =AU142+AV142+AW142-AX142-AY142-AZ142-BA142 -> -25447.678 | BC142: =BB142/H142*100 -> -4.7755906 | BD142: =AU142/$U142*100 -> 21532.58 | BE142: =AV142/$U142*100 -> 33972.004 | BF142: =AW142/$U142*100 -> 25772.102 | BG142: =AX142/$U142*100 -> 23516.635 | BH142: =AY142/$U142*100 -> 13097.34 | BI142: =AZ142/$U142*100 -> 42759.937 | BJ142: =BA142/$U142*100 -> 23759.742 | BK142: =BD142+BE142+BF142-BG142-BH142-BI142-BJ142 -> -21856.967 | BM142: =BM141 -> 0.17144843 | BN142: 404380.67 | BO142: 2357599 | BP142: 3841934.2 | BQ142: 392604.6 | BR142: 2266234.4 | BS142: =BM142*BR142 -> 388542.33 | BT142: =BR142-BS142 -> 1877692.1 | BU142: =BP142-BQ142-BR142 -> 1183095.2 | BV142: 426922.9 | BW142: 135738.3 | BX142: 2648531.8 | BY142: =BP142-BV142-BW142-BX142 -> 630741.2 | BZ142: =BP142/$U142*100 -> 3299830.8 | CA142: =BQ142/$U142*100 -> 337207.42 | CB142: =BR142/$U142*100 -> 1946464.9 | CC142: =BS142/$U142*100 -> 333718.35 | CD142: =BT142/$U142*100 -> 1612746.5 | CE142: =BU142/$U142*100 -> 1016158.5 | CF142: =BV142/$U142*100 -> 366683.35 | CG142: =BW142/$U142*100 -> 116585.4 | ... CI142: =BY142/$U142*100 -> 541742.54 | CK142: 262.48829 | CL142: 234.30886 | CM142: 124.73 | CN142: 3.9 | CO142: 127.545 | CP142: 169.06807 | CQ142: 59.64 | CR142: 63.65
A143: 46082 | U143: =U142*1 -> 116.42822 | AR143: 3.959 | BD143: =AU143/$U143*100 -> 0 | BE143: =AV143/$U143*100 -> 0 | BF143: =AW143/$U143*100 -> 0 | BG143: =AX143/$U143*100 -> 0 | BH143: =AY143/$U143*100 -> 0 | BI143: =AZ143/$U143*100 -> 0 | BJ143: =BA143/$U143*100 -> 0 | BK143: =BD143+BE143+BF143-BG143-BH143-BI143-BJ143 -> 0 | CQ143: 71.797 | CR143: 79.98
A144: 46174 | U144: =U143*1 -> 116.42822 | BD144: =AU144/$U144*100 -> 0 | BE144: =AV144/$U144*100 -> 0 | BF144: =AW144/$U144*100 -> 0 | BG144: =AX144/$U144*100 -> 0 | BH144: =AY144/$U144*100 -> 0 | BI144: =AZ144/$U144*100 -> 0 | BJ144: =BA144/$U144*100 -> 0 | BK144: =BD144+BE144+BF144-BG144-BH144-BI144-BJ144 -> 0
A145: 46266 | U145: =U144*1 -> 116.42822 | BD145: =AU145/$U145*100 -> 0 | BE145: =AV145/$U145*100 -> 0 | BF145: =AW145/$U145*100 -> 0 | BG145: =AX145/$U145*100 -> 0 | BH145: =AY145/$U145*100 -> 0 | BI145: =AZ145/$U145*100 -> 0 | BJ145: =BA145/$U145*100 -> 0 | BK145: =BD145+BE145+BF145-BG145-BH145-BI145-BJ145 -> 0
A146: 46357 | U146: =U145*1 -> 116.42822 | BD146: =AU146/$U146*100 -> 0 | BE146: =AV146/$U146*100 -> 0 | BF146: =AW146/$U146*100 -> 0 | BG146: =AX146/$U146*100 -> 0 | BH146: =AY146/$U146*100 -> 0 | BI146: =AZ146/$U146*100 -> 0 | BJ146: =BA146/$U146*100 -> 0 | BK146: =BD146+BE146+BF146-BG146-BH146-BI146-BJ146 -> 0
A147: 46447 | U147: =U146*1 -> 116.42822 | BD147: =AU147/$U147*100 -> 0 | BE147: =AV147/$U147*100 -> 0 | BF147: =AW147/$U147*100 -> 0 | BG147: =AX147/$U147*100 -> 0 | BH147: =AY147/$U147*100 -> 0 | BI147: =AZ147/$U147*100 -> 0 | BJ147: =BA147/$U147*100 -> 0 | BK147: =BD147+BE147+BF147-BG147-BH147-BI147-BJ147 -> 0
A148: 46539 | U148: =U147*1 -> 116.42822 | BD148: =AU148/$U148*100 -> 0 | BE148: =AV148/$U148*100 -> 0 | BF148: =AW148/$U148*100 -> 0 | BG148: =AX148/$U148*100 -> 0 | BH148: =AY148/$U148*100 -> 0 | BI148: =AZ148/$U148*100 -> 0 | BJ148: =BA148/$U148*100 -> 0 | BK148: =BD148+BE148+BF148-BG148-BH148-BI148-BJ148 -> 0
A149: 46631 | U149: =U148*1 -> 116.42822 | BD149: =AU149/$U149*100 -> 0 | BE149: =AV149/$U149*100 -> 0 | BF149: =AW149/$U149*100 -> 0 | BG149: =AX149/$U149*100 -> 0 | BH149: =AY149/$U149*100 -> 0 | BI149: =AZ149/$U149*100 -> 0 | BJ149: =BA149/$U149*100 -> 0 | BK149: =BD149+BE149+BF149-BG149-BH149-BI149-BJ149 -> 0
A150: 46722 | U150: =U149*1 -> 116.42822 | BD150: =AU150/$U150*100 -> 0 | BE150: =AV150/$U150*100 -> 0 | BF150: =AW150/$U150*100 -> 0 | BG150: =AX150/$U150*100 -> 0 | BH150: =AY150/$U150*100 -> 0 | BI150: =AZ150/$U150*100 -> 0 | BJ150: =BA150/$U150*100 -> 0 | BK150: =BD150+BE150+BF150-BG150-BH150-BI150-BJ150 -> 0
A151: 46813
A152: 46905
A153: 46997
A154: 47088
O157: =LN(O127/O123)*100 -> 4.9418009
O158: =LN(O128/O124)*100 -> 8.8438698
O159: =LN(O129/O125)*100 -> 13.662698
O160: =LN(O130/O126)*100 -> 7.1511073
O161: =LN(O131/O127)*100 -> 5.52412
O162: =LN(O132/O128)*100 -> 2.6333027
O163: =LN(O133/O129)*100 -> 3.042107
O164: =LN(O134/O130)*100 -> 2.7961511
O165: =LN(O135/O131)*100 -> 4.0909197
O166: =LN(O136/O132)*100 -> 5.7345206
O167: =LN(O137/O133)*100 -> 5.2716694
O168: =LN(O138/O134)*100 -> 4.817325
... O171: =LN(O141/O137)*100 -> 5.294309

Sheet NSA data
B1: Real GDP | C1: Household consumption | D1: Gov consumption | E1: Gross fixed capital formation | F1: Exports | G1: Imports | H1: Nominal wages | I1: Labour hours | J1: Fed Gov consumption | K1: Fed Gov investment | L1: Fed gov transfer | M1: Interest payment | N1: Fed gov total revenue (tax + non-tax) | O1: Fed gov total tax revenue | P1: Fed gov household tax revenue | Q1: Fed gov firm tax revenue | R1: Fed gov non-tax revenue | S1: Headline CPI | T1: Core CPI | U1: Non Core CPI | V1: Energy CPI | W1: Export deflator | X1: Import deflator | Y1: OPR | Z1: MYRUSD | AA1: NEER, BIS | AB1: =AVERAGE(AB42:AB137) -> -0.12575287 | AC1: Detrended NEER | AD1: =AVERAGE(AD42:AD137) -> -1.6237012e-15 | AE1: Global Trade | AF1: Global GDP | AG1: Global export price | AH1: Global CPI | AI1: FFR | AJ1: Global commodity price | AK1: Brent crude oil | AL1: Bank system total asset | AM1: Banking system credit, total | AN1: Credit to households | AO1: Credit to firms | AP1: Lending to government | AQ1: Other assets | AR1: Networth | AS1: External borrowings | AT1: Private sector deposit | AU1: Other liabiliites | AV1: Spread, ALR-OPR
A2: 1991-1 | B2: =DATA!O3 -> 74513 | C2: =DATA!I3 -> 40020 | D2: =DATA!J3 -> 6650 | E2: =DATA!K3 -> 22298.503 | F2: =DATA!M3 -> 43385.472 | G2: =DATA!N3 -> 39647.99 | H2: =DATA!W3 -> 1974.8527 | I2: =DATA!X3 -> 4844.7118 | J2: =DATA!BI3 -> 8119.9006 | K2: =DATA!BJ3 -> 1679.8396 | L2: =DATA!BG3 -> 1453.8689 | M2: =DATA!BH3 -> 2081.997 | N2: =O2+R2 -> 16132.501 | O2: =P2+Q2 -> 13124.953 | P2: =DATA!BD3 -> 3341.4258 | Q2: =DATA!BE3 -> 9783.5269 | R2: =DATA!BF3 -> 3007.5484 | S2: 58.429371 | T2: =DATA!AG3 -> 67.076243 | U2: =DATA!AH3 -> 23.84188 | V2: =DATA!AD3 -> 69.585185 | W2: =DATA!S3 -> 52.563151 | X2: =DATA!T3 -> 61.802093 | Y2: =DATA!AN3 -> 6.5866667 | Z2: =DATA!AR3 -> 2.7182 | AA2: =DATA!AS3 -> 138.34506 | AC2: =AA2 -> 138.34506 | AE2: =DATA!CK3 -> 48.625969 | AF2: =DATA!CL3 -> 68.775947 | AG2: =DATA!CM3 -> 84.591 | AH2: =DATA!CO3 -> 61.793 | AI2: =DATA!CN3 -> 6.43 | AK2: =DATA!CR3 -> 20.82 | AV2: =DATA!AQ3 -> 2.5133333
A3: 1992-2 | B3: =DATA!O4 -> 74696 | C3: =DATA!I4 -> 33768 | D3: =DATA!J4 -> 7088 | E3: =DATA!K4 -> 21428.75 | F3: =DATA!M4 -> 43069.236 | G3: =DATA!N4 -> 40861.223 | H3: =DATA!W4 -> 1994.2184 | I3: =DATA!X4 -> 4744.3815 | J3: =DATA!BI4 -> 7851.5941 | K3: =DATA!BJ4 -> 2333.1717 | L3: =DATA!BG4 -> 992.87109 | M3: =DATA!BH4 -> 3990.7721 | N3: =O3+R3 -> 16831.899 | O3: =P3+Q3 -> 13486.935 | P3: =DATA!BD4 -> 2765.2005 | Q3: =DATA!BE4 -> 10721.734 | R3: =DATA!BF4 -> 3344.9645 | S3: 59.186543 | T3: =DATA!AG4 -> 67.734365 | U3: =DATA!AH4 -> 24.995253 | V3: =DATA!AD4 -> 69.6 | W3: =DATA!S4 -> 53.025207 | X3: =DATA!T4 -> 62.28507 | Y3: =DATA!AN4 -> 6.8833333 | Z3: =DATA!AR4 -> 2.7621 | AA3: =DATA!AS4 -> 141.12479 | AB3: =LN(AA3/AA2)*100 -> 1.9893541 | AC3: =EXP(LN(AA3/AA2)-$AB$1/100)*AC2 -> 141.30237 | AD3: =LN(AC3/AC2)*100 -> 2.1151069 | AE3: =DATA!CK4 -> 50.008921 | AF3: =DATA!CL4 -> 69.402571 | AG3: =DATA!CM4 -> 84.115 | AH3: =DATA!CO4 -> 62.27 | AI3: =DATA!CN4 -> 5.86 | AK3: =DATA!CR4 -> 18.87 | AV3: =DATA!AQ4 -> 2.4166667
A4: 1991-3 | B4: =DATA!O5 -> 84432 | C4: =DATA!I5 -> 38019 | D4: =DATA!J5 -> 9128 | E4: =DATA!K5 -> 25300.961 | F4: =DATA!M5 -> 50861.965 | G4: =DATA!N5 -> 43952.112 | H4: =DATA!W5 -> 2069.3729 | I4: =DATA!X5 -> 4912.1779 | J4: =DATA!BI5 -> 9174.6988 | K4: =DATA!BJ5 -> 5653.4451 | L4: =DATA!BG5 -> 1277.1619 | M4: =DATA!BH5 -> 3029.5326 | N4: =O4+R4 -> 16459.628 | O4: =P4+Q4 -> 13798.196 | P4: =DATA!BD5 -> 3209.097 | Q4: =DATA!BE5 -> 10589.099 | R4: =DATA!BF5 -> 2661.4323 | S4: 59.47642 | T4: =DATA!AG5 -> 68.305718 | U4: =DATA!AH5 -> 24.159228 | V4: =DATA!AD5 -> 69.6 | W4: =DATA!S5 -> 53.7594 | X4: =DATA!T5 -> 62.522932 | Y4: =DATA!AN5 -> 7.4066667 | Z4: =DATA!AR5 -> 2.7756 | AA4: =DATA!AS5 -> 140.05566 | AB4: =LN(AA4/AA3)*100 -> -0.76045994 | AC4: =EXP(LN(AA4/AA3)-$AB$1/100)*AC3 -> 140.40835 | AD4: =LN(AC4/AC3)*100 -> -0.63470706 | AE4: =DATA!CK5 -> 51.228721 | AF4: =DATA!CL5 -> 70.132529 | AG4: =DATA!CM5 -> 83.542 | AH4: =DATA!CO5 -> 62.83 | AI4: =DATA!CN5 -> 5.65 | AK4: =DATA!CR5 -> 19.87 | AV4: =DATA!AQ5 -> 1.8933333
A5: 1991-4 | B5: =DATA!O6 -> 85673 | C5: =DATA!I6 -> 37877 | D5: =DATA!J6 -> 12378 | E5: =DATA!K6 -> 27787.64 | F5: =DATA!M6 -> 51518.265 | G5: =DATA!N6 -> 44177.838 | H5: =DATA!W6 -> 2226.5044 | I5: =DATA!X6 -> 4913.876 | J5: =DATA!BI6 -> 13252.185 | K5: =DATA!BJ6 -> 7660.8055 | L5: =DATA!BG6 -> 2054.1155 | M5: =DATA!BH6 -> 5532.3541 | N5: =O5+R5 -> 21570.164 | O5: =P5+Q5 -> 13591.24 | P5: =DATA!BD6 -> 2994.5292 | Q5: =DATA!BE6 -> 10596.711 | R5: =DATA!BF6 -> 7978.9235 | S5: 59.843581 | T5: =DATA!AG6 -> 68.669915 | U5: =DATA!AH6 -> 24.538245 | V5: =DATA!AD6 -> 69.6 | W5: =DATA!S6 -> 54.267468 | X5: =DATA!T6 -> 63.565806 | Y5: =DATA!AN6 -> 7.71 | Z5: =DATA!AR6 -> 2.7434 | AA5: =DATA!AS6 -> 137.59667 | AB5: =LN(AA5/AA4)*100 -> -1.7713209 | AC5: =EXP(LN(AA5/AA4)-$AB$1/100)*AC4 -> 138.11674 | AD5: =LN(AC5/AC4)*100 -> -1.645568 | AE5: =DATA!CK6 -> 52.115671 | AF5: =DATA!CL6 -> 70.761915 | AG5: =DATA!CM6 -> 83.691 | AH5: =DATA!CO6 -> 63.325 | AI5: =DATA!CN6 -> 4.82 | AK5: =DATA!CR6 -> 20.63 | AV5: =DATA!AQ6 -> 1.98
A6: 1992-1 | B6: =DATA!O7 -> 81826 | C6: =DATA!I7 -> 42183 | D6: =DATA!J7 -> 6597 | E6: =DATA!K7 -> 25643.278 | F6: =DATA!M7 -> 47408.986 | G6: =DATA!N7 -> 43408.098 | H6: =DATA!W7 -> 2193.984 | I6: =DATA!X7 -> 4951.0638 | J6: =DATA!BI7 -> 9309.0211 | K6: =DATA!BJ7 -> 1666.204 | L6: =DATA!BG7 -> 1628.6935 | M6: =DATA!BH7 -> 2134.7674 | N6: =O6+R6 -> 18397.617 | O6: =P6+Q6 -> 14619.496 | P6: =DATA!BD7 -> 3844.8822 | Q6: =DATA!BE7 -> 10774.613 | R6: =DATA!BF7 -> 3778.1219 | S6: 60.951382 | T6: =DATA!AG7 -> 69.678963 | U6: =DATA!AH7 -> 26.041058 | V6: =DATA!AD7 -> 69.6 | W6: =DATA!S7 -> 51.036433 | X6: =DATA!T7 -> 59.9121 | Y6: =DATA!AN7 -> 7.93 | Z6: =DATA!AR7 -> 2.6227 | AA6: =DATA!AS7 -> 143.47687 | AB6: =LN(AA6/AA5)*100 -> 4.184711 | AC6: =EXP(LN(AA6/AA5)-$AB$1/100)*AC5 -> 144.20039 | AD6: =LN(AC6/AC5)*100 -> 4.3104639 | AE6: =DATA!CK7 -> 52.952021 | AF6: =DATA!CL7 -> 71.741311 | AG6: =DATA!CM7 -> 83.551 | AH6: =DATA!CO7 -> 63.809 | AI6: =DATA!CN7 -> 4.02 | AJ6: =DATA!CP7 -> 45.563089 | AK6: =DATA!CR7 -> 17.95 | AV6: =DATA!AQ7 -> 1.98
A7: 1992-2 | B7: =DATA!O8 -> 82763 | C7: =DATA!I8 -> 35487 | D7: =DATA!J8 -> 8257 | E7: =DATA!K8 -> 23871.627 | F7: =DATA!M8 -> 52164.087 | G7: =DATA!N8 -> 43615.352 | H7: =DATA!W8 -> 2149.3003 | I7: =DATA!X8 -> 4921.7585 | J7: =DATA!BI8 -> 9109.5957 | K7: =DATA!BJ8 -> 2270.82 | L7: =DATA!BG8 -> 1000.5129 | M7: =DATA!BH8 -> 4015.1618 | N7: =O7+R7 -> 18835.131 | O7: =P7+Q7 -> 14701.576 | P7: =DATA!BD8 -> 3122.4814 | Q7: =DATA!BE8 -> 11579.094 | R7: =DATA!BF8 -> 4133.5555 | S7: 61.899059 | T7: =DATA!AG8 -> 70.352827 | U7: =DATA!AH8 -> 28.083987 | V7: =DATA!AD8 -> 69.6 | W7: =DATA!S8 -> 50.70958 | X7: =DATA!T8 -> 59.474012 | Y7: =DATA!AN8 -> 7.9566667 | Z7: =DATA!AR8 -> 2.531 | AA7: =DATA!AS8 -> 149.03633 | AB7: =LN(AA7/AA6)*100 -> 3.8016274 | AC7: =EXP(LN(AA7/AA6)-$AB$1/100)*AC6 -> 149.97637 | AD7: =LN(AC7/AC6)*100 -> 3.9273803 | AE7: =DATA!CK8 -> 53.652745 | AF7: =DATA!CL8 -> 72.670182 | AG7: =DATA!CM8 -> 83.628 | AH7: =DATA!CO8 -> 64.26 | AI7: =DATA!CN8 -> 3.77 | AJ7: =DATA!CP8 -> 47.754752 | AK7: =DATA!CR8 -> 20.01 | AV7: =DATA!AQ8 -> 2.2133333
A8: 1992-3 | B8: =DATA!O9 -> 90766 | C8: =DATA!I9 -> 39915 | D8: =DATA!J9 -> 8796 | E8: =DATA!K9 -> 28817.794 | F8: =DATA!M9 -> 55379.164 | G8: =DATA!N9 -> 46876.428 | H8: =DATA!W9 -> 2227.1443 | I8: =DATA!X9 -> 4875.7835 | J8: =DATA!BI9 -> 10515.785 | K8: =DATA!BJ9 -> 5478.7008 | L8: =DATA!BG9 -> 1221.8441 | M8: =DATA!BH9 -> 3034.9402 | N8: =O8+R8 -> 18339.35 | O8: =P8+Q8 -> 15064.869 | P8: =DATA!BD9 -> 3608.7346 | Q8: =DATA!BE9 -> 11456.135 | R8: =DATA!BF9 -> 3274.4807 | S8: 62.499898 | T8: =DATA!AG9 -> 70.80095 | U8: =DATA!AH9 -> 29.295691 | V8: =DATA!AD9 -> 69.6 | W8: =DATA!S9 -> 51.822479 | X8: =DATA!T9 -> 59.796253 | Y8: =DATA!AN9 -> 7.8433333 | Z8: =DATA!AR9 -> 2.5002 | AA8: =DATA!AS9 -> 146.68425 | AB8: =LN(AA8/AA7)*100 -> -1.5907783 | AC8: =EXP(LN(AA8/AA7)-$AB$1/100)*AC7 -> 147.79519 | AD8: =LN(AC8/AC7)*100 -> -1.4650254 | AE8: =DATA!CK9 -> 54.35499 | AF8: =DATA!CL9 -> 73.535547 | AG8: =DATA!CM9 -> 83.619 | AH8: =DATA!CO9 -> 64.64 | AI8: =DATA!CN9 -> 3.26 | AJ8: =DATA!CP9 -> 48.522837 | AK8: =DATA!CR9 -> 20.09 | AV8: =DATA!AQ9 -> 2.4566667
A9: 1992-4 | B9: =DATA!O10 -> 92316 | C9: =DATA!I10 -> 39059 | D9: =DATA!J10 -> 13309 | E9: =DATA!K10 -> 29010.296 | F9: =DATA!M10 -> 57665.595 | G9: =DATA!N10 -> 45486.098 | H9: =DATA!W10 -> 2403.8501 | I9: =DATA!X10 -> 4997.5792 | J9: =DATA!BI10 -> 15781.557 | K9: =DATA!BJ10 -> 7522.3456 | L9: =DATA!BG10 -> 1739.7179 | M9: =DATA!BH10 -> 5615.6356 | N9: =O9+R9 -> 24351.842 | O9: =P9+Q9 -> 14372.959 | P9: =DATA!BD10 -> 3409.1765 | Q9: =DATA!BE10 -> 10963.783 | R9: =DATA!BF10 -> 9978.8825 | S9: 62.74584 | T9: =DATA!AG10 -> 71.024095 | U9: =DATA!AH10 -> 29.632818 | V9: =DATA!AD10 -> 69.6 | W9: =DATA!S10 -> 52.976538 | X9: =DATA!T10 -> 61.067079 | Y9: =DATA!AN10 -> 7.9366667 | Z9: =DATA!AR10 -> 2.5337 | AA9: =DATA!AS10 -> 148.07411 | AB9: =LN(AA9/AA8)*100 -> 0.94306103 | AC9: =EXP(LN(AA9/AA8)-$AB$1/100)*AC8 -> 149.38332 | AD9: =LN(AC9/AC8)*100 -> 1.0688139 | AE9: =DATA!CK10 -> 55.138063 | AF9: =DATA!CL10 -> 74.585097 | AG9: =DATA!CM10 -> 83.466 | AH9: =DATA!CO10 -> 65.114 | AI9: =DATA!CN10 -> 3.03 | AJ9: =DATA!CP10 -> 46.85093 | AK9: =DATA!CR10 -> 19.22 | AV9: =DATA!AQ10 -> 2.3333333
A10: 1993-1 | B10: =DATA!O11 -> 88406 | C10: =DATA!I11 -> 41328 | D10: =DATA!J11 -> 6453 | E10: =DATA!K11 -> 27566.524 | F10: =DATA!M11 -> 52922.058 | G10: =DATA!N11 -> 44971.389 | H10: =DATA!W11 -> 2253.7762 | I10: =DATA!X11 -> 4946.9225 | J10: =DATA!BI11 -> 8840.9099 | K10: =DATA!BJ11 -> 1714.9266 | L10: =DATA!BG11 -> 1643.4052 | M10: =DATA!BH11 -> 1989.7479 | N10: =O10+R10 -> 18565.031 | O10: =P10+Q10 -> 15249.037 | P10: =DATA!BD11 -> 4451.4629 | Q10: =DATA!BE11 -> 10797.574 | R10: =DATA!BF11 -> 3315.994 | S10: 63.605043 | T10: =DATA!AG11 -> 71.836605 | U10: =DATA!AH11 -> 30.678796 | V10: =DATA!AD11 -> 69.6 | W10: =DATA!S11 -> 54.572818 | X10: =DATA!T11 -> 62.34415 | Y10: =DATA!AN11 -> 7.6466667 | Z10: =DATA!AR11 -> 2.6106 | AA10: =DATA!AS11 -> 145.4013 | AB10: =LN(AA10/AA9)*100 -> -1.821544 | AC10: =EXP(LN(AA10/AA9)-$AB$1/100)*AC9 -> 146.87145 | AD10: =LN(AC10/AC9)*100 -> -1.6957911 | AE10: =DATA!CK11 -> 56.014871 | AF10: =DATA!CL11 -> 75.277223 | AG10: =DATA!CM11 -> 83.568 | AH10: =DATA!CO11 -> 65.563 | AI10: =DATA!CN11 -> 3.04 | AJ10: =DATA!CP11 -> 46.327112 | AK10: =DATA!CR11 -> 18.24 | AV10: =DATA!AQ11 -> 2.5733333
A11: 1993-2 | B11: =DATA!O12 -> 93185 | C11: =DATA!I12 -> 37957 | D11: =DATA!J12 -> 10148 | E11: =DATA!K12 -> 30316.966 | F11: =DATA!M12 -> 58415.867 | G11: =DATA!N12 -> 51003.044 | H11: =DATA!W12 -> 2279.1197 | I11: =DATA!X12 -> 4986.6827 | J11: =DATA!BI12 -> 8768.9299 | K11: =DATA!BJ12 -> 2348.279 | L11: =DATA!BG12 -> 1013.3835 | M11: =DATA!BH12 -> 3760.1067 | N11: =O11+R11 -> 19096.439 | O11: =P11+Q11 -> 15422.078 | P11: =DATA!BD12 -> 3633.8008 | Q11: =DATA!BE12 -> 11788.277 | R11: =DATA!BF12 -> 3674.3608 | S11: 64.055098 | T11: =DATA!AG12 -> 72.172011 | U11: =DATA!AH12 -> 31.587448 | V11: =DATA!AD12 -> 69.6 | W11: =DATA!S12 -> 55.495061 | X11: =DATA!T12 -> 62.764594 | Y11: =DATA!AN12 -> 7.3066667 | Z11: =DATA!AR12 -> 2.5713 | AA11: =DATA!AS12 -> 143.26304 | AB11: =LN(AA11/AA10)*100 -> -1.4815086 | AC11: =EXP(LN(AA11/AA10)-$AB$1/100)*AC10 -> 144.89367 | AD11: =LN(AC11/AC10)*100 -> -1.3557557 | AE11: =DATA!CK12 -> 56.861776 | AF11: =DATA!CL12 -> 76.119003 | AG11: =DATA!CM12 -> 83.798 | AH11: =DATA!CO12 -> 66.061 | AI11: =DATA!CN12 -> 3 | AJ11: =DATA!CP12 -> 47.382121 | AK11: =DATA!CR12 -> 18.25 | AV11: =DATA!AQ12 -> 2.8533333
A12: 1993-3 | B12: =DATA!O13 -> 100769 | C12: =DATA!I13 -> 42124 | D12: =DATA!J13 -> 10189 | E12: =DATA!K13 -> 32247.112 | F12: =DATA!M13 -> 62890.863 | G12: =DATA!N13 -> 53404.428 | H12: =DATA!W13 -> 2334.8817 | I12: =DATA!X13 -> 5037.5947 | J12: =DATA!BI13 -> 10195.749 | K12: =DATA!BJ13 -> 5728.3843 | L12: =DATA!BG13 -> 1250.5979 | M12: =DATA!BH13 -> 2873.6563 | N12: =O12+R12 -> 18799.887 | O12: =P12+Q12 -> 15857.622 | P12: =DATA!BD13 -> 4223.842 | Q12: =DATA!BE13 -> 11633.78 | R12: =DATA!BF13 -> 2942.2645 | S12: 64.442401 | T12: =DATA!AG13 -> 72.514126 | U12: =DATA!AH13 -> 32.155503 | V12: =DATA!AD13 -> 69.6 | W12: =DATA!S13 -> 55.105245 | X12: =DATA!T13 -> 63.404332 | Y12: =DATA!AN13 -> 6.94 | Z12: =DATA!AR13 -> 2.5553 | AA12: =DATA!AS13 -> 144.01143 | AB12: =LN(AA12/AA11)*100 -> 0.52102835 | AC12: =EXP(LN(AA12/AA11)-$AB$1/100)*AC11 -> 145.83385 | AD12: =LN(AC12/AC11)*100 -> 0.64678122 | AE12: =DATA!CK13 -> 57.458111 | AF12: =DATA!CL13 -> 77.104476 | AG12: =DATA!CM13 -> 83.741 | AH12: =DATA!CO13 -> 66.43 | AI12: =DATA!CN13 -> 3.06 | AJ12: =DATA!CP13 -> 46.698385 | AK12: =DATA!CR13 -> 16.49 | AV12: =DATA!AQ13 -> 2.99
A13: 1993-4 | B13: =DATA!O14 -> 99691 | C13: =DATA!I14 -> 45056 | D13: =DATA!J14 -> 13078 | E13: =DATA!K14 -> 36378.911 | F13: =DATA!M14 -> 62935.038 | G13: =DATA!N14 -> 56975.259 | H13: =DATA!W14 -> 2476.6207 | I13: =DATA!X14 -> 4973.5275 | J13: =DATA!BI14 -> 15494.927 | K13: =DATA!BJ14 -> 7948.0979 | L13: =DATA!BG14 -> 1796.3861 | M13: =DATA!BH14 -> 5373.2737 | N13: =O13+R13 -> 25226.585 | O13: =P13+Q13 -> 16073.707 | P13: =DATA!BD14 -> 4045.8938 | Q13: =DATA!BE14 -> 12027.814 | R13: =DATA!BF14 -> 9152.8779 | S13: 64.83051 | T13: =DATA!AG14 -> 72.725912 | U13: =DATA!AH14 -> 33.248901 | V13: =DATA!AD14 -> 69.2 | W13: =DATA!S14 -> 54.778883 | X13: =DATA!T14 -> 64.060967 | Y13: =DATA!AN14 -> 6.5233333 | Z13: =DATA!AR14 -> 2.5595 | AA13: =DATA!AS14 -> 144.75982 | AB13: =LN(AA13/AA12)*100 -> 0.51832771 | AC13: =EXP(LN(AA13/AA12)-$AB$1/100)*AC12 -> 146.77617 | AD13: =LN(AC13/AC12)*100 -> 0.64408058 | AE13: =DATA!CK14 -> 59.35085 | AF13: =DATA!CL14 -> 78.078835 | AG13: =DATA!CM14 -> 83.707 | AH13: =DATA!CO14 -> 66.772 | AI13: =DATA!CN14 -> 2.99 | AJ13: =DATA!CP14 -> 45.472073 | AK13: =DATA!CR14 -> 15.18 | AV13: =DATA!AQ14 -> 3.2966667
A14: 1994-1 | B14: =DATA!O15 -> 95545 | C14: =DATA!I15 -> 46771 | D14: =DATA!J15 -> 7392 | E14: =DATA!K15 -> 32418.232 | F14: =DATA!M15 -> 63907.536 | G14: =DATA!N15 -> 56399.832 | H14: =DATA!W15 -> 2397.6399 | I14: =DATA!X15 -> 4832.536 | J14: =DATA!BI15 -> 9652.3947 | K14: =DATA!BJ15 -> 1854.3689 | L14: =DATA!BG15 -> 1899.9842 | M14: =DATA!BH15 -> 1870.9543 | N14: =O14+R14 -> 21770.109 | O14: =P14+Q14 -> 17766.831 | P14: =DATA!BD15 -> 5016.3577 | Q14: =DATA!BE15 -> 12750.474 | R14: =DATA!BF15 -> 4003.2782 | S14: 66.206978 | T14: =DATA!AG15 -> 73.300146 | U14: =DATA!AH15 -> 37.834309 | V14: =DATA!AD15 -> 68.355556 | W14: =DATA!S15 -> 57.175123 | X14: =DATA!T15 -> 66.762817 | Y14: =DATA!AN15 -> 4.0466667 | Z14: =DATA!AR15 -> 2.7306 | AA14: =DATA!AS15 -> 137.59667 | AB14: =LN(AA14/AA13)*100 -> -5.0749246 | AC14: =EXP(LN(AA14/AA13)-$AB$1/100)*AC13 -> 139.68879 | AD14: =LN(AC14/AC13)*100 -> -4.9491717 | AE14: =DATA!CK15 -> 60.603953 | AF14: =DATA!CL15 -> 79.203567 | AG14: =DATA!CM15 -> 84.082 | AH14: =DATA!CO15 -> 67.075 | AI14: =DATA!CN15 -> 3.21 | AJ14: =DATA!CP15 -> 45.829922 | AK14: =DATA!CR15 -> 13.96 | AV14: =DATA!AQ15 -> 5.3033333
A15: 1994-2 | B15: =DATA!O16 -> 100307 | C15: =DATA!I16 -> 41547 | D15: =DATA!J16 -> 8931 | E15: =DATA!K16 -> 31772.181 | F15: =DATA!M16 -> 70747.184 | G15: =DATA!N16 -> 62206.611 | H15: =DATA!W16 -> 2443.2014 | I15: =DATA!X16 -> 5162.4223 | J15: =DATA!BI16 -> 9791.9599 | K15: =DATA!BJ16 -> 2516.085 | L15: =DATA!BG16 -> 1144.8524 | M15: =DATA!BH16 -> 3503.4046 | N15: =O15+R15 -> 22189.234 | O15: =P15+Q15 -> 17792.718 | P15: =DATA!BD16 -> 4055.0232 | Q15: =DATA!BE16 -> 13737.695 | R15: =DATA!BF16 -> 4396.5156 | S15: 66.209658 | T15: =DATA!AG16 -> 73.578579 | U15: =DATA!AH16 -> 36.733974 | V15: =DATA!AD16 -> 68.7 | W15: =DATA!S16 -> 56.900549 | X15: =DATA!T16 -> 64.96752 | Y15: =DATA!AN16 -> 4.0666667 | Z15: =DATA!AR16 -> 2.6326 | AA15: =DATA!AS16 -> 141.09 | AB15: =LN(AA15/AA14)*100 -> 2.5071284 | AC15: =EXP(LN(AA15/AA14)-$AB$1/100)*AC14 -> 143.41548 | AD15: =LN(AC15/AC14)*100 -> 2.6328813 | AE15: =DATA!CK16 -> 62.407797 | AF15: =DATA!CL16 -> 80.292642 | AG15: =DATA!CM16 -> 84.411 | AH15: =DATA!CO16 -> 67.526 | AI15: =DATA!CN16 -> 3.94 | AJ15: =DATA!CP16 -> 48.167029 | AK15: =DATA!CR16 -> 16.1 | AV15: =DATA!AQ16 -> 4.8833333
A16: 1994-3 | B16: =DATA!O17 -> 110343 | C16: =DATA!I17 -> 45802 | D16: =DATA!J17 -> 10271 | E16: =DATA!K17 -> 40083.16 | F16: =DATA!M17 -> 75751.095 | G16: =DATA!N17 -> 68651.883 | H16: =DATA!W17 -> 2519.5274 | I16: =DATA!X17 -> 5350.4723 | J16: =DATA!BI17 -> 10907.226 | K16: =DATA!BJ17 -> 5982.2669 | L16: =DATA!BG17 -> 1365.7118 | M16: =DATA!BH17 -> 2609.6544 | N16: =O16+R16 -> 21291.35 | O16: =P16+Q16 -> 17860.012 | P16: =DATA!BD17 -> 4648.5835 | Q16: =DATA!BE17 -> 13211.429 | R16: =DATA!BF17 -> 3431.3382 | S16: 66.752108 | T16: =DATA!AG17 -> 74.124367 | U16: =DATA!AH17 -> 37.263072 | V16: =DATA!AD17 -> 68.4 | W16: =DATA!S17 -> 58.217535 | X16: =DATA!T17 -> 65.07266 | Y16: =DATA!AN17 -> 4.0533333 | Z16: =DATA!AR17 -> 2.5712 | AA16: =DATA!AS17 -> 141.26 | AB16: =LN(AA16/AA15)*100 -> 0.12041794 | AC16: =EXP(LN(AA16/AA15)-$AB$1/100)*AC15 -> 143.76896 | AD16: =LN(AC16/AC15)*100 -> 0.24617081 | AE16: =DATA!CK17 -> 64.205576 | AF16: =DATA!CL17 -> 81.108168 | AG16: =DATA!CM17 -> 84.806 | AH16: =DATA!CO17 -> 67.903 | AI16: =DATA!CN17 -> 4.49 | AJ16: =DATA!CP17 -> 50.360795 | AK16: =DATA!CR17 -> 16.78 | AV16: =DATA!AQ17 -> 4.4866667
A17: 1994-4 | B17: =DATA!O18 -> 111058 | C17: =DATA!I18 -> 47958 | D17: =DATA!J18 -> 16728 | E17: =DATA!K18 -> 42781.599 | F17: =DATA!M18 -> 78701.057 | G17: =DATA!N18 -> 71995.296 | H17: =DATA!W18 -> 2684.4919 | I17: =DATA!X18 -> 5410.5365 | J17: =DATA!BI18 -> 16358.913 | K17: =DATA!BJ18 -> 8099.6047 | L17: =DATA!BG18 -> 1864.7784 | M17: =DATA!BH18 -> 4761.6132 | N17: =O17+R17 -> 27878.757 | O17: =P17+Q17 -> 17459.631 | P17: =DATA!BD18 -> 4303.5001 | Q17: =DATA!BE18 -> 13156.131 | R17: =DATA!BF18 -> 10419.126 | S17: 67.290089 | T17: =DATA!AG18 -> 74.48447 | U17: =DATA!AH18 -> 38.512562 | V17: =DATA!AD18 -> 69.6 | W17: =DATA!S18 -> 58.909606 | X17: =DATA!T18 -> 65.654286 | Y17: =DATA!AN18 -> 4.6333333 | Z17: =DATA!AR18 -> 2.5607 | AA17: =DATA!AS18 -> 140.96333 | AB17: =LN(AA17/AA16)*100 -> -0.21023547 | AC17: =EXP(LN(AA17/AA16)-$AB$1/100)*AC16 -> 143.64755 | AD17: =LN(AC17/AC16)*100 -> -0.084482596 | AE17: =DATA!CK18 -> 65.831577 | AF17: =DATA!CL18 -> 81.942238 | AG17: =DATA!CM18 -> 85.341 | AH17: =DATA!CO18 -> 68.248 | AI17: =DATA!CN18 -> 5.17 | AJ17: =DATA!CP18 -> 51.088318 | AK17: =DATA!CR18 -> 16.56 | AV17: =DATA!AQ18 -> 3.5766667
... A24: 1996-3 | B24: =DATA!O25 -> 130784 | C24: =DATA!I25 -> 54119 | D24: =DATA!J25 -> 12614 | E24: =DATA!K25 -> 48429.756 | F24: =DATA!M25 -> 95620.408 | G24: =DATA!N25 -> 84944.245 | H24: =DATA!W25 -> 3006.2437 | I24: =DATA!X25 -> 5604.3436 | J24: =DATA!BI25 -> 13375.106 | K24: =DATA!BJ25 -> 7105.0999 | L24: =DATA!BG25 -> 1682.6413 | M24: =DATA!BH25 -> 2446.3006 | N24: =O24+R24 -> 23593.632 | O24: =P24+Q24 -> 20620.75 | P24: =DATA!BD25 -> 5907.1776 | Q24: =DATA!BE25 -> 14713.573 | R24: =DATA!BF25 -> 2972.8818 | S24: 71.570776 | T24: =DATA!AG25 -> 78.514076 | U24: =DATA!AH25 -> 43.797578 | V24: =DATA!AD25 -> 68.1 | W24: =DATA!S25 -> 59.40462 | X24: =DATA!T25 -> 64.909607 | Y24: =DATA!AN25 -> 6.9066667 | Z24: =DATA!AR25 -> 2.4951 | AA24: =DATA!AS25 -> 148.16 | AB24: =LN(AA24/AA23)*100 -> 0.53011031 | AC24: =EXP(LN(AA24/AA23)-$AB$1/100)*AC23 -> 152.31617 | AD24: =LN(AC24/AC23)*100 -> 0.65586318 | AE24: =DATA!CK25 -> 74.947163 | AF24: =DATA!CL25 -> 86.893889 | AG24: =DATA!CM25 -> 85.274 | AH24: =DATA!CO25 -> 70.617 | AI24: =DATA!CN25 -> 5.31 | AJ24: =DATA!CP25 -> 56.909897 | AK24: =DATA!CR25 -> 20.86 | AV24: =DATA!AQ25 -> 3.2333333
A25: 1996-4 | B25: =DATA!O26 -> 132655 | C25: =DATA!I26 -> 58047 | D25: =DATA!J26 -> 15550 | E25: =DATA!K26 -> 54735.591 | F25: =DATA!M26 -> 95573.426 | G25: =DATA!N26 -> 88077.625 | H25: =DATA!W26 -> 3236.7036 | I25: =DATA!X26 -> 5685.2538 | J25: =DATA!BI26 -> 20299.486 | K25: =DATA!BJ26 -> 9653.0291 | L25: =DATA!BG26 -> 2348.7995 | M25: =DATA!BH26 -> 4478.9511 | N25: =O25+R25 -> 30999.908 | O25: =P25+Q25 -> 21970.416 | P25: =DATA!BD26 -> 5488.8121 | Q25: =DATA!BE26 -> 16481.603 | R25: =DATA!BF26 -> 9029.492 | S25: 71.854434 | T25: =DATA!AG26 -> 78.907436 | U25: =DATA!AH26 -> 43.642427 | V25: =DATA!AD26 -> 68.1 | W25: =DATA!S26 -> 60.763419 | X25: =DATA!T26 -> 64.79102 | Y25: =DATA!AN26 -> 7.0666667 | Z25: =DATA!AR26 -> 2.5183 | AA25: =DATA!AS26 -> 147.98 | AB25: =LN(AA25/AA24)*100 -> -0.12156414 | AC25: =EXP(LN(AA25/AA24)-$AB$1/100)*AC24 -> 152.32255 | AD25: =LN(AC25/AC24)*100 -> 0.0041887342 | AE25: =DATA!CK26 -> 76.798273 | AF25: =DATA!CL26 -> 87.854615 | AG25: =DATA!CM26 -> 84.399 | AH25: =DATA!CO26 -> 71.019 | AI25: =DATA!CN26 -> 5.28 | AJ25: =DATA!CP26 -> 58.251899 | AK25: =DATA!CR26 -> 23.58 | AL25: =DATA!BZ26 -> 866157.84 | AM25: =DATA!CB26 -> 538104.3 | AN25: =DATA!CC26 -> 69795.884 | AO25: =DATA!CD26 -> 468308.41 | AP25: =DATA!CA26 -> 23340.897 | AQ25: =DATA!CE26 -> 304712.64 | AR25: =DATA!CF26 -> 68873.847 | AS25: =DATA!CG26 -> 35771.97 | AT25: =DATA!CH26 -> 604611.07 | AU25: =DATA!CI26 -> 156900.95 | AV25: =DATA!AQ26 -> 3.1433333
A26: 1997-1 | B26: =DATA!O27 -> 127299 | C26: =DATA!I27 -> 57893 | D26: =DATA!J27 -> 8808 | E26: =DATA!K27 -> 46088.032 | F26: =DATA!M27 -> 97495.322 | G26: =DATA!N27 -> 84164.311 | H26: =DATA!W27 -> 3161.2539 | I26: =DATA!X27 -> 5903.1293 | J26: =DATA!BI27 -> 11974.991 | K26: =DATA!BJ27 -> 2735.327 | L26: =DATA!BG27 -> 2282.4762 | M26: =DATA!BH27 -> 1576.9581 | N26: =O26+R26 -> 25317.719 | O26: =P26+Q26 -> 21714.315 | P26: =DATA!BD27 -> 6595.6103 | Q26: =DATA!BE27 -> 15118.705 | R26: =DATA!BF27 -> 3603.4036 | S26: 72.878912 | T26: =DATA!AG27 -> 79.727141 | U26: =DATA!AH27 -> 45.485992 | V26: =DATA!AD27 -> 68.1 | W26: =DATA!S27 -> 57.336399 | X26: =DATA!T27 -> 63.731293 | Y26: =DATA!AN27 -> 7.0586667 | Z26: =DATA!AR27 -> 2.4845 | AA26: =DATA!AS27 -> 154.76333 | AB26: =LN(AA26/AA25)*100 -> 4.4819939 | AC26: =EXP(LN(AA26/AA25)-$AB$1/100)*AC25 -> 159.5054 | AD26: =LN(AC26/AC25)*100 -> 4.6077468 | AE26: =DATA!CK27 -> 78.793163 | AF26: =DATA!CL27 -> 88.73199 | AG26: =DATA!CM27 -> 84.16 | AH26: =DATA!CO27 -> 71.298 | AI26: =DATA!CN27 -> 5.28 | AJ26: =DATA!CP27 -> 56.059259 | AK26: =DATA!CR27 -> 21.22 | AL26: =DATA!BZ27 -> 980474.19 | AM26: =DATA!CB27 -> 610788.78 | AN26: =DATA!CC27 -> 74360.925 | AO26: =DATA!CD27 -> 536427.85 | AP26: =DATA!CA27 -> 24357.968 | AQ26: =DATA!CE27 -> 345327.44 | AR26: =DATA!CF27 -> 83214.497 | AS26: =DATA!CG27 -> 51481.668 | AT26: =DATA!CH27 -> 669844.19 | AU26: =DATA!CI27 -> 175933.84 | AV26: =DATA!AQ27 -> 3.0913333
A27: 1997-2 | B27: =DATA!O28 -> 132628 | C27: =DATA!I28 -> 53465 | D27: =DATA!J28 -> 10860 | E27: =DATA!K28 -> 52749.99 | F27: =DATA!M28 -> 96139.193 | G27: =DATA!N28 -> 94527.541 | H27: =DATA!W28 -> 3206.1361 | I27: =DATA!X28 -> 6055.7736 | J27: =DATA!BI28 -> 11488.179 | K27: =DATA!BJ28 -> 5745.4835 | L27: =DATA!BG28 -> 1424.7661 | M27: =DATA!BH28 -> 3006.7216 | N27: =O27+R27 -> 28282.606 | O27: =P27+Q27 -> 23702.105 | P27: =DATA!BD28 -> 5198.2946 | Q27: =DATA!BE28 -> 18503.811 | R27: =DATA!BF28 -> 4580.5007 | S27: 72.894962 | T27: =DATA!AG28 -> 80.117734 | U27: =DATA!AH28 -> 44.003872 | V27: =DATA!AD28 -> 69.3 | W27: =DATA!S28 -> 58.974787 | X27: =DATA!T28 -> 63.61702 | Y27: =DATA!AN28 -> 8.1946667 | Z27: =DATA!AR28 -> 2.5087 | AA27: =DATA!AS28 -> 154.11667 | AB27: =LN(AA27/AA26)*100 -> -0.4187177 | AC27: =EXP(LN(AA27/AA26)-$AB$1/100)*AC26 -> 159.03879 | AD27: =LN(AC27/AC26)*100 -> -0.29296482 | AE27: =DATA!CK28 -> 81.267947 | AF27: =DATA!CL28 -> 89.714659 | AG27: =DATA!CM28 -> 84.104 | AH27: =DATA!CO28 -> 71.67 | AI27: =DATA!CN28 -> 5.52 | AJ27: =DATA!CP28 -> 53.892031 | AK27: =DATA!CR28 -> 18.05 | AL27: =DATA!BZ28 -> 1071815.4 | AM27: =DATA!CB28 -> 645311.33 | AN27: =DATA!CC28 -> 83503.4 | AO27: =DATA!CD28 -> 561807.93 | AP27: =DATA!CA28 -> 24718.462 | AQ27: =DATA!CE28 -> 401785.64 | AR27: =DATA!CF28 -> 101914.16 | AS27: =DATA!CG28 -> 57877.789 | AT27: =DATA!CH28 -> 703110.42 | AU27: =DATA!CI28 -> 208913.06 | AV27: =DATA!AQ28 -> 2.3286667
A28: 1997-3 | B28: =DATA!O29 -> 140261 | C28: =DATA!I29 -> 57368 | D28: =DATA!J29 -> 11349 | E28: =DATA!K29 -> 57906.99 | F28: =DATA!M29 -> 102188.37 | G28: =DATA!N29 -> 91015.767 | H28: =DATA!W29 -> 3268.7635 | I28: =DATA!X29 -> 5954.5442 | J28: =DATA!BI29 -> 14257.355 | K28: =DATA!BJ29 -> 5239.0262 | L28: =DATA!BG29 -> 1727.9543 | M28: =DATA!BH29 -> 2253.8839 | N28: =O28+R28 -> 28226.834 | O28: =P28+Q28 -> 23233.868 | P28: =DATA!BD29 -> 6776.9008 | Q28: =DATA!BE29 -> 16456.967 | R28: =DATA!BF29 -> 4992.9663 | S28: 73.214046 | T28: =DATA!AG29 -> 80.367979 | U28: =DATA!AH29 -> 44.598315 | V28: =DATA!AD29 -> 69.9 | W28: =DATA!S29 -> 63.717096 | X28: =DATA!T29 -> 69.141879 | Y28: =DATA!AN29 -> 7.5613333 | Z28: =DATA!AR29 -> 2.7854 | AA28: =DATA!AS29 -> 142.38333 | AB28: =LN(AA28/AA27)*100 -> -7.918694 | AC28: =EXP(LN(AA28/AA27)-$AB$1/100)*AC27 -> 147.1156 | AD28: =LN(AC28/AC27)*100 -> -7.7929412 | AE28: =DATA!CK29 -> 83.227116 | AF28: =DATA!CL29 -> 90.553315 | AG28: =DATA!CM29 -> 83.891 | AH28: =DATA!CO29 -> 71.837 | AI28: =DATA!CN29 -> 5.53 | AJ28: =DATA!CP29 -> 52.462664 | AK28: =DATA!CR29 -> 18.51 | AL28: =DATA!BZ29 -> 1092798.8 | AM28: =DATA!CB29 -> 657439.41 | AN28: =DATA!CC29 -> 89692.963 | AO28: =DATA!CD29 -> 567746.45 | AP28: =DATA!CA29 -> 25643.174 | AQ28: =DATA!CE29 -> 409716.18 | AR28: =DATA!CF29 -> 88891.032 | AS28: =DATA!CG29 -> 62101.735 | AT28: =DATA!CH29 -> 698531.51 | AU28: =DATA!CI29 -> 243274.49 | AV28: =DATA!AQ29 -> 3.1786667
A29: 1997-4 | B29: =DATA!O30 -> 140807 | C29: =DATA!I30 -> 57852 | D29: =DATA!J30 -> 17819 | E29: =DATA!K30 -> 56021.225 | F29: =DATA!M30 -> 100582.68 | G29: =DATA!N30 -> 86245.349 | H29: =DATA!W30 -> 3494.9271 | I29: =DATA!X30 -> 6320.6805 | J29: =DATA!BI30 -> 18863.579 | K29: =DATA!BJ30 -> 10316.565 | L29: =DATA!BG30 -> 2334.8744 | M29: =DATA!BH30 -> 3940.7256 | N29: =O29+R29 -> 29637.39 | O29: =P29+Q29 -> 22491.052 | P29: =DATA!BD30 -> 5388.7589 | Q29: =DATA!BE30 -> 17102.293 | R29: =DATA!BF30 -> 7146.3378 | S29: 73.804113 | T29: =DATA!AG30 -> 80.827224 | U29: =DATA!AH30 -> 45.711668 | V29: =DATA!AD30 -> 69.9 | W29: =DATA!S30 -> 74.212154 | X29: =DATA!T30 -> 84.396527 | Y29: =DATA!AN30 -> 7.4626667 | Z29: =DATA!AR30 -> 3.4961 | AA29: =DATA!AS30 -> 119.17 | AB29: =LN(AA29/AA28)*100 -> -17.797191 | AC29: =EXP(LN(AA29/AA28)-$AB$1/100)*AC28 -> 123.28569 | AD29: =LN(AC29/AC28)*100 -> -17.671438 | AE29: =DATA!CK30 -> 84.205155 | AF29: =DATA!CL30 -> 91.37373 | AG29: =DATA!CM30 -> 83.518 | AH29: =DATA!CO30 -> 72.065 | AI29: =DATA!CN30 -> 5.51 | AJ29: =DATA!CP30 -> 51.565524 | AK29: =DATA!CR30 -> 18.76 | AL29: =DATA!BZ30 -> 1061344 | AM29: =DATA!CB30 -> 630071.55 | AN29: =DATA!CC30 -> 86108.864 | AO29: =DATA!CD30 -> 543962.69 | AP29: =DATA!CA30 -> 28252.414 | AQ29: =DATA!CE30 -> 403020.04 | AR29: =DATA!CF30 -> 81614.577 | AS29: =DATA!CG30 -> 63213.675 | AT29: =DATA!CH30 -> 682095.31 | AU29: =DATA!CI30 -> 234420.44 | AV29: =DATA!AQ30 -> 3.634
A30: 1998-1 | B30: =DATA!O31 -> 125345 | C30: =DATA!I31 -> 52628 | D30: =DATA!J31 -> 8423 | E30: =DATA!K31 -> 35140.48 | F30: =DATA!M31 -> 96637.115 | G30: =DATA!N31 -> 76181.89 | H30: =DATA!W31 -> 3348.2355 | I30: =DATA!X31 -> 6283.5318 | J30: =DATA!BI31 -> 9874.9044 | K30: =DATA!BJ31 -> 1880.5274 | L30: =DATA!BG31 -> 2099.1574 | M30: =DATA!BH31 -> 1537.2232 | N30: =O30+R30 -> 22124.229 | O30: =P30+Q30 -> 18787.654 | P30: =DATA!BD31 -> 5800.1616 | Q30: =DATA!BE31 -> 12987.492 | R30: =DATA!BF31 -> 3336.5746 | S30: 76.014331 | T30: =DATA!AG31 -> 82.664781 | U30: =DATA!AH31 -> 49.41253 | V30: =DATA!AD31 -> 69.9 | W30: =DATA!S31 -> 80.077865 | X30: =DATA!T31 -> 88.254176 | Y30: =DATA!AN31 -> 9.9893333 | Z30: =DATA!AR31 -> 3.9848 | AA30: =DATA!AS31 -> 110.46 | AB30: =LN(AA30/AA29)*100 -> -7.5897581 | AC30: =EXP(LN(AA30/AA29)-$AB$1/100)*AC29 -> 114.41867 | AD30: =LN(AC30/AC29)*100 -> -7.4640052 | AE30: =DATA!CK31 -> 86.125276 | AF30: =DATA!CL31 -> 92.046631 | AG30: =DATA!CM31 -> 82.678 | AH30: =DATA!CO31 -> 72.277 | AI30: =DATA!CN31 -> 5.52 | AJ30: =DATA!CP31 -> 49.142449 | AK30: =DATA!CR31 -> 14.1 | AL30: =DATA!BZ31 -> 1029215.6 | AM30: =DATA!CB31 -> 640018 | AN30: =DATA!CC31 -> 83896.609 | AO30: =DATA!CD31 -> 556121.39 | AP30: =DATA!CA31 -> 27389.944 | AQ30: =DATA!CE31 -> 361807.65 | AR30: =DATA!CF31 -> 85127.844 | AS30: =DATA!CG31 -> 49859.978 | AT30: =DATA!CH31 -> 690025.41 | AU30: =DATA!CI31 -> 204202.36 | AV30: =DATA!AQ31 -> 2.554
A31: 1998-2 | B31: =DATA!O32 -> 124770 | C31: =DATA!I32 -> 48667 | D31: =DATA!J32 -> 10526 | E31: =DATA!K32 -> 30141.04 | F31: =DATA!M32 -> 97553.286 | G31: =DATA!N32 -> 71008.778 | H31: =DATA!W32 -> 3326.0414 | I31: =DATA!X32 -> 5517.0761 | J31: =DATA!BI32 -> 14998.645 | K31: =DATA!BJ32 -> 3855.478 | L31: =DATA!BG32 -> 1339.485 | M31: =DATA!BH32 -> 2944.0686 | N31: =O31+R31 -> 22523.686 | O31: =P31+Q31 -> 18269.034 | P31: =DATA!BD32 -> 4144.0376 | Q31: =DATA!BE32 -> 14124.996 | R31: =DATA!BF32 -> 4254.6522 | S31: 77.070328 | T31: =DATA!AG32 -> 83.874289 | U31: =DATA!AH32 -> 49.854484 | V31: =DATA!AD32 -> 69.9 | W31: =DATA!S32 -> 77.357254 | X31: =DATA!T32 -> 87.353988 | Y31: =DATA!AN32 -> 10.065667 | Z31: =DATA!AR32 -> 3.8539 | AA31: =DATA!AS32 -> 114.02667 | AB31: =LN(AA31/AA30)*100 -> 3.1778875 | AC31: =EXP(LN(AA31/AA30)-$AB$1/100)*AC30 -> 118.26178 | AD31: =LN(AC31/AC30)*100 -> 3.3036403 | AE31: =DATA!CK32 -> 86.478154 | AF31: =DATA!CL32 -> 92.730958 | AG31: =DATA!CM32 -> 82.234 | AH31: =DATA!CO32 -> 72.498 | AI31: =DATA!CN32 -> 5.5 | AJ31: =DATA!CP32 -> 48.160079 | AK31: =DATA!CR32 -> 13.31 | AL31: =DATA!BZ32 -> 999803.58 | AM31: =DATA!CB32 -> 641255.21 | AN31: =DATA!CC32 -> 80363.995 | AO31: =DATA!CD32 -> 560891.21 | AP31: =DATA!CA32 -> 29095.416 | AQ31: =DATA!CE32 -> 329452.96 | AR31: =DATA!CF32 -> 78944.575 | AS31: =DATA!CG32 -> 47705.902 | AT31: =DATA!CH32 -> 677060.82 | AU31: =DATA!CI32 -> 196092.29 | AV31: =DATA!AQ32 -> 3.4476667
A32: 1998-3 | B32: =DATA!O33 -> 126001 | C32: =DATA!I33 -> 50309 | D32: =DATA!J33 -> 11547 | E32: =DATA!K33 -> 25222.515 | F32: =DATA!M33 -> 99868.272 | G32: =DATA!N33 -> 70513.46 | H32: =DATA!W33 -> 3325.7469 | I32: =DATA!X33 -> 5032.894 | J32: =DATA!BI33 -> 10530.118 | K32: =DATA!BJ33 -> 5493.7619 | L32: =DATA!BG33 -> 1620.4163 | M32: =DATA!BH33 -> 2179.2194 | N32: =O32+R32 -> 22119.096 | O32: =P32+Q32 -> 16942.547 | P32: =DATA!BD33 -> 4676.9767 | Q32: =DATA!BE33 -> 12265.571 | R32: =DATA!BF33 -> 5176.5489 | S32: 77.366528 | T32: =DATA!AG33 -> 84.468656 | U32: =DATA!AH33 -> 48.958016 | V32: =DATA!AD33 -> 69.9 | W32: =DATA!S33 -> 80.483568 | X32: =DATA!T33 -> 89.644378 | Y32: =DATA!AN33 -> 8.461 | Z32: =DATA!AR33 -> 4.0591 | AA32: =DATA!AS33 -> 110.56667 | AB32: =LN(AA32/AA31)*100 -> -3.0813682 | AC32: =EXP(LN(AA32/AA31)-$AB$1/100)*AC31 -> 114.81757 | AD32: =LN(AC32/AC31)*100 -> -2.9556153 | AE32: =DATA!CK33 -> 87.155225 | AF32: =DATA!CL33 -> 93.465965 | AG32: =DATA!CM33 -> 81.561 | AH32: =DATA!CO33 -> 72.756 | AI32: =DATA!CN33 -> 5.53 | AJ32: =DATA!CP33 -> 45.148292 | AK32: =DATA!CR33 -> 12.46 | AL32: =DATA!BZ33 -> 934805.96 | AM32: =DATA!CB33 -> 613256.06 | AN32: =DATA!CC33 -> 74514.747 | AO32: =DATA!CD33 -> 538741.31 | AP32: =DATA!CA33 -> 28784.535 | AQ32: =DATA!CE33 -> 292765.36 | AR32: =DATA!CF33 -> 74210.095 | AS32: =DATA!CG33 -> 36534.937 | AT32: =DATA!CH33 -> 648296.45 | AU32: =DATA!CI33 -> 175764.48 | AV32: =DATA!AQ33 -> 4.0956667
A33: 1998-4 | B33: =DATA!O34 -> 125063 | C33: =DATA!I34 -> 51757 | D33: =DATA!J34 -> 13798 | E33: =DATA!K34 -> 30832.059 | F33: =DATA!M34 -> 104276.15 | G33: =DATA!N34 -> 71505.144 | H33: =DATA!W34 -> 3487.56 | I33: =DATA!X34 -> 4955.7102 | J33: =DATA!BI34 -> 15985.396 | K33: =DATA!BJ34 -> 15235.139 | L33: =DATA!BG34 -> 2454.9006 | M33: =DATA!BH34 -> 4143.3044 | N33: =O33+R33 -> 22039.271 | O33: =P33+Q33 -> 17056.2 | P33: =DATA!BD34 -> 4486.1399 | Q33: =DATA!BE34 -> 12570.06 | R33: =DATA!BF34 -> 4983.0709 | S33: 77.770288 | T33: =DATA!AG34 -> 84.664628 | U33: =DATA!AH34 -> 50.192927 | V33: =DATA!AD34 -> 69.9 | W33: =DATA!S34 -> 78.076541 | X33: =DATA!T34 -> 86.605783 | Y33: =DATA!AN34 -> 5.9446667 | Z33: =DATA!AR34 -> 3.8005 | AA33: =DATA!AS34 -> 111.03 | AB33: =LN(AA33/AA32)*100 -> 0.41817778 | AC33: =EXP(LN(AA33/AA32)-$AB$1/100)*AC32 -> 115.4438 | AD33: =LN(AC33/AC32)*100 -> 0.54393065 | AE33: =DATA!CK34 -> 87.976281 | AF33: =DATA!CL34 -> 94.291183 | AG33: =DATA!CM34 -> 81.249 | AH33: =DATA!CO34 -> 72.988 | AI33: =DATA!CN34 -> 4.86 | AJ33: =DATA!CP34 -> 43.818511 | AK33: =DATA!CR34 -> 11.21 | AL33: =DATA!BZ34 -> 942363.27 | AM33: =DATA!CB34 -> 603077.94 | AN33: =DATA!CC34 -> 74340.92 | AO33: =DATA!CD34 -> 528737.02 | AP33: =DATA!CA34 -> 29296.933 | AQ33: =DATA!CE34 -> 309988.39 | AR33: =DATA!CF34 -> 74839.311 | AS33: =DATA!CG34 -> 41989.799 | AT33: =DATA!CH34 -> 662659.02 | AU33: =DATA!CI34 -> 162875.14 | AV33: =DATA!AQ34 -> 4.0686667
A34: 1999-1 | B34: =DATA!O35 -> 124104 | C34: =DATA!I35 -> 51225 | D34: =DATA!J35 -> 9629 | E34: =DATA!K35 -> 26335.079 | F34: =DATA!M35 -> 98670.274 | G34: =DATA!N35 -> 69796.666 | H34: =DATA!W35 -> 3472.8805 | I34: =DATA!X35 -> 5219.7224 | J34: =DATA!BI35 -> 11202.599 | K34: =DATA!BJ35 -> 1450.1585 | L34: =DATA!BG35 -> 2249.1576 | M34: =DATA!BH35 -> 1827.2329 | N34: =O34+R34 -> 18800.566 | O34: =P34+Q34 -> 14963.377 | P34: =DATA!BD35 -> 4923.5622 | Q34: =DATA!BE35 -> 10039.814 | R34: =DATA!BF35 -> 3837.1892 | S34: 79.061583 | T34: =DATA!AG35 -> 85.167747 | U34: =DATA!AH35 -> 54.636929 | V34: =DATA!AD35 -> 69.9 | W34: =DATA!S35 -> 76.478729 | X34: =DATA!T35 -> 86.141956 | Y34: =DATA!AN35 -> 5.2136667 | Z34: =DATA!AR35 -> 3.8 | AA34: =DATA!AS35 -> 111.91667 | AB34: =LN(AA34/AA33)*100 -> 0.79541117 | AC34: =EXP(LN(AA34/AA33)-$AB$1/100)*AC33 -> 116.51214 | AD34: =LN(AC34/AC33)*100 -> 0.92116404 | AE34: =DATA!CK35 -> 88.936011 | AF34: =DATA!CL35 -> 95.215539 | AG34: =DATA!CM35 -> 81.052 | AH34: =DATA!CO35 -> 73.171 | AI34: =DATA!CN35 -> 4.73 | AJ34: =DATA!CP35 -> 42.049951 | AK34: =DATA!CR35 -> 11.37 | AL34: =DATA!BZ35 -> 1025096.2 | AM34: =DATA!CB35 -> 639847.41 | AN34: =DATA!CC35 -> 79592.658 | AO34: =DATA!CD35 -> 560254.75 | AP34: =DATA!CA35 -> 30864.724 | AQ34: =DATA!CE35 -> 354384.11 | AR34: =DATA!CF35 -> 80396.395 | AS34: =DATA!CG35 -> 44014.588 | AT34: =DATA!CH35 -> 728293.89 | AU34: =DATA!CI35 -> 172391.37 | AV34: =DATA!AQ35 -> 4.3663333
A35: 1999-2 | B35: =DATA!O36 -> 130749 | C35: =DATA!I36 -> 49434 | D35: =DATA!J36 -> 11027 | E35: =DATA!K36 -> 26791.331 | F35: =DATA!M36 -> 109959.03 | G35: =DATA!N36 -> 77315.127 | H35: =DATA!W36 -> 3425.2936 | I35: =DATA!X36 -> 5325.3495 | J35: =DATA!BI36 -> 11348.751 | K35: =DATA!BJ36 -> 8505.9639 | L35: =DATA!BG36 -> 1374.2003 | M35: =DATA!BH36 -> 3367.5106 | N35: =O35+R35 -> 24793.197 | O35: =P35+Q35 -> 19737.932 | P35: =DATA!BD36 -> 5260.0356 | Q35: =DATA!BE36 -> 14477.896 | R35: =DATA!BF36 -> 5055.2654 | S35: 79.113928 | T35: =DATA!AG36 -> 85.46324 | U35: =DATA!AH36 -> 53.716681 | V35: =DATA!AD36 -> 69.681481 | W35: =DATA!S36 -> 76.311563 | X35: =DATA!T36 -> 85.821415 | Y35: =DATA!AN36 -> 3.0656667 | Z35: =DATA!AR36 -> 3.8 | AA35: =DATA!AS36 -> 113.43667 | AB35: =LN(AA35/AA34)*100 -> 1.3490132 | AC35: =EXP(LN(AA35/AA34)-$AB$1/100)*AC34 -> 118.24315 | AD35: =LN(AC35/AC34)*100 -> 1.474766 | AE35: =DATA!CK36 -> 90.99663 | AF35: =DATA!CL36 -> 96.184584 | AG35: =DATA!CM36 -> 81.21 | AH35: =DATA!CO36 -> 73.425 | AI35: =DATA!CN36 -> 4.75 | AJ35: =DATA!CP36 -> 45.626233 | AK35: =DATA!CR36 -> 15.48 | AL35: =DATA!BZ36 -> 1007467.4 | AM35: =DATA!CB36 -> 617753.8 | AN35: =DATA!CC36 -> 79118.358 | AO35: =DATA!CD36 -> 538635.44 | AP35: =DATA!CA36 -> 31356.671 | AQ35: =DATA!CE36 -> 358356.92 | AR35: =DATA!CF36 -> 75607.975 | AS35: =DATA!CG36 -> 42435.457 | AT35: =DATA!CH36 -> 717724.39 | AU35: =DATA!CI36 -> 171699.57 | AV35: =DATA!AQ36 -> 5.671
A36: 1999-3 | B36: =DATA!O37 -> 137441 | C36: =DATA!I37 -> 52370 | D36: =DATA!J37 -> 14478 | E36: =DATA!K37 -> 27961.109 | F36: =DATA!M37 -> 118325.17 | G36: =DATA!N37 -> 82959.633 | H36: =DATA!W37 -> 3521.4835 | I36: =DATA!X37 -> 5612.0393 | J36: =DATA!BI37 -> 14552.141 | K36: =DATA!BJ37 -> 11536.625 | L36: =DATA!BG37 -> 1670.322 | M36: =DATA!BH37 -> 2511.6466 | N36: =O36+R36 -> 21567.802 | O36: =P36+Q36 -> 16804.919 | P36: =DATA!BD37 -> 4115.7105 | Q36: =DATA!BE37 -> 12689.208 | R36: =DATA!BF37 -> 4762.8832 | S36: 79.16511 | T36: =DATA!AG37 -> 85.617366 | U36: =DATA!AH37 -> 53.356083 | V36: =DATA!AD37 -> 69.9 | W36: =DATA!S37 -> 78.48112 | X36: =DATA!T37 -> 87.113428 | Y36: =DATA!AN37 -> 2.549 | Z36: =DATA!AR37 -> 3.8 | AA36: =DATA!AS37 -> 112.01667 | AB36: =LN(AA36/AA35)*100 -> -1.2597008 | AC36: =EXP(LN(AA36/AA35)-$AB$1/100)*AC35 -> 116.90991 | AD36: =LN(AC36/AC35)*100 -> -1.133948 | AE36: =DATA!CK37 -> 93.487758 | AF36: =DATA!CL37 -> 97.438874 | AG36: =DATA!CM37 -> 81.316 | AH36: =DATA!CO37 -> 73.695 | AI36: =DATA!CN37 -> 5.1 | AJ36: =DATA!CP37 -> 49.6544 | AK36: =DATA!CR37 -> 20.64 | AL36: =DATA!BZ37 -> 975093.91 | AM36: =DATA!CB37 -> 589609.62 | AN36: =DATA!CC37 -> 77028.132 | AO36: =DATA!CD37 -> 512581.49 | AP36: =DATA!CA37 -> 26371.208 | AQ36: =DATA!CE37 -> 359113.08 | AR36: =DATA!CF37 -> 76231.42 | AS36: =DATA!CG37 -> 38388.755 | AT36: =DATA!CH37 -> 686766.44 | AU36: =DATA!CI37 -> 173707.29 | AV36: =DATA!AQ37 -> 5.5576667
... A137: 2024-4 | B137: =DATA!O138 -> 430476.82 | C137: =DATA!I138 -> 253019.38 | D137: =DATA!J138 -> 67505.818 | E137: =DATA!K138 -> 89038.862 | F137: =DATA!M138 -> 290282.36 | G137: =DATA!N138 -> 268888.35 | H137: =DATA!W138 -> 10617.573 | I137: =DATA!X138 -> 9747 | J137: =DATA!BI138 -> 38611.049 | K137: =DATA!BJ138 -> 26898.868 | L137: =DATA!BG138 -> 24916.801 | M137: =DATA!BH138 -> 12061.975 | N137: =O137+R137 -> 84474.571 | O137: =P137+Q137 -> 59546.591 | P137: =DATA!BD138 -> 19563.049 | Q137: =DATA!BE138 -> 39983.542 | R137: =DATA!BF138 -> 24927.98 | S137: 133.36667 | T137: =DATA!AG138 -> 131.8 | U137: =DATA!AH138 -> 139.63333 | V137: =DATA!AD138 -> 110.43444 | W137: =DATA!S138 -> 124.0516 | X137: =DATA!T138 -> 120.56248 | Y137: =DATA!AN138 -> 3 | Z137: =DATA!AR138 -> 4.3939 | AA137: =DATA!AS138 -> 103.91333 | AB137: =LN(AA137/AA136)*100 -> 2.2743368 | AC137: =EXP(LN(AA137/AA136)-$AB$1/100)*AC136 -> 123.14021 | AD137: =LN(AC137/AC136)*100 -> 2.4000897 | AE137: =DATA!CK138 -> 252.30002 | AF137: =DATA!CL138 -> 227.02351 | AG137: =DATA!CM138 -> 122.186 | AH137: =DATA!CO138 -> 123.997 | AI137: =DATA!CN138 -> 4.65 | AJ137: =DATA!CP138 -> 166.47995 | AK137: =DATA!CR138 -> 74.66 | AL137: =DATA!BZ138 -> 3147391.7 | AM137: =DATA!CB138 -> 1851582.9 | AN137: =DATA!CC138 -> 317294.34 | AO137: =DATA!CD138 -> 1534288.5 | AP137: =DATA!CA138 -> 328220.42 | AQ137: =DATA!CE138 -> 967588.48 | AR137: =DATA!CF138 -> 349497.44 | AS137: =DATA!CG138 -> 122754.38 | AT137: =DATA!CH138 -> 2198598.2 | AU137: =DATA!CI138 -> 476541.69 | AV137: =DATA!AQ138 -> 2.1499293
A138: 2025-1 | B138: =DATA!O139 -> 415337.61 | C138: =DATA!I139 -> 258562.9 | D138: =DATA!J139 -> 51200.647 | E138: =DATA!K139 -> 93243.344 | F138: =DATA!M139 -> 278486.04 | G138: =DATA!N139 -> 258359.62 | H138: =DATA!W139 -> 10579.011 | I138: =DATA!X139 -> 9653 | J138: =DATA!BI139 -> 38456.312 | K138: =DATA!BJ139 -> 15058.179 | L138: =DATA!BG139 -> 19724.612 | M138: =DATA!BH139 -> 7320.4835 | N138: =O138+R138 -> 61791.049 | O138: =P138+Q138 -> 48641.603 | P138: =DATA!BD139 -> 19484.108 | Q138: =DATA!BE139 -> 29157.495 | R138: =DATA!BF139 -> 13149.446 | S138: 133.9 | T138: =DATA!AG139 -> 132.7 | U138: =DATA!AH139 -> 138.7 | V138: =DATA!AD139 -> 110.84963 | W138: =DATA!S139 -> 124.34232 | X138: =DATA!T139 -> 120.45909 | Y138: =DATA!AN139 -> 3 | Z138: =DATA!AR139 -> 4.4453 | AA138: =DATA!AS139 -> 103.89 | AB138: =LN(AA138/AA137)*100 -> -0.022457131 | AC138: =EXP(LN(AA138/AA137)-$AB$1/100)*AC137 -> 123.26747 | AE138: =DATA!CK139 -> 256.99448 | AF138: =DATA!CL139 -> 229.03415 | AG138: =DATA!CM139 -> 123.844 | AH138: =DATA!CO139 -> 125 | AI138: =DATA!CN139 -> 4.33 | AJ138: =DATA!CP139 -> 170.9364 | AK138: =DATA!CR139 -> 75.87 | AL138: =DATA!BZ139 -> 3181662.6 | AM138: =DATA!CB139 -> 1867997.2 | AN138: =DATA!CC139 -> 319985.87 | AO138: =DATA!CD139 -> 1548011.3 | AP138: =DATA!CA139 -> 324438.47 | AQ138: =DATA!CE139 -> 989226.94 | AR138: =DATA!CF139 -> 352340.14 | AS138: =DATA!CG139 -> 126297.83 | AT138: =DATA!CH139 -> 2222115.6 | AU138: =DATA!CI139 -> 480909.07 | AV138: =DATA!AQ139 -> 2.0135958
A139: 2025-2 | B139: =DATA!O140 -> 419420.24 | C139: =DATA!I140 -> 256125.05 | D139: =DATA!J140 -> 51007.323 | E139: =DATA!K140 -> 99725.656 | F139: =DATA!M140 -> 281729.7 | G139: =DATA!N140 -> 277851.24 | H139: =DATA!W140 -> 10430.403 | I139: =DATA!X140 -> 9703 | J139: =DATA!BI140 -> 35251.346 | K139: =DATA!BJ140 -> 13031.144 | L139: =DATA!BG140 -> 17201.351 | M139: =DATA!BH140 -> 15299.634 | N139: =O139+R139 -> 64848.218 | O139: =P139+Q139 -> 53536.038 | P139: =DATA!BD140 -> 22627.915 | Q139: =DATA!BE140 -> 30908.123 | R139: =DATA!BF140 -> 11312.18 | S139: 134.4 | T139: =DATA!AG140 -> 133.5 | U139: =DATA!AH140 -> 138 | V139: =DATA!AD140 -> 110.28148 | W139: =DATA!S140 -> 122.57944 | X139: =DATA!T140 -> 119.34845 | Y139: =DATA!AN140 -> 3 | Z139: =DATA!AR140 -> 4.3075 | AA139: =DATA!AS140 -> 104.17667 | AB139: =LN(AA139/AA138)*100 -> 0.27555288 | AC139: =EXP(LN(AA139/AA138)-$AB$1/100)*AC138 -> 123.76314 | AE139: =DATA!CK140 -> 259.23284 | AF139: =DATA!CL140 -> 231.02747 | AG139: =DATA!CM140 -> 123.429 | AH139: =DATA!CO140 -> 125.804 | AI139: =DATA!CN140 -> 4.33 | AJ139: =DATA!CP140 -> 163.3783 | AK139: =DATA!CR140 -> 68.07 | AL139: =DATA!BZ140 -> 3231120.9 | AM139: =DATA!CB140 -> 1893311.8 | AN139: =DATA!CC140 -> 325294.84 | AO139: =DATA!CD140 -> 1568017 | AP139: =DATA!CA140 -> 341721.95 | AQ139: =DATA!CE140 -> 996087.15 | AR139: =DATA!CF140 -> 361223.91 | AS139: =DATA!CG140 -> 111808.18 | AT139: =DATA!CH140 -> 2223538.9 | AU139: =DATA!CI140 -> 534549.91 | AV139: =DATA!AQ140 -> 1.9160708
A140: 2025-3 | B140: =DATA!O141 -> 443208.4 | C140: =DATA!I141 -> 271562.38 | D140: =DATA!J141 -> 56763.071 | E140: =DATA!K141 -> 95881.078 | F140: =DATA!M141 -> 296897.35 | G140: =DATA!N141 -> 276061.35 | H140: =DATA!W141 -> 10344.033 | I140: =DATA!X141 -> 9795 | J140: =DATA!BI141 -> 39764.885 | K140: =DATA!BJ141 -> 17288.642 | L140: =DATA!BG141 -> 21022.186 | M140: =DATA!BH141 -> 10375.242 | N140: =O140+R140 -> 80410.054 | O140: =P140+Q140 -> 65224.107 | P140: =DATA!BD141 -> 23387.95 | Q140: =DATA!BE141 -> 41836.156 | R140: =DATA!BF141 -> 15185.948 | S140: 134.9 | T140: =DATA!AG141 -> 134.3 | U140: =DATA!AH141 -> 137.3 | V140: =DATA!AD141 -> 109.01889 | W140: =DATA!S141 -> 122.51773 | X140: =DATA!T141 -> 119.23887 | Y140: =DATA!AN141 -> 2.75 | Z140: =DATA!AR141 -> 4.2232 | AA140: =DATA!AS141 -> 105.14 | AB140: =LN(AA140/AA139)*100 -> 0.92046195 | AC140: =EXP(LN(AA140/AA139)-$AB$1/100)*AC139 -> 125.06477 | AE140: =DATA!CK141 -> 260.6366 | AF140: =DATA!CL141 -> 232.57194 | AG140: =DATA!CM141 -> 124.295 | AH140: =DATA!CO141 -> 126.699 | AI140: =DATA!CN141 -> 4.29 | AJ140: =DATA!CP141 -> 165.50667 | AK140: =DATA!CR141 -> 69.03 | AL140: =DATA!BZ141 -> 3258297.6 | AM140: =DATA!CB141 -> 1913069.5 | AN140: =DATA!CC141 -> 327992.76 | AO140: =DATA!CD141 -> 1585076.7 | AP140: =DATA!CA141 -> 350380.9 | AQ140: =DATA!CE141 -> 994847.18 | AR140: =DATA!CF141 -> 358565.71 | AS140: =DATA!CG141 -> 122909.98 | AT140: =DATA!CH141 -> 2239723.1 | AU140: =DATA!CI141 -> 537098.78 | AV140: =DATA!AQ141 -> 2.0015542
A141: 2025-4 | B141: =DATA!O142 -> 457680.93 | C141: =DATA!I142 -> 266319.87 | D141: =DATA!J142 -> 72895.887 | E141: =DATA!K142 -> 97329.094 | F141: =DATA!M142 -> 301695.52 | G141: =DATA!N142 -> 290094.35 | H141: =DATA!W142 -> 10740.001 | I141: =DATA!X142 -> 9880 | J141: =DATA!BI142 -> 42759.937 | K141: =DATA!BJ142 -> 23759.742 | L141: =DATA!BG142 -> 23516.635 | M141: =DATA!BH142 -> 13097.34 | N141: =O141+R141 -> 81276.687 | O141: =P141+Q141 -> 55504.585 | P141: =DATA!BD142 -> 21532.58 | Q141: =DATA!BE142 -> 33972.004 | R141: =DATA!BF142 -> 25772.102 | S141: 135.2 | T141: =DATA!AG142 -> 134.8 | U141: =DATA!AH142 -> 136.8 | V141: =DATA!AD142 -> 105.96222 | W141: =DATA!S142 -> 126.07463 | X141: =DATA!T142 -> 121.226 | Y141: =DATA!AN142 -> 2.75 | Z141: =DATA!AR142 -> 4.1519 | AA141: =DATA!AS142 -> 107.81 | AB141: =LN(AA141/AA140)*100 -> 2.5077623 | AC141: =EXP(LN(AA141/AA140)-$AB$1/100)*AC140 -> 128.40212 | AE141: =DATA!CK142 -> 262.48829 | AF141: =DATA!CL142 -> 234.30886 | AG141: =DATA!CM142 -> 124.73 | AH141: =DATA!CO142 -> 127.545 | AI141: =DATA!CN142 -> 3.9 | AJ141: =DATA!CP142 -> 169.06807 | AK141: =DATA!CR142 -> 63.65 | AL141: =DATA!BZ142 -> 3299830.8 | AM141: =DATA!CB142 -> 1946464.9 | AN141: =DATA!CC142 -> 333718.35 | AO141: =DATA!CD142 -> 1612746.5 | AP141: =DATA!CA142 -> 337207.42 | AQ141: =DATA!CE142 -> 1016158.5 | AR141: =DATA!CF142 -> 366683.35 | AS141: =DATA!CG142 -> 116585.4 | AT141: =DATA!CH142 -> 2274819.5 | AU141: =DATA!CI142 -> 541742.54 | AV141: =DATA!AQ142 -> 1.9121306
A142: 2026-1 | Z142: =DATA!AR143 -> 3.959 | AA142: =(1+-(Z142/Z141-1)*100/100)*AA141 -> 112.81892 | AB142: =LN(AA142/AA141)*100 -> 4.5413667 | AC142: =EXP(LN(AA142/AA141)-$AB$1/100)*AC141 -> 134.53685 | AK142: =DATA!CR143 -> 79.98
A143: 2026-2
A144: 2026-3
A145: 2026-4
A146: 2027-1
A147: 2027-2
A148: 2027-3
A149: 2027-4

Sheet YoY
A1: dlnv_t | B1: dlnc_t | C1: dlng_t | D1: dlni_t | E1: dlnx_t | F1: dlnm_t | G1: dlnl_t | H1: piw_t | I1: dlncg_t | J1: dlnig_t | K1: dlntr_t | M1: dlngr_t | N1: dlntx_t | O1: dlntxh_t | P1: dlntxf_t | Q1: dlnntx_t | R1: pic_t | S1: corepic_t | T1: ncorepic_t | U1: pie_t | V1: dlnpx_t | W1: pim_t | X1: r_t | Y1: dlne_t | Z1: dlnzf_t | AA1: dlnvf_t | AB1: pixf_t | AC1: picf_t | AD1: rf_t | AE1: pipcomf_t | AG1: dlncredit_t | AH1: dlncredith_t | AI1: dlncreditf_t | AJ1: dlnlendg_t | AK1: dlnoa_t | AL1: dlnnetworth_t | AM1: dlnloan_t | AN1: dlndepp_t | AO1: dlnol_t | AP1: spread_t | AQ1: nombot_t
A2: Real GDP | B2: Household consumption | C2: Government consumption | D2: Business investment | E2: Exports | F2: Imports | G2: Labour hours | H2: Wages | I2: Fed gov consumption | J2: Fed gov investment | K2: Government transfer | L2: Debt serivices | M2: Government revenue | N2: Tax revenue | O2: Household tax | P2: Firm tax | Q2: Non tax revenue | R2: Headline CPI | S2: Core CPI | T2: Non core CPI | U2: Energy CPI | V2: Export deflator | W2: Import deflator | X2: OPR | Y2: NEER | Z2: Global Trade | AA2: Global GDP | AB2: Global export price | AC2: Global CPI | AD2: FFR | AE2: Global commodity price | AF2: Brent crude oil | AG2: Credit, total | AH2: ='SA data'!AJ1 -> Credit to households | AI2: ='SA data'!AK1 -> Credit to firms | AJ2: ='SA data'!AL1 -> Lending to government | AK2: ='SA data'!AM1 -> Other assets | AL2: ='SA data'!AN1 -> Networth | AM2: ='SA data'!AO1 -> External borrowings | AN2: ='SA data'!AP1 -> Private sector deposit | AO2: ='SA data'!AQ1 -> Other liabiliites | AP2: Spread, risk premkium
A3: =('SA data'!A6/'SA data'!A2-1)*100 -> 9.809903 | B3: =('SA data'!B6/'SA data'!B2-1)*100 -> 6.3138871 | C3: =('SA data'!C6/'SA data'!C2-1)*100 -> 1.5671555 | D3: =('SA data'!D6/'SA data'!D2-1)*100 -> 14.371355 | E3: =('SA data'!E6/'SA data'!E2-1)*100 -> 9.268347 | F3: =('SA data'!F6/'SA data'!F2-1)*100 -> 9.4864179 | G3: =('SA data'!G6/'SA data'!G2-1)*100 -> 2.1952187 | H3: =('SA data'!H6/'SA data'!H2-1)*100 -> 11.085154 | R3: =('SA data'!S6/'SA data'!S2-1)*100 -> 4.4592895 | S3: =('SA data'!T6/'SA data'!T2-1)*100 -> 3.8728348 | T3: =('SA data'!U6/'SA data'!U2-1)*100 -> 11.217304 | U3: =('SA data'!V6/'SA data'!V2-1)*100 -> 0.021290185 | V3: =('SA data'!W6/'SA data'!W2-1)*100 -> -2.8802228 | W3: =('SA data'!X6/'SA data'!X2-1)*100 -> -3.0756035 | X3: ='SA data'!Y6 -> 7.93 | Y3: =('SA data'!Z6/'SA data'!Z2-1)*100 -> 4.2324127 | Z3: =('SA data'!AA6/'SA data'!AA2-1)*100 -> 8.8965877 | AA3: =('SA data'!AB6/'SA data'!AB2-1)*100 -> 4.3116295 | AB3: =('SA data'!AC6/'SA data'!AC2-1)*100 -> -1.2294452 | AC3: =('SA data'!AD6/'SA data'!AD2-1)*100 -> 3.2625055 | AD3: ='SA data'!AE6 -> 4.02 | AF3: =('SA data'!AG6/'SA data'!AG2-1)*100 -> -13.784822 | AP3: ='SA data'!AR6 -> 1.98 | AQ3: 4 | AR3: 33664
A4: =('SA data'!A7/'SA data'!A3-1)*100 -> 10.695565 | B4: =('SA data'!B7/'SA data'!B3-1)*100 -> 4.2705478 | C4: =('SA data'!C7/'SA data'!C3-1)*100 -> 14.57152 | D4: =('SA data'!D7/'SA data'!D3-1)*100 -> 10.116933 | E4: =('SA data'!E7/'SA data'!E3-1)*100 -> 21.058965 | F4: =('SA data'!F7/'SA data'!F3-1)*100 -> 6.7315358 | G4: =('SA data'!G7/'SA data'!G3-1)*100 -> 3.7386746 | H4: =('SA data'!H7/'SA data'!H3-1)*100 -> 7.7349848 | R4: =('SA data'!S7/'SA data'!S3-1)*100 -> 4.6056463 | S4: =('SA data'!T7/'SA data'!T3-1)*100 -> 3.9890268 | T4: =('SA data'!U7/'SA data'!U3-1)*100 -> 11.377101 | U4: =('SA data'!V7/'SA data'!V3-1)*100 -> 0 | V4: =('SA data'!W7/'SA data'!W3-1)*100 -> -4.3383922 | W4: =('SA data'!X7/'SA data'!X3-1)*100 -> -4.4964593 | X4: ='SA data'!Y7 -> 7.9566667 | Y4: =('SA data'!Z7/'SA data'!Z3-1)*100 -> 6.1386095 | Z4: =('SA data'!AA7/'SA data'!AA3-1)*100 -> 7.286348 | AA4: =('SA data'!AB7/'SA data'!AB3-1)*100 -> 4.7081988 | AB4: =('SA data'!AC7/'SA data'!AC3-1)*100 -> -0.57896927 | AC4: =('SA data'!AD7/'SA data'!AD3-1)*100 -> 3.1957604 | AD4: ='SA data'!AE7 -> 3.77 | AF4: =('SA data'!AG7/'SA data'!AG3-1)*100 -> 6.0413355 | AP4: ='SA data'!AR7 -> 2.2133333 | AQ4: 5 | AR4: 33756
A5: =('SA data'!A8/'SA data'!A4-1)*100 -> 7.5262925 | B5: =('SA data'!B8/'SA data'!B4-1)*100 -> 5.4027636 | C5: =('SA data'!C8/'SA data'!C4-1)*100 -> -2.5254036 | D5: =('SA data'!D8/'SA data'!D4-1)*100 -> 14.415231 | E5: =('SA data'!E8/'SA data'!E4-1)*100 -> 8.9226682 | F5: =('SA data'!F8/'SA data'!F4-1)*100 -> 6.657796 | G5: =('SA data'!G8/'SA data'!G4-1)*100 -> -0.740901 | H5: =('SA data'!H8/'SA data'!H4-1)*100 -> 7.6209763 | R5: =('SA data'!S8/'SA data'!S4-1)*100 -> 5.0346344 | S5: =('SA data'!T8/'SA data'!T4-1)*100 -> 3.6630624 | T5: =('SA data'!U8/'SA data'!U4-1)*100 -> 20.34862 | U5: =('SA data'!V8/'SA data'!V4-1)*100 -> 0 | V5: =('SA data'!W8/'SA data'!W4-1)*100 -> -3.6121458 | W5: =('SA data'!X8/'SA data'!X4-1)*100 -> -4.3146247 | X5: ='SA data'!Y8 -> 7.8433333 | Y5: =('SA data'!Z8/'SA data'!Z4-1)*100 -> 5.2609698 | Z5: =('SA data'!AA8/'SA data'!AA4-1)*100 -> 6.1025709 | AA5: =('SA data'!AB8/'SA data'!AB4-1)*100 -> 4.8522676 | AB5: =('SA data'!AC8/'SA data'!AC4-1)*100 -> 0.092169208 | AC5: =('SA data'!AD8/'SA data'!AD4-1)*100 -> 2.8807894 | AD5: ='SA data'!AE8 -> 3.26 | AF5: =('SA data'!AG8/'SA data'!AG4-1)*100 -> 1.1071968 | AP5: ='SA data'!AR8 -> 2.4566667 | AQ5: 6 | AR5: 33848
A6: =('SA data'!A9/'SA data'!A5-1)*100 -> 7.9213739 | B6: =('SA data'!B9/'SA data'!B5-1)*100 -> 2.3208611 | C6: =('SA data'!C9/'SA data'!C5-1)*100 -> 6.6408186 | D6: =('SA data'!D9/'SA data'!D5-1)*100 -> 4.7892287 | E6: =('SA data'!E9/'SA data'!E5-1)*100 -> 11.974106 | F6: =('SA data'!F9/'SA data'!F5-1)*100 -> 2.9610458 | G6: =('SA data'!G9/'SA data'!G5-1)*100 -> 1.703406 | H6: =('SA data'!H9/'SA data'!H5-1)*100 -> 8.0097919 | ... Q6: =('SA data'!Q9/'SA data'!Q5-1)*100 -> 24.552487 | R6: =('SA data'!S9/'SA data'!S5-1)*100 -> 4.7909536 | S6: =('SA data'!T9/'SA data'!T5-1)*100 -> 3.3262948 | T6: =('SA data'!U9/'SA data'!U5-1)*100 -> 20.984868 | U6: =('SA data'!V9/'SA data'!V5-1)*100 -> 0 | V6: =('SA data'!W9/'SA data'!W5-1)*100 -> -2.3828382 | W6: =('SA data'!X9/'SA data'!X5-1)*100 -> -3.9677088 | X6: ='SA data'!Y9 -> 7.9366667 | Y6: =('SA data'!Z9/'SA data'!Z5-1)*100 -> 8.1572852 | Z6: =('SA data'!AA9/'SA data'!AA5-1)*100 -> 5.7993919 | AA6: =('SA data'!AB9/'SA data'!AB5-1)*100 -> 5.4028809 | AB6: =('SA data'!AC9/'SA data'!AC5-1)*100 -> -0.26884611 | AC6: =('SA data'!AD9/'SA data'!AD5-1)*100 -> 2.8251086 | AD6: ='SA data'!AE9 -> 3.03 | AF6: =('SA data'!AG9/'SA data'!AG5-1)*100 -> -6.8347067 | AP6: ='SA data'!AR9 -> 2.3333333 | AQ6: 7 | AR6: 33939
A7: =('SA data'!A10/'SA data'!A6-1)*100 -> 8.1097836 | B7: =('SA data'!B10/'SA data'!B6-1)*100 -> -1.4062425 | C7: =('SA data'!C10/'SA data'!C6-1)*100 -> -0.95357794 | D7: =('SA data'!D10/'SA data'!D6-1)*100 -> 7.5548821 | E7: =('SA data'!E10/'SA data'!E6-1)*100 -> 11.59289 | F7: =('SA data'!F10/'SA data'!F6-1)*100 -> 3.6090677 | G7: =('SA data'!G10/'SA data'!G6-1)*100 -> -0.083644307 | H7: =('SA data'!H10/'SA data'!H6-1)*100 -> 2.8047781 | ... Q7: =('SA data'!Q10/'SA data'!Q6-1)*100 -> 16.547865 | R7: =('SA data'!S10/'SA data'!S6-1)*100 -> 4.2372736 | S7: =('SA data'!T10/'SA data'!T6-1)*100 -> 3.015022 | T7: =('SA data'!U10/'SA data'!U6-1)*100 -> 17.391789 | U7: =('SA data'!V10/'SA data'!V6-1)*100 -> 0 | V7: =('SA data'!W10/'SA data'!W6-1)*100 -> 6.8401703 | W7: =('SA data'!X10/'SA data'!X6-1)*100 -> 4.0233931 | X7: ='SA data'!Y10 -> 7.6466667 | Y7: =('SA data'!Z10/'SA data'!Z6-1)*100 -> 1.8523242 | Z7: =('SA data'!AA10/'SA data'!AA6-1)*100 -> 5.7841985 | AA7: =('SA data'!AB10/'SA data'!AB6-1)*100 -> 4.9286972 | AB7: =('SA data'!AC10/'SA data'!AC6-1)*100 -> 0.020346854 | AC7: =('SA data'!AD10/'SA data'!AD6-1)*100 -> 2.7488285 | AD7: ='SA data'!AE10 -> 3.04 | AE7: =('SA data'!AF10/'SA data'!AF6-1)*100 -> 1.6768482 | AF7: =('SA data'!AG10/'SA data'!AG6-1)*100 -> 1.6155989 | AP7: ='SA data'!AR10 -> 2.5733333 | AQ7: 8 | AR7: 34029
A8: =('SA data'!A11/'SA data'!A7-1)*100 -> 12.285142 | B8: =('SA data'!B11/'SA data'!B7-1)*100 -> 6.4982188 | C8: =('SA data'!C11/'SA data'!C7-1)*100 -> 22.095468 | D8: =('SA data'!D11/'SA data'!D7-1)*100 -> 24.698589 | E8: =('SA data'!E11/'SA data'!E7-1)*100 -> 11.922984 | F8: =('SA data'!F11/'SA data'!F7-1)*100 -> 16.927101 | G8: =('SA data'!G11/'SA data'!G7-1)*100 -> 1.3191254 | H8: =('SA data'!H11/'SA data'!H7-1)*100 -> 5.8841392 | ... Q8: =('SA data'!Q11/'SA data'!Q7-1)*100 -> 9.1185943 | R8: =('SA data'!S11/'SA data'!S7-1)*100 -> 3.6246016 | S8: =('SA data'!T11/'SA data'!T7-1)*100 -> 2.5884125 | T8: =('SA data'!U11/'SA data'!U7-1)*100 -> 14.24878 | U8: =('SA data'!V11/'SA data'!V7-1)*100 -> 0 | V8: =('SA data'!W11/'SA data'!W7-1)*100 -> 9.3507931 | W8: =('SA data'!X11/'SA data'!X7-1)*100 -> 5.549493 | X8: ='SA data'!Y11 -> 7.3066667 | Y8: =('SA data'!Z11/'SA data'!Z7-1)*100 -> -3.3890004 | Z8: =('SA data'!AA11/'SA data'!AA7-1)*100 -> 5.9811124 | AA8: =('SA data'!AB11/'SA data'!AB7-1)*100 -> 4.7458544 | AB8: =('SA data'!AC11/'SA data'!AC7-1)*100 -> 0.2032812 | AC8: =('SA data'!AD11/'SA data'!AD7-1)*100 -> 2.8026766 | AD8: ='SA data'!AE11 -> 3 | AE8: =('SA data'!AF11/'SA data'!AF7-1)*100 -> -0.78030132 | AF8: =('SA data'!AG11/'SA data'!AG7-1)*100 -> -8.7956022 | AP8: ='SA data'!AR11 -> 2.8533333 | AQ8: 9 | AR8: 34121
A9: =('SA data'!A12/'SA data'!A8-1)*100 -> 11.001009 | B9: =('SA data'!B12/'SA data'!B8-1)*100 -> 6.4986226 | C9: =('SA data'!C12/'SA data'!C8-1)*100 -> 14.627895 | D9: =('SA data'!D12/'SA data'!D8-1)*100 -> 12.324116 | E9: =('SA data'!E12/'SA data'!E8-1)*100 -> 13.624649 | F9: =('SA data'!F12/'SA data'!F8-1)*100 -> 13.933727 | G9: =('SA data'!G12/'SA data'!G8-1)*100 -> 3.3186697 | H9: =('SA data'!H12/'SA data'!H8-1)*100 -> 4.8124076 | ... Q9: =('SA data'!Q12/'SA data'!Q8-1)*100 -> 3.8946881 | R9: =('SA data'!S12/'SA data'!S8-1)*100 -> 3.0708885 | S9: =('SA data'!T12/'SA data'!T8-1)*100 -> 2.407939 | T9: =('SA data'!U12/'SA data'!U8-1)*100 -> 9.4466635 | U9: =('SA data'!V12/'SA data'!V8-1)*100 -> 0 | V9: =('SA data'!W12/'SA data'!W8-1)*100 -> 6.3594133 | W9: =('SA data'!X12/'SA data'!X8-1)*100 -> 6.066288 | X9: ='SA data'!Y12 -> 6.94 | Y9: =('SA data'!Z12/'SA data'!Z8-1)*100 -> -1.3270675 | Z9: =('SA data'!AA12/'SA data'!AA8-1)*100 -> 5.7089901 | AA9: =('SA data'!AB12/'SA data'!AB8-1)*100 -> 4.8533385 | AB9: =('SA data'!AC12/'SA data'!AC8-1)*100 -> 0.14589986 | AC9: =('SA data'!AD12/'SA data'!AD8-1)*100 -> 2.7691832 | AD9: ='SA data'!AE12 -> 3.06 | AE9: =('SA data'!AF12/'SA data'!AF8-1)*100 -> -3.7599857 | AF9: =('SA data'!AG12/'SA data'!AG8-1)*100 -> -17.919363 | AP9: ='SA data'!AR12 -> 2.99 | AQ9: 10 | AR9: 34213
A10: =('SA data'!A13/'SA data'!A9-1)*100 -> 8.1817651 | B10: =('SA data'!B13/'SA data'!B9-1)*100 -> 14.54869 | C10: =('SA data'!C13/'SA data'!C9-1)*100 -> -1.2868613 | D10: =('SA data'!D13/'SA data'!D9-1)*100 -> 27.361073 | E10: =('SA data'!E13/'SA data'!E9-1)*100 -> 9.1917956 | F10: =('SA data'!F13/'SA data'!F9-1)*100 -> 25.249543 | G10: =('SA data'!G13/'SA data'!G9-1)*100 -> -0.48126749 | H10: =('SA data'!H13/'SA data'!H9-1)*100 -> 3.2010795 | ... Q10: =('SA data'!Q13/'SA data'!Q9-1)*100 -> -9.8253695 | R10: =('SA data'!S13/'SA data'!S9-1)*100 -> 3.3020774 | S10: =('SA data'!T13/'SA data'!T9-1)*100 -> 2.3489954 | T10: =('SA data'!U13/'SA data'!U9-1)*100 -> 12.301724 | U10: =('SA data'!V13/'SA data'!V9-1)*100 -> -0.57471264 | V10: =('SA data'!W13/'SA data'!W9-1)*100 -> 3.4489139 | W10: =('SA data'!X13/'SA data'!X9-1)*100 -> 4.8580673 | X10: ='SA data'!Y13 -> 6.5233333 | Y10: =('SA data'!Z13/'SA data'!Z9-1)*100 -> -1.7452755 | Z10: =('SA data'!AA13/'SA data'!AA9-1)*100 -> 7.6404334 | AA10: =('SA data'!AB13/'SA data'!AB9-1)*100 -> 4.6842307 | AB10: =('SA data'!AC13/'SA data'!AC9-1)*100 -> 0.28874033 | AC10: =('SA data'!AD13/'SA data'!AD9-1)*100 -> 2.5463034 | AD10: ='SA data'!AE13 -> 2.99 | AE10: =('SA data'!AF13/'SA data'!AF9-1)*100 -> -2.9430732 | AF10: =('SA data'!AG13/'SA data'!AG9-1)*100 -> -21.019771 | AP10: ='SA data'!AR13 -> 3.2966667 | AQ10: 11 | AR10: 34304
A11: =('SA data'!A14/'SA data'!A10-1)*100 -> 8.1461574 | B11: =('SA data'!B14/'SA data'!B10-1)*100 -> 13.077173 | C11: =('SA data'!C14/'SA data'!C10-1)*100 -> 18.349252 | D11: =('SA data'!D14/'SA data'!D10-1)*100 -> 17.132816 | E11: =('SA data'!E14/'SA data'!E10-1)*100 -> 20.684116 | F11: =('SA data'!F14/'SA data'!F10-1)*100 -> 25.4204 | G11: =('SA data'!G14/'SA data'!G10-1)*100 -> -2.3122768 | H11: =('SA data'!H14/'SA data'!H10-1)*100 -> 6.3766697 | ... Q11: =('SA data'!Q14/'SA data'!Q10-1)*100 -> -4.492756 | R11: =('SA data'!S14/'SA data'!S10-1)*100 -> 4.0439923 | S11: =('SA data'!T14/'SA data'!T10-1)*100 -> 2.085589 | T11: =('SA data'!U14/'SA data'!U10-1)*100 -> 22.540052 | U11: =('SA data'!V14/'SA data'!V10-1)*100 -> -1.7879949 | V11: =('SA data'!W14/'SA data'!W10-1)*100 -> 4.7477293 | W11: =('SA data'!X14/'SA data'!X10-1)*100 -> 7.0145497 | X11: ='SA data'!Y14 -> 4.0466667 | Y11: =('SA data'!Z14/'SA data'!Z10-1)*100 -> -4.8904362 | Z11: =('SA data'!AA14/'SA data'!AA10-1)*100 -> 8.1926137 | AA11: =('SA data'!AB14/'SA data'!AB10-1)*100 -> 5.215846 | AB11: =('SA data'!AC14/'SA data'!AC10-1)*100 -> 0.61506797 | AC11: =('SA data'!AD14/'SA data'!AD10-1)*100 -> 2.3061788 | AD11: ='SA data'!AE14 -> 3.21 | AE11: =('SA data'!AF14/'SA data'!AF10-1)*100 -> -1.0732172 | AF11: =('SA data'!AG14/'SA data'!AG10-1)*100 -> -23.464912 | AP11: ='SA data'!AR14 -> 5.3033333 | AQ11: 12 | AR11: 34394
A12: =('SA data'!A15/'SA data'!A11-1)*100 -> 7.3896097 | B12: =('SA data'!B15/'SA data'!B11-1)*100 -> 8.99739 | C12: =('SA data'!C15/'SA data'!C11-1)*100 -> -10.459177 | D12: =('SA data'!D15/'SA data'!D11-1)*100 -> 4.270284 | E12: =('SA data'!E15/'SA data'!E11-1)*100 -> 21.065624 | F12: =('SA data'!F15/'SA data'!F11-1)*100 -> 21.958808 | G12: =('SA data'!G15/'SA data'!G11-1)*100 -> 3.5241784 | H12: =('SA data'!H15/'SA data'!H11-1)*100 -> 7.0374239 | ... Q12: =('SA data'!Q15/'SA data'!Q11-1)*100 -> 1.240969 | R12: =('SA data'!S15/'SA data'!S11-1)*100 -> 3.3315691 | S12: =('SA data'!T15/'SA data'!T11-1)*100 -> 1.9789575 | T12: =('SA data'!U15/'SA data'!U11-1)*100 -> 15.784632 | U12: =('SA data'!V15/'SA data'!V11-1)*100 -> -1.2931034 | V12: =('SA data'!W15/'SA data'!W11-1)*100 -> 2.5233813 | W12: =('SA data'!X15/'SA data'!X11-1)*100 -> 3.6500382 | X12: ='SA data'!Y15 -> 4.0666667 | Y12: =('SA data'!Z15/'SA data'!Z11-1)*100 -> -1.020189 | Z12: =('SA data'!AA15/'SA data'!AA11-1)*100 -> 9.7535135 | AA12: =('SA data'!AB15/'SA data'!AB11-1)*100 -> 5.4830448 | AB12: =('SA data'!AC15/'SA data'!AC11-1)*100 -> 0.73152104 | AC12: =('SA data'!AD15/'SA data'!AD11-1)*100 -> 2.2176473 | AD12: ='SA data'!AE15 -> 3.94 | AE12: =('SA data'!AF15/'SA data'!AF11-1)*100 -> 1.6565504 | AF12: =('SA data'!AG15/'SA data'!AG11-1)*100 -> -11.780822 | AP12: ='SA data'!AR15 -> 4.8833333 | AQ12: 13 | AR12: 34486
A13: =('SA data'!A16/'SA data'!A12-1)*100 -> 9.663685 | B13: =('SA data'!B16/'SA data'!B12-1)*100 -> 9.6497672 | C13: =('SA data'!C16/'SA data'!C12-1)*100 -> 3.1823686 | D13: =('SA data'!D16/'SA data'!D12-1)*100 -> 25.193644 | E13: =('SA data'!E16/'SA data'!E12-1)*100 -> 20.516529 | F13: =('SA data'!F16/'SA data'!F12-1)*100 -> 28.563065 | G13: =('SA data'!G16/'SA data'!G12-1)*100 -> 6.2108525 | H13: =('SA data'!H16/'SA data'!H12-1)*100 -> 7.9041556 | ... Q13: =('SA data'!Q16/'SA data'!Q12-1)*100 -> 5.3863749 | R13: =('SA data'!S16/'SA data'!S12-1)*100 -> 3.7556459 | S13: =('SA data'!T16/'SA data'!T12-1)*100 -> 2.2216189 | T13: =('SA data'!U16/'SA data'!U12-1)*100 -> 17.560017 | U13: =('SA data'!V16/'SA data'!V12-1)*100 -> -1.7241379 | V13: =('SA data'!W16/'SA data'!W12-1)*100 -> 5.6516766 | W13: =('SA data'!X16/'SA data'!X12-1)*100 -> 2.6944446 | X13: ='SA data'!Y16 -> 4.0533333 | Y13: =('SA data'!Z16/'SA data'!Z12-1)*100 -> -1.4159193 | Z13: =('SA data'!AA16/'SA data'!AA12-1)*100 -> 11.743277 | AA13: =('SA data'!AB16/'SA data'!AB12-1)*100 -> 5.1925546 | AB13: =('SA data'!AC16/'SA data'!AC12-1)*100 -> 1.2717785 | AC13: =('SA data'!AD16/'SA data'!AD12-1)*100 -> 2.2173717 | AD13: ='SA data'!AE16 -> 4.49 | AE13: =('SA data'!AF16/'SA data'!AF12-1)*100 -> 7.8426891 | AF13: =('SA data'!AG16/'SA data'!AG12-1)*100 -> 1.7586416 | AP13: ='SA data'!AR16 -> 4.4866667 | AQ13: 14 | AR13: 34578
A14: =('SA data'!A17/'SA data'!A13-1)*100 -> 11.531001 | B14: =('SA data'!B17/'SA data'!B13-1)*100 -> 6.4443778 | C14: =('SA data'!C17/'SA data'!C13-1)*100 -> 25.770656 | D14: =('SA data'!D17/'SA data'!D13-1)*100 -> 18.650905 | E14: =('SA data'!E17/'SA data'!E13-1)*100 -> 25.097396 | F14: =('SA data'!F17/'SA data'!F13-1)*100 -> 26.351577 | G14: =('SA data'!G17/'SA data'!G13-1)*100 -> 8.7867009 | H14: =('SA data'!H17/'SA data'!H13-1)*100 -> 8.5987906 | ... Q14: =('SA data'!Q17/'SA data'!Q13-1)*100 -> 16.58202 | R14: =('SA data'!S17/'SA data'!S13-1)*100 -> 3.8284217 | S14: =('SA data'!T17/'SA data'!T13-1)*100 -> 2.4433914 | T14: =('SA data'!U17/'SA data'!U13-1)*100 -> 15.747746 | U14: =('SA data'!V17/'SA data'!V13-1)*100 -> 0.57803468 | V14: =('SA data'!W17/'SA data'!W13-1)*100 -> 7.5864023 | W14: =('SA data'!X17/'SA data'!X13-1)*100 -> 2.3627894 | X14: ='SA data'!Y17 -> 4.6333333 | Y14: =('SA data'!Z17/'SA data'!Z13-1)*100 -> -2.1315565 | Z14: =('SA data'!AA17/'SA data'!AA13-1)*100 -> 10.91935 | AA14: =('SA data'!AB17/'SA data'!AB13-1)*100 -> 4.9480797 | AB14: =('SA data'!AC17/'SA data'!AC13-1)*100 -> 1.952047 | AC14: =('SA data'!AD17/'SA data'!AD13-1)*100 -> 2.2105074 | AD14: ='SA data'!AE17 -> 5.17 | AE14: =('SA data'!AF17/'SA data'!AF13-1)*100 -> 12.350975 | AF14: =('SA data'!AG17/'SA data'!AG13-1)*100 -> 9.0909091 | AP14: ='SA data'!AR17 -> 3.5766667 | AQ14: 15 | AR14: 34669
A15: =('SA data'!A18/'SA data'!A14-1)*100 -> 10.624567 | B15: =('SA data'!B18/'SA data'!B14-1)*100 -> 13.706958 | C15: =('SA data'!C18/'SA data'!C14-1)*100 -> -5.7893222 | D15: =('SA data'!D18/'SA data'!D14-1)*100 -> 35.967496 | E15: =('SA data'!E18/'SA data'!E14-1)*100 -> 18.649669 | F15: =('SA data'!F18/'SA data'!F14-1)*100 -> 22.933444 | G15: =('SA data'!G18/'SA data'!G14-1)*100 -> 10.135871 | H15: =('SA data'!H18/'SA data'!H14-1)*100 -> 7.3090922 | ... Q15: =('SA data'!Q18/'SA data'!Q14-1)*100 -> 7.2772175 | R15: =('SA data'!S18/'SA data'!S14-1)*100 -> 3.1249319 | S15: =('SA data'!T18/'SA data'!T14-1)*100 -> 2.5797589 | T15: =('SA data'!U18/'SA data'!U14-1)*100 -> 7.4143444 | U15: =('SA data'!V18/'SA data'!V14-1)*100 -> 1.8205462 | V15: =('SA data'!W18/'SA data'!W14-1)*100 -> 2.0895902 | W15: =('SA data'!X18/'SA data'!X14-1)*100 -> -2.2381866 | X15: ='SA data'!Y18 -> 5.0166667 | Y15: =('SA data'!Z18/'SA data'!Z14-1)*100 -> 2.3936491 | Z15: =('SA data'!AA18/'SA data'!AA14-1)*100 -> 10.759658 | AA15: =('SA data'!AB18/'SA data'!AB14-1)*100 -> 4.2005457 | AB15: =('SA data'!AC18/'SA data'!AC14-1)*100 -> 2.5879499 | AC15: =('SA data'!AD18/'SA data'!AD14-1)*100 -> 2.2825196 | AD15: ='SA data'!AE18 -> 5.8 | AE15: =('SA data'!AF18/'SA data'!AF14-1)*100 -> 14.930012 | AF15: =('SA data'!AG18/'SA data'!AG14-1)*100 -> 20.988539 | AP15: ='SA data'!AR18 -> 3.3333333 | AQ15: 16 | AR15: 34759
A16: =('SA data'!A19/'SA data'!A15-1)*100 -> 12.07873 | B16: =('SA data'!B19/'SA data'!B15-1)*100 -> 13.132597 | C16: =('SA data'!C19/'SA data'!C15-1)*100 -> 14.65077 | D16: =('SA data'!D19/'SA data'!D15-1)*100 -> 44.869988 | E16: =('SA data'!E19/'SA data'!E15-1)*100 -> 15.391073 | F16: =('SA data'!F19/'SA data'!F15-1)*100 -> 28.830489 | G16: =('SA data'!G19/'SA data'!G15-1)*100 -> 7.641342 | H16: =('SA data'!H19/'SA data'!H15-1)*100 -> 10.006519 | ... Q16: =('SA data'!Q19/'SA data'!Q15-1)*100 -> -1.8787018 | R16: =('SA data'!S19/'SA data'!S15-1)*100 -> 3.6497325 | S16: =('SA data'!T19/'SA data'!T15-1)*100 -> 2.7287979 | T16: =('SA data'!U19/'SA data'!U15-1)*100 -> 11.117513 | U16: =('SA data'!V19/'SA data'!V15-1)*100 -> 1.7467249 | V16: =('SA data'!W19/'SA data'!W15-1)*100 -> 2.8624133 | W16: =('SA data'!X19/'SA data'!X15-1)*100 -> 0.61336534 | X16: ='SA data'!Y19 -> 5.4733333 | Y16: =('SA data'!Z19/'SA data'!Z15-1)*100 -> -1.0058855 | Z16: =('SA data'!AA19/'SA data'!AA15-1)*100 -> 9.1723683 | AA16: =('SA data'!AB19/'SA data'!AB15-1)*100 -> 3.3833113 | AB16: =('SA data'!AC19/'SA data'!AC15-1)*100 -> 3.0031631 | AC16: =('SA data'!AD19/'SA data'!AD15-1)*100 -> 2.2021147 | AD16: ='SA data'!AE19 -> 6.02 | AE16: =('SA data'!AF19/'SA data'!AF15-1)*100 -> 11.408019 | AF16: =('SA data'!AG19/'SA data'!AG15-1)*100 -> 12.236025 | AP16: ='SA data'!AR19 -> 3.1766667 | AQ16: 17 | AR16: 34851
A17: =('SA data'!A20/'SA data'!A16-1)*100 -> 8.1708902 | B17: =('SA data'!B20/'SA data'!B16-1)*100 -> 9.1435608 | C17: =('SA data'!C20/'SA data'!C16-1)*100 -> 11.811143 | D17: =('SA data'!D20/'SA data'!D16-1)*100 -> -12.709118 | E17: =('SA data'!E20/'SA data'!E16-1)*100 -> 22.353077 | F17: =('SA data'!F20/'SA data'!F16-1)*100 -> 25.903749 | G17: =('SA data'!G20/'SA data'!G16-1)*100 -> 4.9593039 | H17: =('SA data'!H20/'SA data'!H16-1)*100 -> 9.6400331 | ... Q17: =('SA data'!Q20/'SA data'!Q16-1)*100 -> -8.0711664 | R17: =('SA data'!S20/'SA data'!S16-1)*100 -> 3.4740967 | S17: =('SA data'!T20/'SA data'!T16-1)*100 -> 2.572637 | T17: =('SA data'!U20/'SA data'!U16-1)*100 -> 10.527733 | U17: =('SA data'!V20/'SA data'!V16-1)*100 -> 1.754386 | V17: =('SA data'!W20/'SA data'!W16-1)*100 -> -0.79620634 | W17: =('SA data'!X20/'SA data'!X16-1)*100 -> -0.56419696 | X17: ='SA data'!Y20 -> 5.63 | Y17: =('SA data'!Z20/'SA data'!Z16-1)*100 -> 1.3106276 | Z17: =('SA data'!AA20/'SA data'!AA16-1)*100 -> 7.8741681 | AA17: =('SA data'!AB20/'SA data'!AB16-1)*100 -> 3.2336768 | AB17: =('SA data'!AC20/'SA data'!AC16-1)*100 -> 2.2746032 | AC17: =('SA data'!AD20/'SA data'!AD16-1)*100 -> 2.1191994 | AD17: ='SA data'!AE20 -> 5.8 | AE17: =('SA data'!AF20/'SA data'!AF16-1)*100 -> 4.7897122 | AF17: =('SA data'!AG20/'SA data'!AG16-1)*100 -> -3.3969011 | AP17: ='SA data'!AR20 -> 3.17 | AQ17: 18 | AR17: 34943
A18: =('SA data'!A21/'SA data'!A17-1)*100 -> 8.8412905 | B18: =('SA data'!B21/'SA data'!B17-1)*100 -> 10.404137 | C18: =('SA data'!C21/'SA data'!C17-1)*100 -> 2.7796455 | D18: =('SA data'!D21/'SA data'!D17-1)*100 -> 27.725661 | E18: =('SA data'!E21/'SA data'!E17-1)*100 -> 19.190829 | F18: =('SA data'!F21/'SA data'!F17-1)*100 -> 17.758488 | G18: =('SA data'!G21/'SA data'!G17-1)*100 -> 2.9722148 | H18: =('SA data'!H21/'SA data'!H17-1)*100 -> 7.7957699 | ... Q18: =('SA data'!Q21/'SA data'!Q17-1)*100 -> -24.908877 | R18: =('SA data'!S21/'SA data'!S17-1)*100 -> 3.2777341 | S18: =('SA data'!T21/'SA data'!T17-1)*100 -> 2.5475985 | T18: =('SA data'!U21/'SA data'!U17-1)*100 -> 8.8389183 | U18: =('SA data'!V21/'SA data'!V17-1)*100 -> 0 | V18: =('SA data'!W21/'SA data'!W17-1)*100 -> 0.1340532 | W18: =('SA data'!X21/'SA data'!X17-1)*100 -> -0.43763164 | X18: ='SA data'!Y21 -> 6.2766667 | Y18: =('SA data'!Z21/'SA data'!Z17-1)*100 -> 1.3004416 | Z18: =('SA data'!AA21/'SA data'!AA17-1)*100 -> 6.4648429 | AA18: =('SA data'!AB21/'SA data'!AB17-1)*100 -> 2.8972482 | AB18: =('SA data'!AC21/'SA data'!AC17-1)*100 -> 1.170598 | AC18: =('SA data'!AD21/'SA data'!AD17-1)*100 -> 2.1128824 | AD18: ='SA data'!AE21 -> 5.72 | AE18: =('SA data'!AF21/'SA data'!AF17-1)*100 -> 5.2834289 | AF18: =('SA data'!AG21/'SA data'!AG17-1)*100 -> 2.173913 | AP18: ='SA data'!AR21 -> 2.8533333 | AQ18: 19 | AR18: 35034
... A25: =('SA data'!A28/'SA data'!A24-1)*100 -> 7.4073517 | B25: =('SA data'!B28/'SA data'!B24-1)*100 -> 5.3539903 | C25: =('SA data'!C28/'SA data'!C24-1)*100 -> -7.1742214 | D25: =('SA data'!D28/'SA data'!D24-1)*100 -> 20.174448 | E25: =('SA data'!E28/'SA data'!E24-1)*100 -> 6.9464804 | F25: =('SA data'!F28/'SA data'!F24-1)*100 -> 7.1651731 | G25: =('SA data'!G28/'SA data'!G24-1)*100 -> 6.248734 | H25: =('SA data'!H28/'SA data'!H24-1)*100 -> 8.8781597 | ... Q25: =('SA data'!Q28/'SA data'!Q24-1)*100 -> 23.898008 | R25: =('SA data'!S28/'SA data'!S24-1)*100 -> 2.294189 | S25: =('SA data'!T28/'SA data'!T24-1)*100 -> 2.4258095 | T25: =('SA data'!U28/'SA data'!U24-1)*100 -> 1.3653452 | U25: =('SA data'!V28/'SA data'!V24-1)*100 -> 2.6431718 | V25: =('SA data'!W28/'SA data'!W24-1)*100 -> 7.2595684 | W25: =('SA data'!X28/'SA data'!X24-1)*100 -> 6.2984778 | X25: ='SA data'!Y28 -> 7.5613333 | Y25: =('SA data'!Z28/'SA data'!Z24-1)*100 -> -3.4143209 | Z25: =('SA data'!AA28/'SA data'!AA24-1)*100 -> 11.04772 | AA25: =('SA data'!AB28/'SA data'!AB24-1)*100 -> 4.2113733 | AB25: =('SA data'!AC28/'SA data'!AC24-1)*100 -> -1.6218308 | AC25: =('SA data'!AD28/'SA data'!AD24-1)*100 -> 1.7276293 | AD25: ='SA data'!AE28 -> 5.53 | AE25: =('SA data'!AF28/'SA data'!AF24-1)*100 -> -7.8145162 | AF25: =('SA data'!AG28/'SA data'!AG24-1)*100 -> -11.26558 | AP25: ='SA data'!AR28 -> 3.1786667 | AQ25: 26 | AR25: 35674
A26: =('SA data'!A29/'SA data'!A25-1)*100 -> 6.3489344 | B26: =('SA data'!B29/'SA data'!B25-1)*100 -> 0.061184077 | C26: =('SA data'!C29/'SA data'!C25-1)*100 -> 15.322839 | D26: =('SA data'!D29/'SA data'!D25-1)*100 -> 2.8097435 | E26: =('SA data'!E29/'SA data'!E25-1)*100 -> 5.2547978 | F26: =('SA data'!F29/'SA data'!F25-1)*100 -> -2.0933446 | G26: =('SA data'!G29/'SA data'!G25-1)*100 -> 11.176752 | H26: =('SA data'!H29/'SA data'!H25-1)*100 -> 8.0280555 | ... Q26: =('SA data'!Q29/'SA data'!Q25-1)*100 -> 6.3159983 | R26: =('SA data'!S29/'SA data'!S25-1)*100 -> 2.6892695 | S26: =('SA data'!T29/'SA data'!T25-1)*100 -> 2.4141284 | T26: =('SA data'!U29/'SA data'!U25-1)*100 -> 4.6327056 | U26: =('SA data'!V29/'SA data'!V25-1)*100 -> 2.6431718 | V26: =('SA data'!W29/'SA data'!W25-1)*100 -> 22.35081 | W26: =('SA data'!X29/'SA data'!X25-1)*100 -> 30.527262 | X26: ='SA data'!Y29 -> 7.4626667 | Y26: =('SA data'!Z29/'SA data'!Z25-1)*100 -> -19.062746 | Z26: =('SA data'!AA29/'SA data'!AA25-1)*100 -> 9.6445945 | AA26: =('SA data'!AB29/'SA data'!AB25-1)*100 -> 4.005612 | AB26: =('SA data'!AC29/'SA data'!AC25-1)*100 -> -1.0438512 | AC26: =('SA data'!AD29/'SA data'!AD25-1)*100 -> 1.4728453 | AD26: ='SA data'!AE29 -> 5.51 | AE26: =('SA data'!AF29/'SA data'!AF25-1)*100 -> -11.478381 | AF26: =('SA data'!AG29/'SA data'!AG25-1)*100 -> -20.441052 | AG26: =('SA data'!AI29/'SA data'!AI25-1)*100 -> 17.090972 | AH26: =('SA data'!AJ29/'SA data'!AJ25-1)*100 -> 23.37241 | AI26: =('SA data'!AK29/'SA data'!AK25-1)*100 -> 16.154797 | AJ26: =('SA data'!AL29/'SA data'!AL25-1)*100 -> 21.042538 | AK26: =('SA data'!AM29/'SA data'!AM25-1)*100 -> 32.262329 | AL26: =('SA data'!AN29/'SA data'!AN25-1)*100 -> 18.498647 | AM26: =('SA data'!AO29/'SA data'!AO25-1)*100 -> 76.712873 | AN26: =('SA data'!AP29/'SA data'!AP25-1)*100 -> 12.815551 | AO26: =('SA data'!AQ29/'SA data'!AQ25-1)*100 -> 49.406643 | AP26: ='SA data'!AR29 -> 3.634 | AQ26: 27 | AR26: 35765
A27: =('SA data'!A30/'SA data'!A26-1)*100 -> -1.7061147 | B27: =('SA data'!B30/'SA data'!B26-1)*100 -> -8.1707535 | C27: =('SA data'!C30/'SA data'!C26-1)*100 -> -5.4213949 | D27: =('SA data'!D30/'SA data'!D26-1)*100 -> -23.258384 | E27: =('SA data'!E30/'SA data'!E26-1)*100 -> -0.93989129 | F27: =('SA data'!F30/'SA data'!F26-1)*100 -> -9.4954557 | G27: =('SA data'!G30/'SA data'!G26-1)*100 -> 6.4440817 | H27: =('SA data'!H30/'SA data'!H26-1)*100 -> 5.7095414 | ... Q27: =('SA data'!Q30/'SA data'!Q26-1)*100 -> 3.7768439 | R27: =('SA data'!S30/'SA data'!S26-1)*100 -> 4.2264804 | S27: =('SA data'!T30/'SA data'!T26-1)*100 -> 3.7833971 | T27: =('SA data'!U30/'SA data'!U26-1)*100 -> 7.3919727 | U27: =('SA data'!V30/'SA data'!V26-1)*100 -> 2.6431718 | V27: =('SA data'!W30/'SA data'!W26-1)*100 -> 39.234257 | W27: =('SA data'!X30/'SA data'!X26-1)*100 -> 38.949122 | X27: ='SA data'!Y30 -> 9.9893333 | Y27: =('SA data'!Z30/'SA data'!Z26-1)*100 -> -28.266584 | Z27: =('SA data'!AA30/'SA data'!AA26-1)*100 -> 9.3055193 | AA27: =('SA data'!AB30/'SA data'!AB26-1)*100 -> 3.7355648 | AB27: =('SA data'!AC30/'SA data'!AC26-1)*100 -> -1.7609316 | AC27: =('SA data'!AD30/'SA data'!AD26-1)*100 -> 1.37311 | AD27: ='SA data'!AE30 -> 5.52 | AE27: =('SA data'!AF30/'SA data'!AF26-1)*100 -> -12.33839 | AF27: =('SA data'!AG30/'SA data'!AG26-1)*100 -> -33.553252 | AG27: =('SA data'!AI30/'SA data'!AI26-1)*100 -> 4.7854871 | AH27: =('SA data'!AJ30/'SA data'!AJ26-1)*100 -> 12.823515 | AI27: =('SA data'!AK30/'SA data'!AK26-1)*100 -> 3.6712362 | AJ27: =('SA data'!AL30/'SA data'!AL26-1)*100 -> 12.447571 | AK27: =('SA data'!AM30/'SA data'!AM26-1)*100 -> 4.7723422 | AL27: =('SA data'!AN30/'SA data'!AN26-1)*100 -> 2.2992957 | AM27: =('SA data'!AO30/'SA data'!AO26-1)*100 -> -3.1500333 | AN27: =('SA data'!AP30/'SA data'!AP26-1)*100 -> 3.0128232 | AO27: =('SA data'!AQ30/'SA data'!AQ26-1)*100 -> 16.067701 | AP27: ='SA data'!AR30 -> 2.554 | AQ27: 28 | AR27: 35855
A28: =('SA data'!A31/'SA data'!A27-1)*100 -> -6.069677 | B28: =('SA data'!B31/'SA data'!B27-1)*100 -> -9.931248 | C28: =('SA data'!C31/'SA data'!C27-1)*100 -> -3.4239369 | D28: =('SA data'!D31/'SA data'!D27-1)*100 -> -42.592417 | E28: =('SA data'!E31/'SA data'!E27-1)*100 -> 1.4524791 | F28: =('SA data'!F31/'SA data'!F27-1)*100 -> -24.872088 | G28: =('SA data'!G31/'SA data'!G27-1)*100 -> -8.8956008 | H28: =('SA data'!H31/'SA data'!H27-1)*100 -> 3.7438931 | ... Q28: =('SA data'!Q31/'SA data'!Q27-1)*100 -> -2.2577079 | R28: =('SA data'!S31/'SA data'!S27-1)*100 -> 5.7215502 | S28: =('SA data'!T31/'SA data'!T27-1)*100 -> 4.7282475 | T28: =('SA data'!U31/'SA data'!U27-1)*100 -> 12.991418 | U28: =('SA data'!V31/'SA data'!V27-1)*100 -> 0.86580087 | V28: =('SA data'!W31/'SA data'!W27-1)*100 -> 30.969507 | W28: =('SA data'!X31/'SA data'!X27-1)*100 -> 36.737564 | X28: ='SA data'!Y31 -> 10.065667 | Y28: =('SA data'!Z31/'SA data'!Z27-1)*100 -> -25.639659 | Z28: =('SA data'!AA31/'SA data'!AA27-1)*100 -> 6.4111463 | AA28: =('SA data'!AB31/'SA data'!AB27-1)*100 -> 3.3621027 | AB28: =('SA data'!AC31/'SA data'!AC27-1)*100 -> -2.2234376 | AC28: =('SA data'!AD31/'SA data'!AD27-1)*100 -> 1.1552951 | AD28: ='SA data'!AE31 -> 5.5 | AE28: =('SA data'!AF31/'SA data'!AF27-1)*100 -> -10.635992 | AF28: =('SA data'!AG31/'SA data'!AG27-1)*100 -> -26.260388 | AG28: =('SA data'!AI31/'SA data'!AI27-1)*100 -> -0.62855224 | AH28: =('SA data'!AJ31/'SA data'!AJ27-1)*100 -> -3.7596135 | AI28: =('SA data'!AK31/'SA data'!AK27-1)*100 -> -0.16317208 | AJ28: =('SA data'!AL31/'SA data'!AL27-1)*100 -> 17.707226 | AK28: =('SA data'!AM31/'SA data'!AM27-1)*100 -> -18.002805 | AL28: =('SA data'!AN31/'SA data'!AN27-1)*100 -> -22.538167 | AM28: =('SA data'!AO31/'SA data'!AO27-1)*100 -> -17.574768 | AN28: =('SA data'!AP31/'SA data'!AP27-1)*100 -> -3.7049099 | AO28: =('SA data'!AQ31/'SA data'!AQ27-1)*100 -> -6.1368933 | AP28: ='SA data'!AR31 -> 3.4476667 | AQ28: 29 | AR28: 35947
A29: =('SA data'!A32/'SA data'!A28-1)*100 -> -10.04061 | B29: =('SA data'!B32/'SA data'!B28-1)*100 -> -12.230671 | C29: =('SA data'!C32/'SA data'!C28-1)*100 -> 0.7312587 | D29: =('SA data'!D32/'SA data'!D28-1)*100 -> -56.27294 | E29: =('SA data'!E32/'SA data'!E28-1)*100 -> -2.2071401 | F29: =('SA data'!F32/'SA data'!F28-1)*100 -> -22.511923 | G29: =('SA data'!G32/'SA data'!G28-1)*100 -> -15.478098 | H29: =('SA data'!H32/'SA data'!H28-1)*100 -> 1.85507 | ... Q29: =('SA data'!Q32/'SA data'!Q28-1)*100 -> -10.322488 | R29: =('SA data'!S32/'SA data'!S28-1)*100 -> 5.7325653 | S29: =('SA data'!T32/'SA data'!T28-1)*100 -> 5.0947989 | T29: =('SA data'!U32/'SA data'!U28-1)*100 -> 10.280359 | U29: =('SA data'!V32/'SA data'!V28-1)*100 -> 0 | V29: =('SA data'!W32/'SA data'!W28-1)*100 -> 26.462145 | W29: =('SA data'!X32/'SA data'!X28-1)*100 -> 29.456405 | X29: ='SA data'!Y32 -> 8.461 | Y29: =('SA data'!Z32/'SA data'!Z28-1)*100 -> -21.954186 | Z29: =('SA data'!AA32/'SA data'!AA28-1)*100 -> 4.7197466 | AA29: =('SA data'!AB32/'SA data'!AB28-1)*100 -> 3.2165029 | AB29: =('SA data'!AC32/'SA data'!AC28-1)*100 -> -2.7774135 | AC29: =('SA data'!AD32/'SA data'!AD28-1)*100 -> 1.279285 | AD29: ='SA data'!AE32 -> 5.53 | AE29: =('SA data'!AF32/'SA data'!AF28-1)*100 -> -13.942052 | AF29: =('SA data'!AG32/'SA data'!AG28-1)*100 -> -32.685035 | AG29: =('SA data'!AI32/'SA data'!AI28-1)*100 -> -6.7205207 | AH29: =('SA data'!AJ32/'SA data'!AJ28-1)*100 -> -16.922417 | AI29: =('SA data'!AK32/'SA data'!AK28-1)*100 -> -5.1088184 | AJ29: =('SA data'!AL32/'SA data'!AL28-1)*100 -> 12.250283 | AK29: =('SA data'!AM32/'SA data'!AM28-1)*100 -> -28.544349 | AL29: =('SA data'!AN32/'SA data'!AN28-1)*100 -> -16.515656 | AM29: =('SA data'!AO32/'SA data'!AO28-1)*100 -> -41.169217 | AN29: =('SA data'!AP32/'SA data'!AP28-1)*100 -> -7.1915238 | AO29: =('SA data'!AQ32/'SA data'!AQ28-1)*100 -> -27.750551 | AP29: ='SA data'!AR32 -> 4.0956667 | AQ29: 30 | AR29: 36039
A30: =('SA data'!A33/'SA data'!A29-1)*100 -> -11.066201 | B30: =('SA data'!B33/'SA data'!B29-1)*100 -> -10.604132 | C30: =('SA data'!C33/'SA data'!C29-1)*100 -> -20.860445 | D30: =('SA data'!D33/'SA data'!D29-1)*100 -> -46.384727 | E30: =('SA data'!E33/'SA data'!E29-1)*100 -> 3.6798917 | F30: =('SA data'!F33/'SA data'!F29-1)*100 -> -17.100198 | G30: =('SA data'!G33/'SA data'!G29-1)*100 -> -21.595306 | H30: =('SA data'!H33/'SA data'!H29-1)*100 -> -0.093213984 | ... Q30: =('SA data'!Q33/'SA data'!Q29-1)*100 -> -12.657262 | R30: =('SA data'!S33/'SA data'!S29-1)*100 -> 5.3927816 | S30: =('SA data'!T33/'SA data'!T29-1)*100 -> 4.8210102 | T30: =('SA data'!U33/'SA data'!U29-1)*100 -> 9.3458062 | U30: =('SA data'!V33/'SA data'!V29-1)*100 -> 0 | V30: =('SA data'!W33/'SA data'!W29-1)*100 -> 5.2390704 | W30: =('SA data'!X33/'SA data'!X29-1)*100 -> 2.6477771 | X30: ='SA data'!Y33 -> 5.9446667 | Y30: =('SA data'!Z33/'SA data'!Z29-1)*100 -> -6.3607446 | Z30: =('SA data'!AA33/'SA data'!AA29-1)*100 -> 4.4784978 | AA30: =('SA data'!AB33/'SA data'!AB29-1)*100 -> 3.1928794 | AB30: =('SA data'!AC33/'SA data'!AC29-1)*100 -> -2.7167796 | AC30: =('SA data'!AD33/'SA data'!AD29-1)*100 -> 1.2807882 | AD30: ='SA data'!AE33 -> 4.86 | AE30: =('SA data'!AF33/'SA data'!AF29-1)*100 -> -15.02363 | AF30: =('SA data'!AG33/'SA data'!AG29-1)*100 -> -40.245203 | AG30: =('SA data'!AI33/'SA data'!AI29-1)*100 -> -4.2842132 | AH30: =('SA data'!AJ33/'SA data'!AJ29-1)*100 -> -13.666356 | AI30: =('SA data'!AK33/'SA data'!AK29-1)*100 -> -2.7990274 | AJ30: =('SA data'!AL33/'SA data'!AL29-1)*100 -> 3.6970944 | AK30: =('SA data'!AM33/'SA data'!AM29-1)*100 -> -23.083628 | AL30: =('SA data'!AN33/'SA data'!AN29-1)*100 -> -8.3015395 | AM30: =('SA data'!AO33/'SA data'!AO29-1)*100 -> -33.574818 | AN30: =('SA data'!AP33/'SA data'!AP29-1)*100 -> -2.8494978 | AO30: =('SA data'!AQ33/'SA data'!AQ29-1)*100 -> -30.520079 | AP30: ='SA data'!AR33 -> 4.0686667 | AQ30: 31 | AR30: 36130
A31: =('SA data'!A34/'SA data'!A30-1)*100 -> -1.150554 | B31: =('SA data'!B34/'SA data'!B30-1)*100 -> -1.911372 | C31: =('SA data'!C34/'SA data'!C30-1)*100 -> 10.594496 | D31: =('SA data'!D34/'SA data'!D30-1)*100 -> -24.333043 | E31: =('SA data'!E34/'SA data'!E30-1)*100 -> 2.0563926 | F31: =('SA data'!F34/'SA data'!F30-1)*100 -> -8.392432 | G31: =('SA data'!G34/'SA data'!G30-1)*100 -> -16.930119 | H31: =('SA data'!H34/'SA data'!H30-1)*100 -> 3.4918483 | ... Q31: =('SA data'!Q34/'SA data'!Q30-1)*100 -> -8.9992226 | R31: =('SA data'!S34/'SA data'!S30-1)*100 -> 4.0937678 | S31: =('SA data'!T34/'SA data'!T30-1)*100 -> 3.0247024 | T31: =('SA data'!U34/'SA data'!U30-1)*100 -> 11.474784 | U31: =('SA data'!V34/'SA data'!V30-1)*100 -> 0 | V31: =('SA data'!W34/'SA data'!W30-1)*100 -> -4.4395043 | W31: =('SA data'!X34/'SA data'!X30-1)*100 -> -2.2047163 | X31: ='SA data'!Y34 -> 5.2136667 | Y31: =('SA data'!Z34/'SA data'!Z30-1)*100 -> 1.8296565 | Z31: =('SA data'!AA34/'SA data'!AA30-1)*100 -> 3.2635425 | AA31: =('SA data'!AB34/'SA data'!AB30-1)*100 -> 3.4427202 | AB31: =('SA data'!AC34/'SA data'!AC30-1)*100 -> -1.9666659 | AC31: =('SA data'!AD34/'SA data'!AD30-1)*100 -> 1.236908 | AD31: ='SA data'!AE34 -> 4.73 | AE31: =('SA data'!AF34/'SA data'!AF30-1)*100 -> -14.432529 | AF31: =('SA data'!AG34/'SA data'!AG30-1)*100 -> -19.361702 | AG31: =('SA data'!AI34/'SA data'!AI30-1)*100 -> -0.026653945 | AH31: =('SA data'!AJ34/'SA data'!AJ30-1)*100 -> -5.1300657 | AI31: =('SA data'!AK34/'SA data'!AK30-1)*100 -> 0.74324801 | AJ31: =('SA data'!AL34/'SA data'!AL30-1)*100 -> 12.686338 | AK31: =('SA data'!AM34/'SA data'!AM30-1)*100 -> -2.0517912 | AL31: =('SA data'!AN34/'SA data'!AN30-1)*100 -> -5.5580515 | AM31: =('SA data'!AO34/'SA data'!AO30-1)*100 -> -11.723611 | AN31: =('SA data'!AP34/'SA data'!AP30-1)*100 -> 5.5459531 | AO31: =('SA data'!AQ34/'SA data'!AQ30-1)*100 -> -15.578171 | AP31: ='SA data'!AR34 -> 4.3663333 | AQ31: 32 | AR31: 36220
A32: =('SA data'!A35/'SA data'!A31-1)*100 -> 4.7625882 | B32: =('SA data'!B35/'SA data'!B31-1)*100 -> 1.298852 | C32: =('SA data'!C35/'SA data'!C31-1)*100 -> 4.0142657 | D32: =('SA data'!D35/'SA data'!D31-1)*100 -> -12.011546 | E32: =('SA data'!E35/'SA data'!E31-1)*100 -> 12.698389 | F32: =('SA data'!F35/'SA data'!F31-1)*100 -> 8.8898894 | G32: =('SA data'!G35/'SA data'!G31-1)*100 -> -3.4751495 | H32: =('SA data'!H35/'SA data'!H31-1)*100 -> 3.0242066 | ... Q32: =('SA data'!Q35/'SA data'!Q31-1)*100 -> -3.4386127 | R32: =('SA data'!S35/'SA data'!S31-1)*100 -> 2.6282206 | S32: =('SA data'!T35/'SA data'!T31-1)*100 -> 1.8950927 | T32: =('SA data'!U35/'SA data'!U31-1)*100 -> 7.601502 | U32: =('SA data'!V35/'SA data'!V31-1)*100 -> -0.31261591 | V32: =('SA data'!W35/'SA data'!W31-1)*100 -> -1.3415793 | W32: =('SA data'!X35/'SA data'!X31-1)*100 -> -1.875327 | X32: ='SA data'!Y35 -> 3.0656667 | Y32: =('SA data'!Z35/'SA data'!Z31-1)*100 -> -0.015753355 | Z32: =('SA data'!AA35/'SA data'!AA31-1)*100 -> 5.2249913 | AA32: =('SA data'!AB35/'SA data'!AB31-1)*100 -> 3.7243506 | AB32: =('SA data'!AC35/'SA data'!AC31-1)*100 -> -1.245227 | AC32: =('SA data'!AD35/'SA data'!AD31-1)*100 -> 1.278656 | AD32: ='SA data'!AE35 -> 4.75 | AE32: =('SA data'!AF35/'SA data'!AF31-1)*100 -> -5.2612985 | AF32: =('SA data'!AG35/'SA data'!AG31-1)*100 -> 16.303531 | AG32: =('SA data'!AI35/'SA data'!AI31-1)*100 -> -3.6649076 | AH32: =('SA data'!AJ35/'SA data'!AJ31-1)*100 -> -1.5499928 | AI32: =('SA data'!AK35/'SA data'!AK31-1)*100 -> -3.9679307 | AJ32: =('SA data'!AL35/'SA data'!AL31-1)*100 -> 7.7718582 | AK32: =('SA data'!AM35/'SA data'!AM31-1)*100 -> 8.7733213 | AL32: =('SA data'!AN35/'SA data'!AN31-1)*100 -> -4.2265108 | AM32: =('SA data'!AO35/'SA data'!AO31-1)*100 -> -11.047784 | AN32: =('SA data'!AP35/'SA data'!AP31-1)*100 -> 6.0058966 | AO32: =('SA data'!AQ35/'SA data'!AQ31-1)*100 -> -12.439406 | AP32: ='SA data'!AR35 -> 5.671 | AQ32: 33 | AR32: 36312
A33: =('SA data'!A36/'SA data'!A32-1)*100 -> 9.2801089 | B33: =('SA data'!B36/'SA data'!B32-1)*100 -> 4.5002871 | C33: =('SA data'!C36/'SA data'!C32-1)*100 -> 21.595637 | D33: =('SA data'!D36/'SA data'!D32-1)*100 -> 11.183402 | E33: =('SA data'!E36/'SA data'!E32-1)*100 -> 18.544888 | F33: =('SA data'!F36/'SA data'!F32-1)*100 -> 17.664186 | G33: =('SA data'!G36/'SA data'!G32-1)*100 -> 11.507203 | H33: =('SA data'!H36/'SA data'!H32-1)*100 -> 5.9527005 | ... Q33: =('SA data'!Q36/'SA data'!Q32-1)*100 -> -6.4060337 | R33: =('SA data'!S36/'SA data'!S32-1)*100 -> 2.3355651 | S33: =('SA data'!T36/'SA data'!T32-1)*100 -> 1.324673 | T33: =('SA data'!U36/'SA data'!U32-1)*100 -> 9.205095 | U33: =('SA data'!V36/'SA data'!V32-1)*100 -> 0 | V33: =('SA data'!W36/'SA data'!W32-1)*100 -> -2.4778581 | W33: =('SA data'!X36/'SA data'!X32-1)*100 -> -2.9545193 | X33: ='SA data'!Y36 -> 2.549 | Y33: =('SA data'!Z36/'SA data'!Z32-1)*100 -> 1.822318 | Z33: =('SA data'!AA36/'SA data'!AA32-1)*100 -> 7.2658099 | AA33: =('SA data'!AB36/'SA data'!AB32-1)*100 -> 4.2506478 | AB33: =('SA data'!AC36/'SA data'!AC32-1)*100 -> -0.30038867 | AC33: =('SA data'!AD36/'SA data'!AD32-1)*100 -> 1.2906152 | AD33: ='SA data'!AE36 -> 5.1 | AE33: =('SA data'!AF36/'SA data'!AF32-1)*100 -> 9.9806824 | AF33: =('SA data'!AG36/'SA data'!AG32-1)*100 -> 65.65008 | AG33: =('SA data'!AI36/'SA data'!AI32-1)*100 -> -3.855883 | AH33: =('SA data'!AJ36/'SA data'!AJ32-1)*100 -> 3.3730044 | AI33: =('SA data'!AK36/'SA data'!AK32-1)*100 -> -4.8557297 | AJ33: =('SA data'!AL36/'SA data'!AL32-1)*100 -> -8.3841105 | AK33: =('SA data'!AM36/'SA data'!AM32-1)*100 -> 22.662419 | AL33: =('SA data'!AN36/'SA data'!AN32-1)*100 -> 2.7237875 | AM33: =('SA data'!AO36/'SA data'!AO32-1)*100 -> 5.0740982 | AN33: =('SA data'!AP36/'SA data'!AP32-1)*100 -> 5.9340123 | AO33: =('SA data'!AQ36/'SA data'!AQ32-1)*100 -> -1.1704211 | AP33: ='SA data'!AR36 -> 5.5576667 | AQ33: 34 | AR33: 36404
